Workbook
Name Articulo: 'Listado de Artículos'!$B:$B
Name CCCC: '[1]Listado de Artículos'!$B$1:$B$65536
Name Descripción: #REF!
Name Excel_BuiltIn__FilterDatabase: 'Listado de Artículos'!$A$9:$I$1327

Sheet Listado de Artículos
A1: COCTEL | B1: A.AAAAA
A2: COCTEL | B2: A.AAAAA
B3: A.P AJO BLANCO, CON UVA Y SARDINAS.
A4: COCTEL | B4: A.P BASE DE AJO BLANCO PRECIO KG.
A5: COCTEL | B5: A.P BOMBON DE FOIE CON CONFITURA DE TOMATE Y PAN DE PASAS.
B6: A.P BRIOX DE CURRI, SECRETO A BAJA TEMPERATURA Y CEBOLLITA ENCURTIDA. | F6: 0.63
A7: Pau gavalda. | B7: A.P BROCHETA DE GAMBA XL, CON PANKO Y CHUTNEY DE MARACUYA. | F7: 1
A8: COCTEL | B8: A.P BROCHETA DE POLLO CON SALSA KARE. | D8: M.P APERITIVOS. | F8: 0.56
A9: COCTEL | B9: A.P BUFFET DE ARROCES Y FIDEUA. | D9: M.P APERITIVOS. | F9: 1.5
A10: COCTEL | B10: A.P BUFFET DE QUESOS. | D10: M.P APERITIVOS. | F10: 1.51
A11: COCTEL | B11: A.P BUÑUELO DE BACALAO. | D11: M.P APERITIVOS. | F11: 0.58
A12: COCTEL | B12: A.P CARAMELO DE CONFIT DE PATO CON MANZANA SALTEADA Y JENJIBRE. | D12: M.P APERITIVOS. | F12: 0.7
A13: COCTEL | B13: A.P CHUPITO DE AJO BLANCO DE COCO. | D13: M.P APERITIVOS. | F13: 3.68
A14: COCTEL | B14: A.P COCA DE TOMATE SECO, PUERRO CONFITADO Y PETA CRYSPI. | D14: M.P APERITIVOS. | F14: 0.41
A15: COCTEL | B15: A.P CREMA DE AJO BLANCO, SARDINA Y UVA. | D15: M.P APERITIVOS. | F15: 0.7
A16: COCTEL | B16: A.P CROQUETA DE TXULETA, BQT CASABLANCA. | D16: M.P APERITIVOS. | F16: 0.4
A17: COCTEL | B17: A.P CUCURUCHO DE ENSALADILLA CON CAMARONES CRUJIENTES. | D17: M.P APERITIVOS. | F17: 0.42
A18: COCTEL | B18: A.P DEGUSTACION DE ARROZ NEGRO. | D18: M.P APERITIVOS. | F18: 0.8
A19: COCTEL | B19: A.P DEGUSTACION DE CROQUETAS DE SETAS Y CHULETON. | D19: M.P APERITIVOS. | F19: 0.66
B20: A.P DEGUSTACION DE FIDEOS ROSSOS. | D20: M.P APERITIVOS. | F20: 0.65
A21: COCTEL | B21: A.P DUO DE CROQUETAS. | D21: M.P APERITIVOS. | F21: 0.66
A22: COCTEL | B22: A.P ENDIVIAS CON STEAK TARTAR DE SOLOMILLO Y MOSTAZA DE CERVEZA. | D22: M.P APERITIVOS. | F22: 1.05
A23: COCTEL | B23: A.P ESPUMA DE ALLIPEBRE CON PULPO. | D23: M.P APERITIVOS. | F23: 0.78
A24: COCTEL | B24: A.P GAZPACHO DE FRAMBUESA Y BITER KAS. | D24: M.P APERITIVOS. | F24: 0.18
A25: COCTEL | B25: A.P HUMUS CON MELON, MENTA Y PLATANO MACHO. | D25: M.P APERITIVOS. | F25: 0.16
A26: COCTEL | B26: A.P JAMON AL CENTRO EVENTOS SOCIALES. | D26: M.P APERITIVOS. | F26: 1.44
A27: COCTEL | B27: A.P JAMON IBERICO AL CORTE BODAS. | D27: M.P APERITIVOS. | F27: 1.91
A28: COCTEL | B28: A.P JAMON IBERICO Y BUFET DE SURTIDO DE IBERICOS. | D28: M.P APERITIVOS. | F28: 2.82
A29: COCTEL | B29: A.P MEJILLONES MYOGA. | D29: M.P APERITIVOS. | F29: 0.38
A30: COCTEL | B30: A.P MINI BURGUER DE PAN DE SESAMO. | D30: M.P APERITIVOS. | F30: 0.68
A31: COCTEL | B31: A.P MINI GOFRE CON SOBRASADA Y MIEL. | D31: M.P APERITIVOS. | F31: 0.54
A32: COCTEL | B32: A.P NINOYAKI DE ATUN. | D32: M.P APERITIVOS. | F32: 0.6
... A35: COCTEL | B35: A.P PATATAS BRAVAS CON SALSA PICANTE, BQT CASABLANCA. | D35: M.P APERITIVOS. | F35: 0.17
A36: COCTEL | B36: A.P SALMOREJO DE SANDIA. | D36: M.P APERITIVOS.
A37: COCTEL | B37: A.P SURTIDO DE IBERICOS. | D37: M.P APERITIVOS. | F37: 0.95
A38: COCTEL | B38: A.P TARTAR DE SALMON MARINADO. | D38: M.P APERITIVOS. | F38: 0.58
A39: Sarda | B39: ACEITE DE OLIVA SUAVE 5 LT | D39: SARDA | F39: 5.95
A40: Sarda | B40: ACEITE DE OLIVA VIRGEN EXTRA SALOMO . | D40: SARDA | F40: 8.97
A41: Disbesa. | B41: aceite de trufa 250ml. 3,55€ Botella | D41: SARDA | F41: 14.22
A42: Disbesa. | B42: ACEITE GIRASOL 5 LT. | D42: SARDA | F42: 1.65
A43: Disbesa. | B43: Agua con gas 1/3. 6,18€. 0,25€ unidad | D43: Disbesa. | F43: 0.25
A44: Disbesa. | B44: Agua Fon vella 1 LT Caja de 12 unid. | D44: Disbesa. | F44: 0.8
A45: ZAvicsa | B45: Agua Font Vella 1/3 caja de 24 unid. 24,05 | D45: Disbesa. | F45: 1
B46: Aguacate | D46: PAU GAVALDA | F46: 5.65
A47: Pau gavalda. | B47: Ají limo | D47: Pau GAVALDA | F47: 6
A48: ZAvicsa | B48: Ajo extra entero. makro | D48: PAU GAVALDA | F48: 3.68
A49: Disbesa. | B49: Ajo Pau Gavalda entero. | D49: PAU GAVALDA | F49: 6.8
A50: Disbesa. | B50: Ajo rojo extra a granel. | D50: PAU GAVALDA | F50: 2
A51: M.PCarnes bundo | B51: Ajo rojo pelado. pqt 1 kg. | D51: PAU GAVALDA | F51: 28.59
B52: Albahaca | D52: PAU GAVALDA | F52: 25.2
A53: M.PCarnes bundo | B53: Albahaca bandeja de 80 gr. 2,00€ | D53: PAU GAVALDA | F53: 3.5
A54: M.PCarnes bundo | B54: Albahaca. bandeja 125 gr. | D54: PAU GAVALDA | F54: 33333
A55: M.PCarnes bundo | B55: Alcachofas. | D55: PAU GAVALDA | F55: 12.5
A56: Sarda | B56: Alfiler | D56: SARDA | F56: 19.9
A57: M.PCarnes bundo | B57: Almendra tostada repelada | D57: SARDA | F57: 85.56
B58: Almodi petit blanc. | D58: bodega | F58: 85.55
A59: M.PCarnes bundo | B59: Ameja gallega G | D59: PESCADO JOPEP | F59: 55.87
A60: M.PCarnes bundo | B60: Anchoa D.Bocarte. Bandeja 115 gr- 9,84€ | D60: AVICSA | F60: 0.51
A61: Sarda | B61: Aperitivo en mesa. calçots en tempura con romesco al estilo mejicano de cacahuete. | D61: M.P APERITIVOS. | F61: 0.35
A62: M.PCarnes bundo | B62: Anchoa lata de 115 g. A. virgen. 8,55€ 100 gr. | D62: AVICSA | F62: 2.45
A63: M.PCarnes bundo | B63: Anchoa Noemar tarrina de 120 unid. 0,32€ unid. 38,87 bandeja de 700 gr. | D63: SARDA | F63: 0.44
A64: M.PCarnes bundo | B64: Aperitivo completo para calçotada. | D64: M.P APERITIVOS. | F64: 0.44
A65: Sarda | B65: Apionabo. makro | D65: PAU GAVALDA | F65: 13.2
A66: Sarda | B66: Aquarius Limon lata 33cl*24 | D66: Disbesa. | F66: 7.95
A67: Sarda | B67: Aquarius Naranja lata 33cl*24 | D67: Disbesa. | F67: 10.3
A68: Sarda | B68: Arandanos bandeja 125 gr. ( 1,65€) | D68: PAU GAVALDA | F68: 8.63
A69: Sarda | B69: Aros metalicos 6 moldes. | D69: MAKRO | F69: 21.9
A70: Sarda | B70: ATUN CLARO. OVIDIO. LATA 1 KG | D70: SARDA | F70: 18.99
... A73: Sarda | B73: Azafran /0,4 gr). pote. 2,09€- | D73: SARDA | F73: 0.01
B74: AZUCAR | D74: SARDA | F74: 0.82
B75: Azucar sobres. Caja 1000 unid. 18,03 | C75: EUROESTRELLA | D75: Disbesa. | F75: 0.76
B76: Barra 5 semillas. Masa madre 300 gr. | D76: ALVILARDAN | F76: 3.75
B77: Barra o Forno Galego 18*280 gr. 1 caja. (13,85€) unid. 0,76€ | D77: ALVILARDAN | F77: 3.75
B78: Bayas enebro | F78: 1.56
B79: Berengena | D79: PAU GAVALDA | F79: 2.5
B80: Biberon 3 unid. (4,69€. 15cl. 3 unid). | D80: MAKRO | F80: 0.9
B81: Boda entrante.carpaccio de gambon con aguachile de citricos, mayonesa de tamarindo y olivas de kalamata. | D81: M.P APERITIVOS. | F81: 0.54
B82: Boda pan unidad. | D82: M.P APERITIVOS. | F82: 6
B83: Boda Postre. Marquesa de mandarina con cava y menta. | D83: M.P APERITIVOS. | F83: 1.79
B84: Boda principal.Suquet de lomo de bacalao con achiote y patatas al azafran. | D84: M.P APERITIVOS. | F84: 8.83
B85: Boniato. kg | D85: PAU GAVALDA | F85: 8.55
B86: Botifarra blanca grande. | C86: BUNDO. | D86: BUNDO. | F86: 2.65
A87: Sarda | B87: Botifarra de cebolla. carnes palau. | D87: CARNES PALAU | F87: 2.18
A88: Sarda | B88: Butifarra fresca corta 14.cm. calçots. 90 gr porcianda | D88: BUNDO. | F88: 6.15
A89: Sarda | B89: Butifarra negra* calçotada racionada a 70 gr. | D89: BUNDO. | F89: 7.6
A90: Sarda | B90: Botifarra negra tombada. Carnes palau. | D90: CARNES PALAU. | F90: 5.95
A91: ZAvicsa | B91: Brocoli. | D91: PAU GAVALDA | F91: 0.42
B92: Burrata 6 uni | D92: Makro | F92: 0.42
A93: Sarda | B93: Butifarra sin cortar. | D93: BUNDO. | F93: 0.2
A94: Sarda | B94: Calabacin. makro. | D94: PAU GAVALDA | F94: 1.79
A95: Sarda | B95: Calabaza cacahuete. makro | D95: MAKRO.SARDA | F95: 1.05
A96: Sarda | B96: Calabaza dados 400 gr. | D96: PAU GAVALDA | F96: 3
A97: Sarda | B97: Calçots Valls. Cocinados. | D97: MAJOLS | F97: 0.26
A98: Sarda | B98: Calçots Valls. Majols. crudos | D98: MAJOLS | F98: 0.16
A99: Tot Selecte | B99: Callos blancos cort. ternera.. carnes palau. | D99: CARNES PALAU. | F99: 5.6
A100: Sarda | B100: Cafe descafeinado de capsula. 442,86€ caja de 100 unid. | D100: Disbesa. | F100: 10.76
A101: Sarda | B101: Cafe descafeinado de capsula. 442,86€ caja de 100 unid. | D101: Disbesa. | F101: 10.98
A102: Sarda | B102: Cafe Natural. 1 kg. 120 cafes. 24,48€ .kg. 0,22 unid | C102: EUROESTRELLA | D102: Disbesa. | F102: 0.65
A103: Vermouth Padro | B103: Cane de ñora " la legua". bote 650 gr. | D103: PAU GAVALDA | F103: 18.75
A104: Vermuth Padro. | B104: CANELA EN RAMA BOTE | D104: SARDA | F104: 5.73
...

Sheet M.P Menú finde 45€
C3: CALÇOTADA MAS BORONAT
C4: FICHA TÉCNICA PLATO
C7: ARTÍCULO | D7: Vermouth rojo con Gilda MasBoronat
C8: TAPA | D8: ELABORADOS.
C9: unid. | D9: 1 | E9: Coste TOTAL | G9: =SUM(K12:K14) -> 1.64975 | H9: Coste KG: | J9: =G9/D9 -> 1.64975
B11: ARTICULO | C11: KG | D11: €/UN | E11: BRUTO | F11: NETO | G11: %NETO | H11: %DESP | I11: DESP | J11: SUCIO | K11: € / RACION
B12: Mirrah. rojo 15% 5 l. 15,01€ precio backin box | C12: 0.1 | D12: =IF(ISNA(VLOOKUP(B12,'Listado de Artículos'!$B$16:$F$1328,5,0)),0,(VLOOKUP(B12,'Listado de Artículos'!$B$16:$F$1328,5,0))) -> 5.62 | E12: 1 | F12: 1 | G12: =IF(E12>0,(F12/E12),"") -> 1 | H12: =IF(E12>0,(100%-G12),"") -> 0 | I12: =IF(C12>0,(H12*C12/G12),"") -> 0 | J12: =IF(C12>0,(C12+I12),"") -> 0.1 | K12: =IF(D12>0,(D12*J12),"") -> 0.562
B13: Naranja extra de mesa. | C13: 0.005 | D13: =IF(ISNA(VLOOKUP(B13,'Listado de Artículos'!$B$16:$F$1328,5,0)),0,(VLOOKUP(B13,'Listado de Artículos'!$B$16:$F$1328,5,0))) -> 17.55 | E13: 1 | F13: 1 | G13: =IF(E13>0,(F13/E13),"") -> 1 | H13: =IF(E13>0,(100%-G13),"") -> 0 | I13: =IF(C13>0,(H13*C13/G13),"") -> 0 | J13: =IF(C13>0,(C13+I13),"") -> 0.005 | K13: =IF(D13>0,(D13*J13),"") -> 0.08775
B14: Gilda MasBoronat | C14: 1 | D14: =IF(ISNA(VLOOKUP(B14,'Listado de Artículos'!$B$16:$F$1328,5,0)),0,(VLOOKUP(B14,'Listado de Artículos'!$B$16:$F$1328,5,0))) -> 1 | E14: 1 | F14: 1 | G14: =IF(E14>0,(F14/E14),"") -> 1 | H14: =IF(E14>0,(100%-G14),"") -> 0 | I14: =IF(C14>0,(H14*C14/G14),"") -> 0 | J14: =IF(C14>0,(C14+I14),"") -> 1 | K14: =IF(D14>0,(D14*J14),"") -> 1
C17: CALÇOTADA MAS BORONAT
C18: FICHA TÉCNICA PLATO
C21: ARTÍCULO | D21: Ensaladilla de gamba
C22: TAPA | D22: ELABORADOS | H22: PRECIO DE VENTA P.V.P
C23: unid. | D23: 4 | E23: Coste TOTAL | G23: =SUM(K26:K33) -> 6.8215 | H23: Coste UNID: | J23: =G23/D23 -> 1.705375
B25: ARTICULO | C25: KG | D25: €/UN | E25: BRUTO | F25: NETO | G25: %NETO | H25: %DESP | I25: DESP | J25: SUCIO | K25: € / RACION
B26: Patata Monalisa. | C26: 0.3 | D26: =IF(ISNA(VLOOKUP(B26,'Listado de Artículos'!$B$16:$F$1328,5,0)),0,(VLOOKUP(B26,'Listado de Artículos'!$B$16:$F$1328,5,0))) -> 2 | E26: 1 | F26: 1 | G26: =IF(E26>0,(F26/E26),"") -> 1 | H26: =IF(E26>0,(100%-G26),"") -> 0 | I26: =IF(C26>0,(H26*C26/G26),"") -> 0 | J26: =IF(C26>0,(C26+I26),"") -> 0.3 | K26: =IF(D26>0,(D26*J26),"") -> 0.6
B27: Mayonesa 2,2kg | C27: 0.05 | D27: =IF(ISNA(VLOOKUP(B27,'Listado de Artículos'!$B$16:$F$1328,5,0)),0,(VLOOKUP(B27,'Listado de Artículos'!$B$16:$F$1328,5,0))) -> 16.72 | E27: 1 | F27: 1 | G27: =IF(E27>0,(F27/E27),"") -> 1 | H27: =IF(E27>0,(100%-G27),"") -> 0 | I27: =IF(C27>0,(H27*C27/G27),"") -> 0 | J27: =IF(C27>0,(C27+I27),"") -> 0.05 | K27: =IF(D27>0,(D27*J27),"") -> 0.836
B28: Gamba paella | C28: 0.19 | D28: =IF(ISNA(VLOOKUP(B28,'Listado de Artículos'!$B$16:$F$1328,5,0)),0,(VLOOKUP(B28,'Listado de Artículos'!$B$16:$F$1328,5,0))) -> 10.5 | E28: 1 | F28: 1 | G28: =IF(E28>0,(F28/E28),"") -> 1 | H28: =IF(E28>0,(100%-G28),"") -> 0 | I28: =IF(C28>0,(H28*C28/G28),"") -> 0 | J28: =IF(C28>0,(C28+I28),"") -> 0.19 | K28: =IF(D28>0,(D28*J28),"") -> 1.995
B29: Limones extra. | C29: 0.1 | D29: =IF(ISNA(VLOOKUP(B29,'Listado de Artículos'!$B$16:$F$1328,5,0)),0,(VLOOKUP(B29,'Listado de Artículos'!$B$16:$F$1328,5,0))) -> 1.38 | E29: 1 | F29: 1 | G29: =IF(E29>0,(F29/E29),"") -> 1 | H29: =IF(E29>0,(100%-G29),"") -> 0 | I29: =IF(C29>0,(H29*C29/G29),"") -> 0 | J29: =IF(C29>0,(C29+I29),"") -> 0.1 | K29: =IF(D29>0,(D29*J29),"") -> 0.138
B30: Zanahorias. | C30: 0.15 | D30: =IF(ISNA(VLOOKUP(B30,'Listado de Artículos'!$B$16:$F$1328,5,0)),0,(VLOOKUP(B30,'Listado de Artículos'!$B$16:$F$1328,5,0))) -> 4.25 | E30: 1 | F30: 1 | G30: =IF(E30>0,(F30/E30),"") -> 1 | H30: =IF(E30>0,(100%-G30),"") -> 0 | I30: =IF(C30>0,(H30*C30/G30),"") -> 0 | J30: =IF(C30>0,(C30+I30),"") -> 0.15 | K30: =IF(D30>0,(D30*J30),"") -> 0.6375
B31: Huevos "L" Granja Vidal, pqt de 6 unid: 1,60€ | C31: 1 | D31: =IF(ISNA(VLOOKUP(B31,'Listado de Artículos'!$B$16:$F$1328,5,0)),0,(VLOOKUP(B31,'Listado de Artículos'!$B$16:$F$1328,5,0))) -> 0.26 | E31: 1 | F31: 1 | G31: =IF(E31>0,(F31/E31),"") -> 1 | H31: =IF(E31>0,(100%-G31),"") -> 0 | I31: =IF(C31>0,(H31*C31/G31),"") -> 0 | J31: =IF(C31>0,(C31+I31),"") -> 1 | K31: =IF(D31>0,(D31*J31),"") -> 0.26
B32: OLIVAS PARTIDAS DE LA ABUELA LATA 2,5 KG. 9,95€ | C32: 0.05 | D32: =IF(ISNA(VLOOKUP(B32,'Listado de Artículos'!$B$16:$F$1328,5,0)),0,(VLOOKUP(B32,'Listado de Artículos'!$B$16:$F$1328,5,0))) -> 13 | E32: 1 | F32: 1 | G32: =IF(E32>0,(F32/E32),"") -> 1 | H32: =IF(E32>0,(100%-G32),"") -> 0 | I32: =IF(C32>0,(H32*C32/G32),"") -> 0 | J32: =IF(C32>0,(C32+I32),"") -> 0.05 | K32: =IF(D32>0,(D32*J32),"") -> 0.65
B33: Palitos pan | C33: 0.1 | D33: =IF(ISNA(VLOOKUP(B33,'Listado de Artículos'!$B$16:$F$1328,5,0)),0,(VLOOKUP(B33,'Listado de Artículos'!$B$16:$F$1328,5,0))) -> 17.05 | E33: 1 | F33: 1 | G33: =IF(E33>0,(F33/E33),"") -> 1 | H33: =IF(E33>0,(100%-G33),"") -> 0 | I33: =IF(C33>0,(H33*C33/G33),"") -> 0 | J33: =IF(C33>0,(C33+I33),"") -> 0.1 | K33: =IF(D33>0,(D33*J33),"") -> 1.705
C36: CALÇOTADA MAS BORONAT
C37: FICHA TÉCNICA PLATO
C40: ARTÍCULO | D40: Tartar de fuet con encurtidos
C41: TAPA | D41: ELABORADOS.
C42: unid. | D42: 4 | E42: Coste TOTAL | G42: =SUM(K45:K50) -> 5.18275 | H42: Coste UNID: | J42: =G42/D42 -> 1.2956875
B44: ARTICULO | C44: KG | D44: €/UN | E44: BRUTO | F44: NETO | G44: %NETO | H44: %DESP | I44: DESP | J44: SUCIO | K44: € / RACION
B45: Fuet tradicional precio kg* calçotada. | C45: 0.1 | D45: =IF(ISNA(VLOOKUP(B45,'Listado de Artículos'!$B$16:$F$1328,5,0)),0,(VLOOKUP(B45,'Listado de Artículos'!$B$16:$F$1328,5,0))) -> 11.5 | E45: 1 | F45: 1 | G45: =IF(E45>0,(F45/E45),"") -> 1 | H45: =IF(E45>0,(100%-G45),"") -> 0 | I45: =IF(C45>0,(H45*C45/G45),"") -> 0 | J45: =IF(C45>0,(C45+I45),"") -> 0.1 | K45: =IF(D45>0,(D45*J45),"") -> 1.15
B46: Encurtidos tartar | C46: 1 | D46: =IF(ISNA(VLOOKUP(B46,'Listado de Artículos'!$B$16:$F$1328,5,0)),0,(VLOOKUP(B46,'Listado de Artículos'!$B$16:$F$1328,5,0))) -> 0.2 | E46: 1 | F46: 1 | G46: =IF(E46>0,(F46/E46),"") -> 1 | H46: =IF(E46>0,(100%-G46),"") -> 0 | I46: =IF(C46>0,(H46*C46/G46),"") -> 0 | J46: =IF(C46>0,(C46+I46),"") -> 1 | K46: =IF(D46>0,(D46*J46),"") -> 0.2
B47: Huevos "L" Granja Vidal, pqt de 6 unid: 1,60€ | C47: 1 | D47: =IF(ISNA(VLOOKUP(B47,'Listado de Artículos'!$B$16:$F$1328,5,0)),0,(VLOOKUP(B47,'Listado de Artículos'!$B$16:$F$1328,5,0))) -> 0.26 | E47: 1 | F47: 1 | G47: =IF(E47>0,(F47/E47),"") -> 1 | H47: =IF(E47>0,(100%-G47),"") -> 0 | I47: =IF(C47>0,(H47*C47/G47),"") -> 0 | J47: =IF(C47>0,(C47+I47),"") -> 1 | K47: =IF(D47>0,(D47*J47),"") -> 0.26
B48: ACEITE DE OLIVA VIRGEN EXTRA SALOMO . | C48: 0.075 | D48: =IF(ISNA(VLOOKUP(B48,'Listado de Artículos'!$B$16:$F$1328,5,0)),0,(VLOOKUP(B48,'Listado de Artículos'!$B$16:$F$1328,5,0))) -> 8.97 | E48: 1 | F48: 1 | G48: =IF(E48>0,(F48/E48),"") -> 1 | H48: =IF(E48>0,(100%-G48),"") -> 0 | I48: =IF(C48>0,(H48*C48/G48),"") -> 0 | J48: =IF(C48>0,(C48+I48),"") -> 0.075 | K48: =IF(D48>0,(D48*J48),"") -> 0.67275
B49: Pan cristal precortado. (3,200 gr). 64 *50. 26,78€ Caja. 0,20€ medio trozo. | C49: 1 | D49: =IF(ISNA(VLOOKUP(B49,'Listado de Artículos'!$B$16:$F$1328,5,0)),0,(VLOOKUP(B49,'Listado de Artículos'!$B$16:$F$1328,5,0))) -> 2.9 | E49: 1 | F49: 1 | G49: =IF(E49>0,(F49/E49),"") -> 1 | H49: =IF(E49>0,(100%-G49),"") -> 0 | I49: =IF(C49>0,(H49*C49/G49),"") -> 0 | J49: =IF(C49>0,(C49+I49),"") -> 1 | K49: =IF(D49>0,(D49*J49),"") -> 2.9
C53: CALÇOTADA MAS BORONAT
C54: FICHA TÉCNICA PLATO
C57: ARTÍCULO | D57: Calçot en tempura y salsa romesco
C58: TAPA | D58: ELABORADOS.
C59: unid. | D59: 4 | E59: Coste TOTAL | G59: =SUM(K62:K67) -> 2.1878 | H59: PAX | J59: =G59/D59 -> 0.54695
B61: ARTICULO | C61: KG | D61: €/UN | E61: BRUTO | F61: NETO | G61: %NETO | H61: %DESP | I61: DESP | J61: SUCIO | K61: € / RACION
B62: Calçots Valls. Majols. crudos | C62: 10 | D62: =IF(ISNA(VLOOKUP(B62,'Listado de Artículos'!$B$16:$F$1328,5,0)),0,(VLOOKUP(B62,'Listado de Artículos'!$B$16:$F$1328,5,0))) -> 0.16 | E62: 1 | F62: 1 | G62: =IF(E62>0,(F62/E62),"") -> 1 | H62: =IF(E62>0,(100%-G62),"") -> 0 | I62: =IF(C62>0,(H62*C62/G62),"") -> 0 | J62: =IF(C62>0,(C62+I62),"") -> 10 | K62: =IF(D62>0,(D62*J62),"") -> 1.6
B63: Salsa romesco. | C63: 0.15 | D63: =IF(ISNA(VLOOKUP(B63,'Listado de Artículos'!$B$16:$F$1328,5,0)),0,(VLOOKUP(B63,'Listado de Artículos'!$B$16:$F$1328,5,0))) -> 2.94 | E63: 1 | F63: 1 | G63: =IF(E63>0,(F63/E63),"") -> 1 | H63: =IF(E63>0,(100%-G63),"") -> 0 | I63: =IF(C63>0,(H63*C63/G63),"") -> 0 | J63: =IF(C63>0,(C63+I63),"") -> 0.15 | K63: =IF(D63>0,(D63*J63),"") -> 0.441
B64: Sal negra en escamas. | C64: 0.01 | D64: =IF(ISNA(VLOOKUP(B64,'Listado de Artículos'!$B$16:$F$1328,5,0)),0,(VLOOKUP(B64,'Listado de Artículos'!$B$16:$F$1328,5,0))) -> 5.78 | E64: 1 | F64: 1 | G64: =IF(E64>0,(F64/E64),"") -> 1 | H64: =IF(E64>0,(100%-G64),"") -> 0 | I64: =IF(C64>0,(H64*C64/G64),"") -> 0 | J64: =IF(C64>0,(C64+I64),"") -> 0.01 | K64: =IF(D64>0,(D64*J64),"") -> 0.0578
B65: Harina TEmpura samlip 1 kg. | C65: 0.1 | D65: =IF(ISNA(VLOOKUP(B65,'Listado de Artículos'!$B$16:$F$1328,5,0)),0,(VLOOKUP(B65,'Listado de Artículos'!$B$16:$F$1328,5,0))) -> 0.89 | E65: 1 | F65: 1 | G65: =IF(E65>0,(F65/E65),"") -> 1 | H65: =IF(E65>0,(100%-G65),"") -> 0 | I65: =IF(C65>0,(H65*C65/G65),"") -> 0 | J65: =IF(C65>0,(C65+I65),"") -> 0.1 | K65: =IF(D65>0,(D65*J65),"") -> 0.089
C69: CALÇOTADA MAS BORONAT
C70: FICHA TÉCNICA PLATO
C73: ARTÍCULO | D73: Parrillada bbq fin de semana
C74: TAPA | D74: ELABORADOS.
C75: unid. | D75: 1 | E75: Coste TOTAL | G75: =SUM(K78:K83) -> 5.42026 | H75: PAX | J75: =G75/D75 -> 5.42026
B77: ARTICULO | C77: KG | D77: €/UN | E77: BRUTO | F77: NETO | G77: %NETO | H77: %DESP | I77: DESP | J77: SUCIO | K77: € / RACION
B78: Entraña de ternera. Carnes palau. | C78: 0.15 | D78: =IF(ISNA(VLOOKUP(B78,'Listado de Artículos'!$B$16:$F$1328,5,0)),0,(VLOOKUP(B78,'Listado de Artículos'!$B$16:$F$1328,5,0))) -> 21.9 | E78: 1 | F78: 1 | G78: =IF(E78>0,(F78/E78),"") -> 1 | H78: =IF(E78>0,(100%-G78),"") -> 0 | I78: =IF(C78>0,(H78*C78/G78),"") -> 0 | J78: =IF(C78>0,(C78+I78),"") -> 0.15 | K78: =IF(D78>0,(D78*J78),"") -> 3.285
B79: Butifarra fresca corta 14.cm. calçots. 90 gr porcianda | C79: 0.09 | D79: =IF(ISNA(VLOOKUP(B79,'Listado de Artículos'!$B$16:$F$1328,5,0)),0,(VLOOKUP(B79,'Listado de Artículos'!$B$16:$F$1328,5,0))) -> 6.15 | E79: 1 | F79: 1 | G79: =IF(E79>0,(F79/E79),"") -> 1 | H79: =IF(E79>0,(100%-G79),"") -> 0 | I79: =IF(C79>0,(H79*C79/G79),"") -> 0 | J79: =IF(C79>0,(C79+I79),"") -> 0.09 | K79: =IF(D79>0,(D79*J79),"") -> 0.5535
B80: Butifarra negra* calçotada racionada a 70 gr. | C80: 0.07 | D80: =IF(ISNA(VLOOKUP(B80,'Listado de Artículos'!$B$16:$F$1328,5,0)),0,(VLOOKUP(B80,'Listado de Artículos'!$B$16:$F$1328,5,0))) -> 7.6 | E80: 1 | F80: 1 | G80: =IF(E80>0,(F80/E80),"") -> 1 | H80: =IF(E80>0,(100%-G80),"") -> 0 | I80: =IF(C80>0,(H80*C80/G80),"") -> 0 | J80: =IF(C80>0,(C80+I80),"") -> 0.07 | K80: =IF(D80>0,(D80*J80),"") -> 0.532
B81: MENU CALÇOTADA GUARNICION DE CORDERO. | C81: 1 | D81: =IF(ISNA(VLOOKUP(B81,'Listado de Artículos'!$B$16:$F$1328,5,0)),0,(VLOOKUP(B81,'Listado de Artículos'!$B$16:$F$1328,5,0))) -> 0.96 | E81: 1 | F81: 1 | G81: =IF(E81>0,(F81/E81),"") -> 1 | H81: =IF(E81>0,(100%-G81),"") -> 0 | I81: =IF(C81>0,(H81*C81/G81),"") -> 0 | J81: =IF(C81>0,(C81+I81),"") -> 1 | K81: =IF(D81>0,(D81*J81),"") -> 0.96
B82: Pimienta negra molida. | C82: 0.002 | D82: =IF(ISNA(VLOOKUP(B82,'Listado de Artículos'!$B$16:$F$1328,5,0)),0,(VLOOKUP(B82,'Listado de Artículos'!$B$16:$F$1328,5,0))) -> 0.03 | E82: 1 | F82: 1 | G82: =IF(E82>0,(F82/E82),"") -> 1 | H82: =IF(E82>0,(100%-G82),"") -> 0 | I82: =IF(C82>0,(H82*C82/G82),"") -> 0 | J82: =IF(C82>0,(C82+I82),"") -> 0.002 | K82: =IF(D82>0,(D82*J82),"") -> 6e-05
B83: ACEITE DE OLIVA VIRGEN EXTRA SALOMO . | C83: 0.01 | D83: =IF(ISNA(VLOOKUP(B83,'Listado de Artículos'!$B$16:$F$1328,5,0)),0,(VLOOKUP(B83,'Listado de Artículos'!$B$16:$F$1328,5,0))) -> 8.97 | E83: 1 | F83: 1 | G83: =IF(E83>0,(F83/E83),"") -> 1 | H83: =IF(E83>0,(100%-G83),"") -> 0 | I83: =IF(C83>0,(H83*C83/G83),"") -> 0 | J83: =IF(C83>0,(C83+I83),"") -> 0.01 | K83: =IF(D83>0,(D83*J83),"") -> 0.0897
C85: CALÇOTADA MAS BORONAT
C86: FICHA TÉCNICA PLATO
C89: ARTÍCULO | D89: GUARNICION DE CALÇOTADA.
C90: TAPA | D90: ELABORADOS.
C91: unid. | D91: 1 | E91: Coste TOTAL | G91: =SUM(K94:K98) -> 2.87706 | H91: Coste pax | J91: =G91/D91 -> 2.87706
B93: ARTICULO | C93: KG | D93: €/UN | E93: BRUTO | F93: NETO | G93: %NETO | H93: %DESP | I93: DESP | J93: SUCIO | K93: € / RACION
B94: Patata Monalisa. | C94: 0.24 | D94: =IF(ISNA(VLOOKUP(B94,'Listado de Artículos'!$B$16:$F$1328,5,0)),0,(VLOOKUP(B94,'Listado de Artículos'!$B$16:$F$1328,5,0))) -> 2 | E94: 1 | F94: 1 | G94: =IF(E94>0,(F94/E94),"") -> 1 | H94: =IF(E94>0,(100%-G94),"") -> 0 | I94: =IF(C94>0,(H94*C94/G94),"") -> 0 | J94: =IF(C94>0,(C94+I94),"") -> 0.24 | K94: =IF(D94>0,(D94*J94),"") -> 0.48
B95: Alcachofas. | C95: 0.18 | D95: =IF(ISNA(VLOOKUP(B95,'Listado de Artículos'!$B$16:$F$1328,5,0)),0,(VLOOKUP(B95,'Listado de Artículos'!$B$16:$F$1328,5,0))) -> 12.5 | E95: 1 | F95: 1 | G95: =IF(E95>0,(F95/E95),"") -> 1 | H95: =IF(E95>0,(100%-G95),"") -> 0 | I95: =IF(C95>0,(H95*C95/G95),"") -> 0 | J95: =IF(C95>0,(C95+I95),"") -> 0.18 | K95: =IF(D95>0,(D95*J95),"") -> 2.25
B96: ACEITE DE OLIVA SUAVE 5 LT | C96: 0.02 | D96: =IF(ISNA(VLOOKUP(B96,'Listado de Artículos'!$B$16:$F$1328,5,0)),0,(VLOOKUP(B96,'Listado de Artículos'!$B$16:$F$1328,5,0))) -> 5.95 | E96: 1 | F96: 1 | G96: =IF(E96>0,(F96/E96),"") -> 1 | H96: =IF(E96>0,(100%-G96),"") -> 0 | I96: =IF(C96>0,(H96*C96/G96),"") -> 0 | J96: =IF(C96>0,(C96+I96),"") -> 0.02 | K96: =IF(D96>0,(D96*J96),"") -> 0.119
B97: Sal gruesa | C97: 0.008 | D97: =IF(ISNA(VLOOKUP(B97,'Listado de Artículos'!$B$16:$F$1328,5,0)),0,(VLOOKUP(B97,'Listado de Artículos'!$B$16:$F$1328,5,0))) -> 3.5 | E97: 1 | F97: 1 | G97: =IF(E97>0,(F97/E97),"") -> 1 | H97: =IF(E97>0,(100%-G97),"") -> 0 | I97: =IF(C97>0,(H97*C97/G97),"") -> 0 | J97: =IF(C97>0,(C97+I97),"") -> 0.008 | K97: =IF(D97>0,(D97*J97),"") -> 0.028
B98: Pimienta negra molida. | C98: 0.002 | D98: =IF(ISNA(VLOOKUP(B98,'Listado de Artículos'!$B$16:$F$1328,5,0)),0,(VLOOKUP(B98,'Listado de Artículos'!$B$16:$F$1328,5,0))) -> 0.03 | E98: 1 | F98: 1 | G98: =IF(E98>0,(F98/E98),"") -> 1 | H98: =IF(E98>0,(100%-G98),"") -> 0 | I98: =IF(C98>0,(H98*C98/G98),"") -> 0 | J98: =IF(C98>0,(C98+I98),"") -> 0.002 | K98: =IF(D98>0,(D98*J98),"") -> 6e-05
C100: CALÇOTADA MAS BORONAT
C101: FICHA TÉCNICA PLATO
C104: ARTÍCULO | D104: CORDERO y butifarra N CALÇOTADA
C105: TAPA | D105: ELABORADOS.
C106: unid. | D106: 1 | E106: Coste TOTAL | G106: =SUM(K109:K115) -> 2.8824 | H106: Coste pax | J106: =G106/D106 -> 2.8824
B108: ARTICULO | C108: KG | D108: €/UN | E108: BRUTO | F108: NETO | G108: %NETO | H108: %DESP | I108: DESP | J108: SUCIO | K108: € / RACION
B109: Butifarra negra* calçotada racionada a 70 gr. | C109: 0.07 | D109: =IF(ISNA(VLOOKUP(B109,'Listado de Artículos'!$B$16:$F$1328,5,0)),0,(VLOOKUP(B109,'Listado de Artículos'!$B$16:$F$1328,5,0))) -> 7.6 | E109: 1 | F109: 1 | G109: =IF(E109>0,(F109/E109),"") -> 1 | H109: =IF(E109>0,(100%-G109),"") -> 0 | I109: =IF(C109>0,(H109*C109/G109),"") -> 0 | J109: =IF(C109>0,(C109+I109),"") -> 0.07 | K109: =IF(D109>0,(D109*J109),"") -> 0.532
B110: Chuleta de corderdo para calçotada con riñonada. caja 3 kg | C110: 0.075 | D110: =IF(ISNA(VLOOKUP(B110,'Listado de Artículos'!$B$16:$F$1328,5,0)),0,(VLOOKUP(B110,'Listado de Artículos'!$B$16:$F$1328,5,0))) -> 12.5 | E110: 1 | F110: 1 | G110: =IF(E110>0,(F110/E110),"") -> 1 | H110: =IF(E110>0,(100%-G110),"") -> 0 | I110: =IF(C110>0,(H110*C110/G110),"") -> 0 | J110: =IF(C110>0,(C110+I110),"") -> 0.075 | K110: =IF(D110>0,(D110*J110),"") -> 0.9375 | L110: 2 chuletas
B111: Costilla cordero * calçotada. congelada caja 3 kg. | C111: 0.075 | D111: =IF(ISNA(VLOOKUP(B111,'Listado de Artículos'!$B$16:$F$1328,5,0)),0,(VLOOKUP(B111,'Listado de Artículos'!$B$16:$F$1328,5,0))) -> 16.398 | E111: 1 | F111: 1 | G111: =IF(E111>0,(F111/E111),"") -> 1 | H111: =IF(E111>0,(100%-G111),"") -> 0 | I111: =IF(C111>0,(H111*C111/G111),"") -> 0 | J111: =IF(C111>0,(C111+I111),"") -> 0.075 | K111: =IF(D111>0,(D111*J111),"") -> 1.22985 | L111: 1 costilla
B112: Sal gruesa | C112: 0.01 | D112: =IF(ISNA(VLOOKUP(B112,'Listado de Artículos'!$B$16:$F$1328,5,0)),0,(VLOOKUP(B112,'Listado de Artículos'!$B$16:$F$1328,5,0))) -> 3.5 | E112: 1 | F112: 1 | G112: =IF(E112>0,(F112/E112),"") -> 1 | H112: =IF(E112>0,(100%-G112),"") -> 0 | I112: =IF(C112>0,(H112*C112/G112),"") -> 0 | J112: =IF(C112>0,(C112+I112),"") -> 0.01 | K112: =IF(D112>0,(D112*J112),"") -> 0.035
B113: Pimienta negra molida. | C113: 0.005 | D113: =IF(ISNA(VLOOKUP(B113,'Listado de Artículos'!$B$16:$F$1328,5,0)),0,(VLOOKUP(B113,'Listado de Artículos'!$B$16:$F$1328,5,0))) -> 0.03 | E113: 1 | F113: 1 | G113: =IF(E113>0,(F113/E113),"") -> 1 | H113: =IF(E113>0,(100%-G113),"") -> 0 | I113: =IF(C113>0,(H113*C113/G113),"") -> 0 | J113: =IF(C113>0,(C113+I113),"") -> 0.005 | K113: =IF(D113>0,(D113*J113),"") -> 0.00015
B114: ACEITE DE OLIVA SUAVE 5 LT | C114: 0.02 | D114: =IF(ISNA(VLOOKUP(B114,'Listado de Artículos'!$B$16:$F$1328,5,0)),0,(VLOOKUP(B114,'Listado de Artículos'!$B$16:$F$1328,5,0))) -> 5.95 | E114: 1 | F114: 1 | G114: =IF(E114>0,(F114/E114),"") -> 1 | H114: =IF(E114>0,(100%-G114),"") -> 0 | I114: =IF(C114>0,(H114*C114/G114),"") -> 0 | J114: =IF(C114>0,(C114+I114),"") -> 0.02 | K114: =IF(D114>0,(D114*J114),"") -> 0.119
B115: Sal negra en escamas. | C115: 0.005 | D115: =IF(ISNA(VLOOKUP(B115,'Listado de Artículos'!$B$16:$F$1328,5,0)),0,(VLOOKUP(B115,'Listado de Artículos'!$B$16:$F$1328,5,0))) -> 5.78 | E115: 1 | F115: 1 | G115: =IF(E115>0,(F115/E115),"") -> 1 | H115: =IF(E115>0,(100%-G115),"") -> 0 | I115: =IF(C115>0,(H115*C115/G115),"") -> 0 | J115: =IF(C115>0,(C115+I115),"") -> 0.005 | K115: =IF(D115>0,(D115*J115),"") -> 0.0289
C118: CALÇOTADA MAS BORONAT
C119: FICHA TÉCNICA PLATO
C122: ARTÍCULO | D122: SALSA ROMESCO PARA CALÇOTS.
C123: TAPA | D123: ELABORADOS.
C124: KG | D124: 15 | E124: Coste TOTAL | G124: =SUM(K127:K138) -> 346.638 | H124: Coste KG | J124: =G124/D124 -> 23.1092
B126: ARTICULO | C126: KG | D126: €/UN | E126: BRUTO | F126: NETO | G126: %NETO | H126: %DESP | I126: DESP | J126: SUCIO | K126: € / RACION
B127: Tomate Maduro. | C127: 12 | D127: =IF(ISNA(VLOOKUP(B127,'Listado de Artículos'!$B$16:$F$1328,5,0)),0,(VLOOKUP(B127,'Listado de Artículos'!$B$16:$F$1328,5,0))) -> 13.9 | E127: 1 | F127: 1 | G127: =IF(E127>0,(F127/E127),"") -> 1 | H127: =IF(E127>0,(100%-G127),"") -> 0 | I127: =IF(C127>0,(H127*C127/G127),"") -> 0 | J127: =IF(C127>0,(C127+I127),"") -> 12 | K127: =IF(D127>0,(D127*J127),"") -> 166.8
B128: Ajo rojo extra a granel. | C128: 1.4 | D128: =IF(ISNA(VLOOKUP(B128,'Listado de Artículos'!$B$16:$F$1328,5,0)),0,(VLOOKUP(B128,'Listado de Artículos'!$B$16:$F$1328,5,0))) -> 2 | E128: 1 | F128: 1 | G128: =IF(E128>0,(F128/E128),"") -> 1 | H128: =IF(E128>0,(100%-G128),"") -> 0 | I128: =IF(C128>0,(H128*C128/G128),"") -> 0 | J128: =IF(C128>0,(C128+I128),"") -> 1.4 | K128: =IF(D128>0,(D128*J128),"") -> 2.8
B129: ACEITE DE OLIVA SUAVE 5 LT | C129: 3 | D129: =IF(ISNA(VLOOKUP(B129,'Listado de Artículos'!$B$16:$F$1328,5,0)),0,(VLOOKUP(B129,'Listado de Artículos'!$B$16:$F$1328,5,0))) -> 5.95 | E129: 1 | F129: 1 | G129: =IF(E129>0,(F129/E129),"") -> 1 | H129: =IF(E129>0,(100%-G129),"") -> 0 | I129: =IF(C129>0,(H129*C129/G129),"") -> 0 | J129: =IF(C129>0,(C129+I129),"") -> 3 | K129: =IF(D129>0,(D129*J129),"") -> 17.85
B130: ACEITE DE OLIVA VIRGEN EXTRA SALOMO . | C130: 3 | D130: =IF(ISNA(VLOOKUP(B130,'Listado de Artículos'!$B$16:$F$1328,5,0)),0,(VLOOKUP(B130,'Listado de Artículos'!$B$16:$F$1328,5,0))) -> 8.97 | E130: 1 | F130: 1 | G130: =IF(E130>0,(F130/E130),"") -> 1 | H130: =IF(E130>0,(100%-G130),"") -> 0 | I130: =IF(C130>0,(H130*C130/G130),"") -> 0 | J130: =IF(C130>0,(C130+I130),"") -> 3 | K130: =IF(D130>0,(D130*J130),"") -> 26.91
B131: Almendra tostada repelada | C131: 1.5 | D131: =IF(ISNA(VLOOKUP(B131,'Listado de Artículos'!$B$16:$F$1328,5,0)),0,(VLOOKUP(B131,'Listado de Artículos'!$B$16:$F$1328,5,0))) -> 85.56 | E131: 1 | F131: 1 | G131: =IF(E131>0,(F131/E131),"") -> 1 | H131: =IF(E131>0,(100%-G131),"") -> 0 | I131: =IF(C131>0,(H131*C131/G131),"") -> 0 | J131: =IF(C131>0,(C131+I131),"") -> 1.5 | K131: =IF(D131>0,(D131*J131),"") -> 128.34
B132: AVELLANA TOSTADA PELADA. | C132: 1.5 | D132: =IF(ISNA(VLOOKUP(B132,'Listado de Artículos'!$B$16:$F$1328,5,0)),0,(VLOOKUP(B132,'Listado de Artículos'!$B$16:$F$1328,5,0))) -> 1.15 | E132: 1 | F132: 1 | G132: =IF(E132>0,(F132/E132),"") -> 1 | H132: =IF(E132>0,(100%-G132),"") -> 0 | I132: =IF(C132>0,(H132*C132/G132),"") -> 0 | J132: =IF(C132>0,(C132+I132),"") -> 1.5 | K132: =IF(D132>0,(D132*J132),"") -> 1.725
B133: PIMENTON DULCE DE LA VERA | C133: 0.025 | D133: =IF(ISNA(VLOOKUP(B133,'Listado de Artículos'!$B$16:$F$1328,5,0)),0,(VLOOKUP(B133,'Listado de Artículos'!$B$16:$F$1328,5,0))) -> 23 | E133: 1 | F133: 1 | G133: =IF(E133>0,(F133/E133),"") -> 1 | H133: =IF(E133>0,(100%-G133),"") -> 0 | I133: =IF(C133>0,(H133*C133/G133),"") -> 0 | J133: =IF(C133>0,(C133+I133),"") -> 0.025 | K133: =IF(D133>0,(D133*J133),"") -> 0.575
B134: Vinagre de modena garrafa de 5 lt. | C134: 0.25 | D134: =IF(ISNA(VLOOKUP(B134,'Listado de Artículos'!$B$16:$F$1328,5,0)),0,(VLOOKUP(B134,'Listado de Artículos'!$B$16:$F$1328,5,0))) -> 1 | E134: 1 | F134: 1 | G134: =IF(E134>0,(F134/E134),"") -> 1 | H134: =IF(E134>0,(100%-G134),"") -> 0 | I134: =IF(C134>0,(H134*C134/G134),"") -> 0 | J134: =IF(C134>0,(C134+I134),"") -> 0.25 | K134: =IF(D134>0,(D134*J134),"") -> 0.25
B135: Vinagre de jerez | C135: 0.05 | D135: =IF(ISNA(VLOOKUP(B135,'Listado de Artículos'!$B$16:$F$1328,5,0)),0,(VLOOKUP(B135,'Listado de Artículos'!$B$16:$F$1328,5,0))) -> 4.5 | E135: 1 | F135: 1 | G135: =IF(E135>0,(F135/E135),"") -> 1 | H135: =IF(E135>0,(100%-G135),"") -> 0 | I135: =IF(C135>0,(H135*C135/G135),"") -> 0 | J135: =IF(C135>0,(C135+I135),"") -> 0.05 | K135: =IF(D135>0,(D135*J135),"") -> 0.225
B136: Cayena entera. | C136: 0.01 | D136: =IF(ISNA(VLOOKUP(B136,'Listado de Artículos'!$B$16:$F$1328,5,0)),0,(VLOOKUP(B136,'Listado de Artículos'!$B$16:$F$1328,5,0))) -> 1.55 | E136: 1 | F136: 1 | G136: =IF(E136>0,(F136/E136),"") -> 1 | H136: =IF(E136>0,(100%-G136),"") -> 0 | I136: =IF(C136>0,(H136*C136/G136),"") -> 0 | J136: =IF(C136>0,(C136+I136),"") -> 0.01 | K136: =IF(D136>0,(D136*J136),"") -> 0.0155
B137: Sal gruesa | C137: 0.06 | D137: =IF(ISNA(VLOOKUP(B137,'Listado de Artículos'!$B$16:$F$1328,5,0)),0,(VLOOKUP(B137,'Listado de Artículos'!$B$16:$F$1328,5,0))) -> 3.5 | E137: 1 | F137: 1 | G137: =IF(E137>0,(F137/E137),"") -> 1 | H137: =IF(E137>0,(100%-G137),"") -> 0 | I137: =IF(C137>0,(H137*C137/G137),"") -> 0 | J137: =IF(C137>0,(C137+I137),"") -> 0.06 | K137: =IF(D137>0,(D137*J137),"") -> 0.21
B138: Cane de ñora " la legua". bote 650 gr. | C138: 0.05 | D138: =IF(ISNA(VLOOKUP(B138,'Listado de Artículos'!$B$16:$F$1328,5,0)),0,(VLOOKUP(B138,'Listado de Artículos'!$B$16:$F$1328,5,0))) -> 18.75 | E138: 1 | F138: 1 | G138: =IF(E138>0,(F138/E138),"") -> 1 | H138: =IF(E138>0,(100%-G138),"") -> 0 | I138: =IF(C138>0,(H138*C138/G138),"") -> 0 | J138: =IF(C138>0,(C138+I138),"") -> 0.05 | K138: =IF(D138>0,(D138*J138),"") -> 0.9375
C140: CALÇOTADA MAS BORONAT
C141: FICHA TÉCNICA PLATO
...

Sheet Menú bbq finde 45€
A2: MENU BBQ FIN DE SEMANA 45€ CARTA. 01/04/2026
A4: APERITIVO. | B4: P.V.P | C4: NETO | D4: COSTO | E4: FOOD COST
A5: CALÇOTADA. APERITIVO CARTA | B5: GR O KG. | C5: PRECIO KG | D5: EUROS/RACION.
A6: Vermuth rojo con Gilda MasBoronat | B6: 1 | C6: =IF(ISNA(VLOOKUP(A6,'Listado de Artículos'!$B$16:$F$1328,5,0)),0,(VLOOKUP(A6,'Listado de Artículos'!$B$16:$F$1328,5,0))) -> 1.64975 | D6: =B6*C6 -> 1.64975
A7: Ensaladilla de Gamba | B7: 1 | C7: =IF(ISNA(VLOOKUP(A7,'Listado de Artículos'!$B$16:$F$1328,5,0)),0,(VLOOKUP(A7,'Listado de Artículos'!$B$16:$F$1328,5,0))) -> 1.705375 | D7: =B7*C7 -> 1.705375
A8: Tartar de fuet | B8: 1 | C8: =IF(ISNA(VLOOKUP(A8,'Listado de Artículos'!$B$16:$F$1328,5,0)),0,(VLOOKUP(A8,'Listado de Artículos'!$B$16:$F$1328,5,0))) -> 1.2956875 | D8: =B8*C8 -> 1.2956875
A9: Calçots en tempura!!! | B9: 1 | C9: =IF(ISNA(VLOOKUP(A9,'Listado de Artículos'!$B$16:$F$1328,5,0)),0,(VLOOKUP(A9,'Listado de Artículos'!$B$16:$F$1328,5,0))) -> 0.54695 | D9: =B9*C9 -> 0.54695
A10: EN MESA.
A11: Ensalada para calçotada terminada lechuga de pages. | B11: 1 | C11: =IF(ISNA(VLOOKUP(A11,'Listado de Artículos'!$B$16:$F$1328,5,0)),0,(VLOOKUP(A11,'Listado de Artículos'!$B$16:$F$1328,5,0))) -> 0.7 | D11: =B11*C11 -> 0.7
A12: MENU CALÇOTADA. CESTA DE PAN, TOMATE Y AJO. | B12: 1 | C12: =IF(ISNA(VLOOKUP(A12,'Listado de Artículos'!$B$16:$F$1328,5,0)),0,(VLOOKUP(A12,'Listado de Artículos'!$B$16:$F$1328,5,0))) -> 0.54 | D12: =B12*C12 -> 0.54
A13: Parrillada bbq fin de semana | B13: 1 | C13: =IF(ISNA(VLOOKUP(A13,'Listado de Artículos'!$B$16:$F$1328,5,0)),0,(VLOOKUP(A13,'Listado de Artículos'!$B$16:$F$1328,5,0))) -> 5.42026 | D13: =B13*C13 -> 5.42026
A14: Salsa Allioli. natural. bote de 1 lt. | B14: 0.03 | C14: =IF(ISNA(VLOOKUP(A14,'Listado de Artículos'!$B$16:$F$1328,5,0)),0,(VLOOKUP(A14,'Listado de Artículos'!$B$16:$F$1328,5,0))) -> 3.85 | D14: =B14*C14 -> 0.1155
A15: POSTRES
A16: Crema Catalana. | B16: 1 | C16: =IF(ISNA(VLOOKUP(A16,'Listado de Artículos'!$B$16:$F$1328,5,0)),0,(VLOOKUP(A16,'Listado de Artículos'!$B$16:$F$1328,5,0))) -> 0.5 | D16: =B16*C16 -> 0.5
A18: POSTRES
A19: CLOS PINELL TERRA TINTO ALTA | B19: 0.25 | C19: =IF(ISNA(VLOOKUP(A19,'Listado de Artículos'!$B$16:$F$1328,5,0)),0,(VLOOKUP(A19,'Listado de Artículos'!$B$16:$F$1328,5,0))) -> 0.9 | D19: =B19*C19 -> 0.225
A20: Agua Fon vella 1 LT Caja de 12 unid. | B20: 0.5 | C20: =IF(ISNA(VLOOKUP(A20,'Listado de Artículos'!$B$16:$F$1328,5,0)),0,(VLOOKUP(A20,'Listado de Artículos'!$B$16:$F$1328,5,0))) -> 0.8 | D20: =B20*C20 -> 0.4
A21: Cafe Natural. 1 kg. 120 cafes. 24,48€ .kg. 0,22 unid | B21: 1 | C21: =IF(ISNA(VLOOKUP(A21,'Listado de Artículos'!$B$16:$F$1328,5,0)),0,(VLOOKUP(A21,'Listado de Artículos'!$B$16:$F$1328,5,0))) -> 0.65 | D21: =B21*C21 -> 0.65
B22: 0.3 | C22: =IF(ISNA(VLOOKUP(A22,'Listado de Artículos'!$B$16:$F$1328,5,0)),0,(VLOOKUP(A22,'Listado de Artículos'!$B$16:$F$1328,5,0))) -> 0 | D22: =B22*C22 -> 0
A24: ESCANDALLO | B24: 46 | C24: =B24/1.1 -> 41.818182 | D24: =SUM(D6:D23) -> 13.748523 | E24: =(D24*100/C24)/100 -> 0.32876902

Sheet Menú paella finde 45€
A2: MENU BBQ 45€ CARTA. 01/04/2026
A4: APERITIVO. | B4: P.V.P | C4: NETO | D4: COSTO | E4: FOOD COST
A5: CALÇOTADA. APERITIVO CARTA | B5: GR O KG. | C5: PRECIO KG | D5: EUROS/RACION.
A6: Vermuth rojo con Gilda MasBoronat | B6: 1 | C6: =IF(ISNA(VLOOKUP(A6,'Listado de Artículos'!$B$16:$F$1328,5,0)),0,(VLOOKUP(A6,'Listado de Artículos'!$B$16:$F$1328,5,0))) -> 1.64975 | D6: =B6*C6 -> 1.64975
A7: Ensaladilla de Gamba | B7: 1 | C7: =IF(ISNA(VLOOKUP(A7,'Listado de Artículos'!$B$16:$F$1328,5,0)),0,(VLOOKUP(A7,'Listado de Artículos'!$B$16:$F$1328,5,0))) -> 1.705375 | D7: =B7*C7 -> 1.705375
A8: Tartar de fuet | B8: 1 | C8: =IF(ISNA(VLOOKUP(A8,'Listado de Artículos'!$B$16:$F$1328,5,0)),0,(VLOOKUP(A8,'Listado de Artículos'!$B$16:$F$1328,5,0))) -> 1.2956875 | D8: =B8*C8 -> 1.2956875
A9: Calçots en tempura!!! | B9: 1 | C9: =IF(ISNA(VLOOKUP(A9,'Listado de Artículos'!$B$16:$F$1328,5,0)),0,(VLOOKUP(A9,'Listado de Artículos'!$B$16:$F$1328,5,0))) -> 0.54695 | D9: =B9*C9 -> 0.54695
A10: EN MESA.
A11: Ensalada para calçotada terminada lechuga de pages. | B11: 1 | C11: =IF(ISNA(VLOOKUP(A11,'Listado de Artículos'!$B$16:$F$1328,5,0)),0,(VLOOKUP(A11,'Listado de Artículos'!$B$16:$F$1328,5,0))) -> 0.7 | D11: =B11*C11 -> 0.7
A12: MENU CALÇOTADA. CESTA DE PAN, TOMATE Y AJO. | B12: 1 | C12: =IF(ISNA(VLOOKUP(A12,'Listado de Artículos'!$B$16:$F$1328,5,0)),0,(VLOOKUP(A12,'Listado de Artículos'!$B$16:$F$1328,5,0))) -> 0.54 | D12: =B12*C12 -> 0.54
B13: 1 | C13: =IF(ISNA(VLOOKUP(A13,'Listado de Artículos'!$B$16:$F$1328,5,0)),0,(VLOOKUP(A13,'Listado de Artículos'!$B$16:$F$1328,5,0))) -> 0 | D13: 5.95
A14: Salsa Allioli. natural. bote de 1 lt. | B14: 0.03 | C14: =IF(ISNA(VLOOKUP(A14,'Listado de Artículos'!$B$16:$F$1328,5,0)),0,(VLOOKUP(A14,'Listado de Artículos'!$B$16:$F$1328,5,0))) -> 3.85 | D14: =B14*C14 -> 0.1155
A15: POSTRES
A16: Crema Catalana. | B16: 1 | C16: =IF(ISNA(VLOOKUP(A16,'Listado de Artículos'!$B$16:$F$1328,5,0)),0,(VLOOKUP(A16,'Listado de Artículos'!$B$16:$F$1328,5,0))) -> 0.5 | D16: =B16*C16 -> 0.5
A17: MENU CALÇOTADA NARANJA CON MIEL. POR PAX. | B17: 1 | C17: =IF(ISNA(VLOOKUP(A17,'Listado de Artículos'!$B$16:$F$1328,5,0)),0,(VLOOKUP(A17,'Listado de Artículos'!$B$16:$F$1328,5,0))) -> 0.37 | D17: =B17*C17 -> 0.37
A18: POSTRES
A19: CLOS PINELL TERRA TINTO ALTA | B19: 0.25 | C19: =IF(ISNA(VLOOKUP(A19,'Listado de Artículos'!$B$16:$F$1328,5,0)),0,(VLOOKUP(A19,'Listado de Artículos'!$B$16:$F$1328,5,0))) -> 0.9 | D19: =B19*C19 -> 0.225
B20: 0.15 | C20: =IF(ISNA(VLOOKUP(A20,'Listado de Artículos'!$B$16:$F$1328,5,0)),0,(VLOOKUP(A20,'Listado de Artículos'!$B$16:$F$1328,5,0))) -> 0 | D20: =B20*C20 -> 0
A21: Cafe Natural. 1 kg. 120 cafes. 24,48€ .kg. 0,22 unid | B21: 1 | C21: =IF(ISNA(VLOOKUP(A21,'Listado de Artículos'!$B$16:$F$1328,5,0)),0,(VLOOKUP(A21,'Listado de Artículos'!$B$16:$F$1328,5,0))) -> 0.65 | D21: =B21*C21 -> 0.65
B22: 0.3 | C22: =IF(ISNA(VLOOKUP(A22,'Listado de Artículos'!$B$16:$F$1328,5,0)),0,(VLOOKUP(A22,'Listado de Artículos'!$B$16:$F$1328,5,0))) -> 0 | D22: =B22*C22 -> 0
A24: ESCANDALLO | B24: 46 | C24: =B24/1.1 -> 41.818182 | D24: =SUM(D6:D23) -> 14.248263 | E24: =(D24*100/C24)/100 -> 0.34071932

Sheet M.P menú bbq 95€
C3: CALÇOTADA MAS BORONAT
C4: FICHA TÉCNICA PLATO
C7: ARTÍCULO | D7: Carpaccio de tomate con burrata i aceite albahaca
C8: TAPA | D8: ELABORADOS.
C9: unid. | D9: 12 | E9: Coste TOTAL | G9: =SUM(K12:K15) -> 1.9889 | H9: Coste KG: | J9: =G9/D9 -> 0.16574167
B11: ARTICULO | C11: KG | D11: €/UN | E11: BRUTO | F11: NETO | G11: %NETO | H11: %DESP | I11: DESP | J11: SUCIO | K11: € / RACION
B12: Tomate Cor de Bou. | C12: 0.2 | D12: =IF(ISNA(VLOOKUP(B12,'Listado de Artículos'!$B$16:$F$1328,5,0)),0,(VLOOKUP(B12,'Listado de Artículos'!$B$16:$F$1328,5,0))) -> 0 | E12: 1 | F12: 1 | G12: =IF(E12>0,(F12/E12),"") -> 1 | H12: =IF(E12>0,(100%-G12),"") -> 0 | I12: =IF(C12>0,(H12*C12/G12),"") -> 0 | J12: =IF(C12>0,(C12+I12),"") -> 0.2 | K12: =IF(D12>0,(D12*J12),"")
B13: Burrata 6 uni | C13: 0.5 | D13: =IF(ISNA(VLOOKUP(B13,'Listado de Artículos'!$B$16:$F$1328,5,0)),0,(VLOOKUP(B13,'Listado de Artículos'!$B$16:$F$1328,5,0))) -> 0.42 | E13: 1 | F13: 1 | G13: =IF(E13>0,(F13/E13),"") -> 1 | H13: =IF(E13>0,(100%-G13),"") -> 0 | I13: =IF(C13>0,(H13*C13/G13),"") -> 0 | J13: =IF(C13>0,(C13+I13),"") -> 0.5 | K13: =IF(D13>0,(D13*J13),"") -> 0.21
B14: Albahaca bandeja de 80 gr. 2,00€ | C14: 0.5 | D14: =IF(ISNA(VLOOKUP(B14,'Listado de Artículos'!$B$16:$F$1328,5,0)),0,(VLOOKUP(B14,'Listado de Artículos'!$B$16:$F$1328,5,0))) -> 3.5 | E14: 1 | F14: 1 | G14: =IF(E14>0,(F14/E14),"") -> 1 | H14: =IF(E14>0,(100%-G14),"") -> 0 | I14: =IF(C14>0,(H14*C14/G14),"") -> 0 | J14: =IF(C14>0,(C14+I14),"") -> 0.5 | K14: =IF(D14>0,(D14*J14),"") -> 1.75
B15: Sal negra en escamas. | C15: 0.005 | D15: =IF(ISNA(VLOOKUP(B15,'Listado de Artículos'!$B$16:$F$1328,5,0)),0,(VLOOKUP(B15,'Listado de Artículos'!$B$16:$F$1328,5,0))) -> 5.78 | E15: 1 | F15: 1 | G15: =IF(E15>0,(F15/E15),"") -> 1 | H15: =IF(E15>0,(100%-G15),"") -> 0 | I15: =IF(C15>0,(H15*C15/G15),"") -> 0 | J15: =IF(C15>0,(C15+I15),"") -> 0.005 | K15: =IF(D15>0,(D15*J15),"") -> 0.0289
C20: CALÇOTADA MAS BORONAT
C21: FICHA TÉCNICA PLATO
C24: ARTÍCULO | D24: Huevos rotos con jamón i foie
C25: TAPA | D25: ELABORADOS. | H25: COSTE UNID.
C26: PAX | D26: 1 | E26: Coste TOTAL | G26: =SUM(K29:K34) -> 2.0265 | H26: Coste unid: | J26: =G26/D26 -> 2.0265
B28: ARTICULO | C28: KG | D28: €/UN | E28: BRUTO | F28: NETO | G28: %NETO | H28: %DESP | I28: DESP | J28: SUCIO | K28: € / RACION
B29: Patata Monalisa. | C29: 0.2 | D29: =IF(ISNA(VLOOKUP(B29,'Listado de Artículos'!$B$16:$F$1328,5,0)),0,(VLOOKUP(B29,'Listado de Artículos'!$B$16:$F$1328,5,0))) -> 2 | E29: 1 | F29: 1 | G29: =IF(E29>0,(F29/E29),"") -> 1 | H29: =IF(E29>0,(100%-G29),"") -> 0 | I29: =IF(C29>0,(H29*C29/G29),"") -> 0 | J29: =IF(C29>0,(C29+I29),"") -> 0.2 | K29: =IF(D29>0,(D29*J29),"") -> 0.4
B30: Pimiento del padron. | C30: 0.1 | D30: =IF(ISNA(VLOOKUP(B30,'Listado de Artículos'!$B$16:$F$1328,5,0)),0,(VLOOKUP(B30,'Listado de Artículos'!$B$16:$F$1328,5,0))) -> 6.9 | E30: 1 | F30: 1 | G30: =IF(E30>0,(F30/E30),"") -> 1 | H30: =IF(E30>0,(100%-G30),"") -> 0 | I30: =IF(C30>0,(H30*C30/G30),"") -> 0 | J30: =IF(C30>0,(C30+I30),"") -> 0.1 | K30: =IF(D30>0,(D30*J30),"") -> 0.69
B31: Huevos "L" Granja Vidal, pqt de 6 unid: 1,60€ | C31: 2 | D31: =IF(ISNA(VLOOKUP(B31,'Listado de Artículos'!$B$16:$F$1328,5,0)),0,(VLOOKUP(B31,'Listado de Artículos'!$B$16:$F$1328,5,0))) -> 0.26 | E31: 1 | F31: 1 | G31: =IF(E31>0,(F31/E31),"") -> 1 | H31: =IF(E31>0,(100%-G31),"") -> 0 | I31: =IF(C31>0,(H31*C31/G31),"") -> 0 | J31: =IF(C31>0,(C31+I31),"") -> 2 | K31: =IF(D31>0,(D31*J31),"") -> 0.52
B32: Foie mi cuit 250g | C32: 0.02 | D32: =IF(ISNA(VLOOKUP(B32,'Listado de Artículos'!$B$16:$F$1328,5,0)),0,(VLOOKUP(B32,'Listado de Artículos'!$B$16:$F$1328,5,0))) -> 0.38 | E32: 1 | F32: 1 | G32: =IF(E32>0,(F32/E32),"") -> 1 | H32: =IF(E32>0,(100%-G32),"") -> 0 | I32: =IF(C32>0,(H32*C32/G32),"") -> 0 | J32: =IF(C32>0,(C32+I32),"") -> 0.02 | K32: =IF(D32>0,(D32*J32),"") -> 0.0076
B33: Sal negra en escamas. | C33: 0.005 | D33: =IF(ISNA(VLOOKUP(B33,'Listado de Artículos'!$B$16:$F$1328,5,0)),0,(VLOOKUP(B33,'Listado de Artículos'!$B$16:$F$1328,5,0))) -> 5.78 | E33: 1 | F33: 1 | G33: =IF(E33>0,(F33/E33),"") -> 1 | H33: =IF(E33>0,(100%-G33),"") -> 0 | I33: =IF(C33>0,(H33*C33/G33),"") -> 0 | J33: =IF(C33>0,(C33+I33),"") -> 0.005 | K33: =IF(D33>0,(D33*J33),"") -> 0.0289
B34: Paletilla jamón casa marcial | C34: 0.05 | D34: =IF(ISNA(VLOOKUP(B34,'Listado de Artículos'!$B$16:$F$1328,5,0)),0,(VLOOKUP(B34,'Listado de Artículos'!$B$16:$F$1328,5,0))) -> 7.6 | E34: 1 | F34: 1 | G34: =IF(E34>0,(F34/E34),"") -> 1 | H34: =IF(E34>0,(100%-G34),"") -> 0 | I34: =IF(C34>0,(H34*C34/G34),"") -> 0 | J34: =IF(C34>0,(C34+I34),"") -> 0.05 | K34: =IF(D34>0,(D34*J34),"") -> 0.38
C37: CALÇOTADA MAS BORONAT
C38: FICHA TÉCNICA PLATO
C41: ARTÍCULO | D41: Pulpo a la feira a la brasa
C42: TAPA | D42: ELABORADOS | H42: PRECIO DE VENTA P.V.P
C43: unid. | D43: 1 | E43: Coste TOTAL | G43: =SUM(K46:K52) -> 3.6789 | H43: Coste UNID: | J43: =G43/D43 -> 3.6789
B45: ARTICULO | C45: KG | D45: €/UN | E45: BRUTO | F45: NETO | G45: %NETO | H45: %DESP | I45: DESP | J45: SUCIO | K45: € / RACION
B46: Patata Monalisa. | C46: 0.1 | D46: =IF(ISNA(VLOOKUP(B46,'Listado de Artículos'!$B$16:$F$1328,5,0)),0,(VLOOKUP(B46,'Listado de Artículos'!$B$16:$F$1328,5,0))) -> 2 | E46: 1 | F46: 1 | G46: =IF(E46>0,(F46/E46),"") -> 1 | H46: =IF(E46>0,(100%-G46),"") -> 0 | I46: =IF(C46>0,(H46*C46/G46),"") -> 0 | J46: =IF(C46>0,(C46+I46),"") -> 0.1 | K46: =IF(D46>0,(D46*J46),"") -> 0.2
B47: Pata pulpo 250g | C47: 0.25 | D47: =IF(ISNA(VLOOKUP(B47,'Listado de Artículos'!$B$16:$F$1328,5,0)),0,(VLOOKUP(B47,'Listado de Artículos'!$B$16:$F$1328,5,0))) -> 10.5 | E47: 1 | F47: 1 | G47: =IF(E47>0,(F47/E47),"") -> 1 | H47: =IF(E47>0,(100%-G47),"") -> 0 | I47: =IF(C47>0,(H47*C47/G47),"") -> 0 | J47: =IF(C47>0,(C47+I47),"") -> 0.25 | K47: =IF(D47>0,(D47*J47),"") -> 2.625
B48: PIMENTON DULCE DE LA VERA | C48: 0.01 | D48: =IF(ISNA(VLOOKUP(B48,'Listado de Artículos'!$B$16:$F$1328,5,0)),0,(VLOOKUP(B48,'Listado de Artículos'!$B$16:$F$1328,5,0))) -> 23 | E48: 1 | F48: 1 | G48: =IF(E48>0,(F48/E48),"") -> 1 | H48: =IF(E48>0,(100%-G48),"") -> 0 | I48: =IF(C48>0,(H48*C48/G48),"") -> 0 | J48: =IF(C48>0,(C48+I48),"") -> 0.01 | K48: =IF(D48>0,(D48*J48),"") -> 0.23
B49: Sal negra en escamas. | C49: 0.005 | D49: =IF(ISNA(VLOOKUP(B49,'Listado de Artículos'!$B$16:$F$1328,5,0)),0,(VLOOKUP(B49,'Listado de Artículos'!$B$16:$F$1328,5,0))) -> 5.78 | E49: 1 | F49: 1 | G49: =IF(E49>0,(F49/E49),"") -> 1 | H49: =IF(E49>0,(100%-G49),"") -> 0 | I49: =IF(C49>0,(H49*C49/G49),"") -> 0 | J49: =IF(C49>0,(C49+I49),"") -> 0.005 | K49: =IF(D49>0,(D49*J49),"") -> 0.0289
B50: ACEITE DE OLIVA SUAVE 5 LT | C50: 0.1 | D50: =IF(ISNA(VLOOKUP(B50,'Listado de Artículos'!$B$16:$F$1328,5,0)),0,(VLOOKUP(B50,'Listado de Artículos'!$B$16:$F$1328,5,0))) -> 5.95 | E50: 1 | F50: 1 | G50: =IF(E50>0,(F50/E50),"") -> 1 | H50: =IF(E50>0,(100%-G50),"") -> 0 | I50: =IF(C50>0,(H50*C50/G50),"") -> 0 | J50: =IF(C50>0,(C50+I50),"") -> 0.1 | K50: =IF(D50>0,(D50*J50),"") -> 0.595
C55: CALÇOTADA MAS BORONAT
C56: FICHA TÉCNICA PLATO
C59: ARTÍCULO | D59: Chuleta lomo bajo con pimiento de piquillo y alcachofa
C60: TAPA | D60: ELABORADOS.
C61: unid. | D61: 1 | E61: Coste TOTAL | G61: =SUM(K64:K66) -> 15.2695 | H61: Coste UNID: | J61: =G61/D61 -> 15.2695
B63: ARTICULO | C63: KG | D63: €/UN | E63: BRUTO | F63: NETO | G63: %NETO | H63: %DESP | I63: DESP | J63: SUCIO | K63: € / RACION
B64: Chuleta lomo bajo 300-350g | C64: 1 | D64: 9.95 | E64: 1 | F64: 1 | G64: =IF(E64>0,(F64/E64),"") -> 1 | H64: =IF(E64>0,(100%-G64),"") -> 0 | I64: =IF(C64>0,(H64*C64/G64),"") -> 0 | J64: =IF(C64>0,(C64+I64),"") -> 1 | K64: =IF(D64>0,(D64*J64),"") -> 9.95
B65: PIMIENTO DE PIQUILLO LATA 1/2 KG. | C65: 0.15 | D65: =IF(ISNA(VLOOKUP(B65,'Listado de Artículos'!$B$16:$F$1328,5,0)),0,(VLOOKUP(B65,'Listado de Artículos'!$B$16:$F$1328,5,0))) -> 14.63 | E65: 1 | F65: 1 | G65: =IF(E65>0,(F65/E65),"") -> 1 | H65: =IF(E65>0,(100%-G65),"") -> 0 | I65: =IF(C65>0,(H65*C65/G65),"") -> 0 | J65: =IF(C65>0,(C65+I65),"") -> 0.15 | K65: =IF(D65>0,(D65*J65),"") -> 2.1945
B66: Alcachofas. | C66: 0.25 | D66: =IF(ISNA(VLOOKUP(B66,'Listado de Artículos'!$B$16:$F$1328,5,0)),0,(VLOOKUP(B66,'Listado de Artículos'!$B$16:$F$1328,5,0))) -> 12.5 | E66: 1 | F66: 1 | G66: =IF(E66>0,(F66/E66),"") -> 1 | H66: =IF(E66>0,(100%-G66),"") -> 0 | I66: =IF(C66>0,(H66*C66/G66),"") -> 0 | J66: =IF(C66>0,(C66+I66),"") -> 0.25 | K66: =IF(D66>0,(D66*J66),"") -> 3.125
C69: CALÇOTADA MAS BORONAT
C70: FICHA TÉCNICA PLATO
C73: ARTÍCULO | D73: Botifarra con mongetes del ganxet.
C74: TAPA | D74: ELABORADOS.
C75: unid. | D75: 1 | E75: Coste TOTAL | G75: =SUM(K78:K83) -> 0.92836 | H75: PAX | J75: =G75/D75 -> 0.92836
B77: ARTICULO | C77: KG | D77: €/UN | E77: BRUTO | F77: NETO | G77: %NETO | H77: %DESP | I77: DESP | J77: SUCIO | K77: € / RACION
B78: Mongetes del ganxet. lata de 3 kg-17,22€ | C78: 0.1 | D78: =IF(ISNA(VLOOKUP(B78,'Listado de Artículos'!$B$16:$F$1328,5,0)),0,(VLOOKUP(B78,'Listado de Artículos'!$B$16:$F$1328,5,0))) -> 0.2 | E78: 1 | F78: 1 | G78: =IF(E78>0,(F78/E78),"") -> 1 | H78: =IF(E78>0,(100%-G78),"") -> 0 | I78: =IF(C78>0,(H78*C78/G78),"") -> 0 | J78: =IF(C78>0,(C78+I78),"") -> 0.1 | K78: =IF(D78>0,(D78*J78),"") -> 0.02
B79: Butifarra fresca corta 14.cm. calçots. 90 gr porcianda | C79: 0.09 | D79: =IF(ISNA(VLOOKUP(B79,'Listado de Artículos'!$B$16:$F$1328,5,0)),0,(VLOOKUP(B79,'Listado de Artículos'!$B$16:$F$1328,5,0))) -> 6.15 | E79: 1 | F79: 1 | G79: =IF(E79>0,(F79/E79),"") -> 1 | H79: =IF(E79>0,(100%-G79),"") -> 0 | I79: =IF(C79>0,(H79*C79/G79),"") -> 0 | J79: =IF(C79>0,(C79+I79),"") -> 0.09 | K79: =IF(D79>0,(D79*J79),"") -> 0.5535
B80: Picada de ajo y perejil. | C80: 0.01 | D80: =IF(ISNA(VLOOKUP(B80,'Listado de Artículos'!$B$16:$F$1328,5,0)),0,(VLOOKUP(B80,'Listado de Artículos'!$B$16:$F$1328,5,0))) -> 23.71 | E80: 1 | F80: 1 | G80: =IF(E80>0,(F80/E80),"") -> 1 | H80: =IF(E80>0,(100%-G80),"") -> 0 | I80: =IF(C80>0,(H80*C80/G80),"") -> 0 | J80: =IF(C80>0,(C80+I80),"") -> 0.01 | K80: =IF(D80>0,(D80*J80),"") -> 0.2371
B81: Sal gruesa | C81: 0.008 | D81: =IF(ISNA(VLOOKUP(B81,'Listado de Artículos'!$B$16:$F$1328,5,0)),0,(VLOOKUP(B81,'Listado de Artículos'!$B$16:$F$1328,5,0))) -> 3.5 | E81: 1 | F81: 1 | G81: =IF(E81>0,(F81/E81),"") -> 1 | H81: =IF(E81>0,(100%-G81),"") -> 0 | I81: =IF(C81>0,(H81*C81/G81),"") -> 0 | J81: =IF(C81>0,(C81+I81),"") -> 0.008 | K81: =IF(D81>0,(D81*J81),"") -> 0.028
B82: Pimienta negra molida. | C82: 0.002 | D82: =IF(ISNA(VLOOKUP(B82,'Listado de Artículos'!$B$16:$F$1328,5,0)),0,(VLOOKUP(B82,'Listado de Artículos'!$B$16:$F$1328,5,0))) -> 0.03 | E82: 1 | F82: 1 | G82: =IF(E82>0,(F82/E82),"") -> 1 | H82: =IF(E82>0,(100%-G82),"") -> 0 | I82: =IF(C82>0,(H82*C82/G82),"") -> 0 | J82: =IF(C82>0,(C82+I82),"") -> 0.002 | K82: =IF(D82>0,(D82*J82),"") -> 6e-05
B83: ACEITE DE OLIVA VIRGEN EXTRA SALOMO . | C83: 0.01 | D83: =IF(ISNA(VLOOKUP(B83,'Listado de Artículos'!$B$16:$F$1328,5,0)),0,(VLOOKUP(B83,'Listado de Artículos'!$B$16:$F$1328,5,0))) -> 8.97 | E83: 1 | F83: 1 | G83: =IF(E83>0,(F83/E83),"") -> 1 | H83: =IF(E83>0,(100%-G83),"") -> 0 | I83: =IF(C83>0,(H83*C83/G83),"") -> 0 | J83: =IF(C83>0,(C83+I83),"") -> 0.01 | K83: =IF(D83>0,(D83*J83),"") -> 0.0897
C85: CALÇOTADA MAS BORONAT
C86: FICHA TÉCNICA PLATO
C89: ARTÍCULO | D89: Botifarra con mongetes del ganxet.
C90: TAPA | D90: ELABORADOS.
C91: unid. | D91: 1 | E91: Coste TOTAL | G91: =SUM(K94:K99) -> 3.80336 | H91: PAX | J91: =G91/D91 -> 3.80336
B93: ARTICULO | C93: KG | D93: €/UN | E93: BRUTO | F93: NETO | G93: %NETO | H93: %DESP | I93: DESP | J93: SUCIO | K93: € / RACION
B94: MONGETAS NATURALES. 3 KG( 2,89€ LATA DE 3 KG). | C94: 0.1 | D94: =IF(ISNA(VLOOKUP(B94,'Listado de Artículos'!$B$16:$F$1328,5,0)),0,(VLOOKUP(B94,'Listado de Artículos'!$B$16:$F$1328,5,0))) -> 28.95 | E94: 1 | F94: 1 | G94: =IF(E94>0,(F94/E94),"") -> 1 | H94: =IF(E94>0,(100%-G94),"") -> 0 | I94: =IF(C94>0,(H94*C94/G94),"") -> 0 | J94: =IF(C94>0,(C94+I94),"") -> 0.1 | K94: =IF(D94>0,(D94*J94),"") -> 2.895
B95: Butifarra fresca corta 14.cm. calçots. 90 gr porcianda | C95: 0.09 | D95: =IF(ISNA(VLOOKUP(B95,'Listado de Artículos'!$B$16:$F$1328,5,0)),0,(VLOOKUP(B95,'Listado de Artículos'!$B$16:$F$1328,5,0))) -> 6.15 | E95: 1 | F95: 1 | G95: =IF(E95>0,(F95/E95),"") -> 1 | H95: =IF(E95>0,(100%-G95),"") -> 0 | I95: =IF(C95>0,(H95*C95/G95),"") -> 0 | J95: =IF(C95>0,(C95+I95),"") -> 0.09 | K95: =IF(D95>0,(D95*J95),"") -> 0.5535
B96: Picada de ajo y perejil. | C96: 0.01 | D96: =IF(ISNA(VLOOKUP(B96,'Listado de Artículos'!$B$16:$F$1328,5,0)),0,(VLOOKUP(B96,'Listado de Artículos'!$B$16:$F$1328,5,0))) -> 23.71 | E96: 1 | F96: 1 | G96: =IF(E96>0,(F96/E96),"") -> 1 | H96: =IF(E96>0,(100%-G96),"") -> 0 | I96: =IF(C96>0,(H96*C96/G96),"") -> 0 | J96: =IF(C96>0,(C96+I96),"") -> 0.01 | K96: =IF(D96>0,(D96*J96),"") -> 0.2371
B97: Sal gruesa | C97: 0.008 | D97: =IF(ISNA(VLOOKUP(B97,'Listado de Artículos'!$B$16:$F$1328,5,0)),0,(VLOOKUP(B97,'Listado de Artículos'!$B$16:$F$1328,5,0))) -> 3.5 | E97: 1 | F97: 1 | G97: =IF(E97>0,(F97/E97),"") -> 1 | H97: =IF(E97>0,(100%-G97),"") -> 0 | I97: =IF(C97>0,(H97*C97/G97),"") -> 0 | J97: =IF(C97>0,(C97+I97),"") -> 0.008 | K97: =IF(D97>0,(D97*J97),"") -> 0.028
B98: Pimienta negra molida. | C98: 0.002 | D98: =IF(ISNA(VLOOKUP(B98,'Listado de Artículos'!$B$16:$F$1328,5,0)),0,(VLOOKUP(B98,'Listado de Artículos'!$B$16:$F$1328,5,0))) -> 0.03 | E98: 1 | F98: 1 | G98: =IF(E98>0,(F98/E98),"") -> 1 | H98: =IF(E98>0,(100%-G98),"") -> 0 | I98: =IF(C98>0,(H98*C98/G98),"") -> 0 | J98: =IF(C98>0,(C98+I98),"") -> 0.002 | K98: =IF(D98>0,(D98*J98),"") -> 6e-05
B99: ACEITE DE OLIVA VIRGEN EXTRA SALOMO . | C99: 0.01 | D99: =IF(ISNA(VLOOKUP(B99,'Listado de Artículos'!$B$16:$F$1328,5,0)),0,(VLOOKUP(B99,'Listado de Artículos'!$B$16:$F$1328,5,0))) -> 8.97 | E99: 1 | F99: 1 | G99: =IF(E99>0,(F99/E99),"") -> 1 | H99: =IF(E99>0,(100%-G99),"") -> 0 | I99: =IF(C99>0,(H99*C99/G99),"") -> 0 | J99: =IF(C99>0,(C99+I99),"") -> 0.01 | K99: =IF(D99>0,(D99*J99),"") -> 0.0897
C101: CALÇOTADA MAS BORONAT
C102: FICHA TÉCNICA PLATO
C105: ARTÍCULO | D105: GUARNICION DE CALÇOTADA.
C106: TAPA | D106: ELABORADOS.
C107: unid. | D107: 1 | E107: Coste TOTAL | G107: =SUM(K110:K114) -> 2.87706 | H107: Coste pax | J107: =G107/D107 -> 2.87706
B109: ARTICULO | C109: KG | D109: €/UN | E109: BRUTO | F109: NETO | G109: %NETO | H109: %DESP | I109: DESP | J109: SUCIO | K109: € / RACION
B110: Patata Monalisa. | C110: 0.24 | D110: =IF(ISNA(VLOOKUP(B110,'Listado de Artículos'!$B$16:$F$1328,5,0)),0,(VLOOKUP(B110,'Listado de Artículos'!$B$16:$F$1328,5,0))) -> 2 | E110: 1 | F110: 1 | G110: =IF(E110>0,(F110/E110),"") -> 1 | H110: =IF(E110>0,(100%-G110),"") -> 0 | I110: =IF(C110>0,(H110*C110/G110),"") -> 0 | J110: =IF(C110>0,(C110+I110),"") -> 0.24 | K110: =IF(D110>0,(D110*J110),"") -> 0.48
B111: Alcachofas. | C111: 0.18 | D111: =IF(ISNA(VLOOKUP(B111,'Listado de Artículos'!$B$16:$F$1328,5,0)),0,(VLOOKUP(B111,'Listado de Artículos'!$B$16:$F$1328,5,0))) -> 12.5 | E111: 1 | F111: 1 | G111: =IF(E111>0,(F111/E111),"") -> 1 | H111: =IF(E111>0,(100%-G111),"") -> 0 | I111: =IF(C111>0,(H111*C111/G111),"") -> 0 | J111: =IF(C111>0,(C111+I111),"") -> 0.18 | K111: =IF(D111>0,(D111*J111),"") -> 2.25
B112: ACEITE DE OLIVA SUAVE 5 LT | C112: 0.02 | D112: =IF(ISNA(VLOOKUP(B112,'Listado de Artículos'!$B$16:$F$1328,5,0)),0,(VLOOKUP(B112,'Listado de Artículos'!$B$16:$F$1328,5,0))) -> 5.95 | E112: 1 | F112: 1 | G112: =IF(E112>0,(F112/E112),"") -> 1 | H112: =IF(E112>0,(100%-G112),"") -> 0 | I112: =IF(C112>0,(H112*C112/G112),"") -> 0 | J112: =IF(C112>0,(C112+I112),"") -> 0.02 | K112: =IF(D112>0,(D112*J112),"") -> 0.119
B113: Sal gruesa | C113: 0.008 | D113: =IF(ISNA(VLOOKUP(B113,'Listado de Artículos'!$B$16:$F$1328,5,0)),0,(VLOOKUP(B113,'Listado de Artículos'!$B$16:$F$1328,5,0))) -> 3.5 | E113: 1 | F113: 1 | G113: =IF(E113>0,(F113/E113),"") -> 1 | H113: =IF(E113>0,(100%-G113),"") -> 0 | I113: =IF(C113>0,(H113*C113/G113),"") -> 0 | J113: =IF(C113>0,(C113+I113),"") -> 0.008 | K113: =IF(D113>0,(D113*J113),"") -> 0.028
B114: Pimienta negra molida. | C114: 0.002 | D114: =IF(ISNA(VLOOKUP(B114,'Listado de Artículos'!$B$16:$F$1328,5,0)),0,(VLOOKUP(B114,'Listado de Artículos'!$B$16:$F$1328,5,0))) -> 0.03 | E114: 1 | F114: 1 | G114: =IF(E114>0,(F114/E114),"") -> 1 | H114: =IF(E114>0,(100%-G114),"") -> 0 | I114: =IF(C114>0,(H114*C114/G114),"") -> 0 | J114: =IF(C114>0,(C114+I114),"") -> 0.002 | K114: =IF(D114>0,(D114*J114),"") -> 6e-05
C116: CALÇOTADA MAS BORONAT
C117: FICHA TÉCNICA PLATO
C120: ARTÍCULO | D120: CORDERO y butifarra N CALÇOTADA
C121: TAPA | D121: ELABORADOS.
C122: unid. | D122: 1 | E122: Coste TOTAL | G122: =SUM(K125:K131) -> 2.8824 | H122: Coste pax | J122: =G122/D122 -> 2.8824
B124: ARTICULO | C124: KG | D124: €/UN | E124: BRUTO | F124: NETO | G124: %NETO | H124: %DESP | I124: DESP | J124: SUCIO | K124: € / RACION
B125: Butifarra negra* calçotada racionada a 70 gr. | C125: 0.07 | D125: =IF(ISNA(VLOOKUP(B125,'Listado de Artículos'!$B$16:$F$1328,5,0)),0,(VLOOKUP(B125,'Listado de Artículos'!$B$16:$F$1328,5,0))) -> 7.6 | E125: 1 | F125: 1 | G125: =IF(E125>0,(F125/E125),"") -> 1 | H125: =IF(E125>0,(100%-G125),"") -> 0 | I125: =IF(C125>0,(H125*C125/G125),"") -> 0 | J125: =IF(C125>0,(C125+I125),"") -> 0.07 | K125: =IF(D125>0,(D125*J125),"") -> 0.532
B126: Chuleta de corderdo para calçotada con riñonada. caja 3 kg | C126: 0.075 | D126: =IF(ISNA(VLOOKUP(B126,'Listado de Artículos'!$B$16:$F$1328,5,0)),0,(VLOOKUP(B126,'Listado de Artículos'!$B$16:$F$1328,5,0))) -> 12.5 | E126: 1 | F126: 1 | G126: =IF(E126>0,(F126/E126),"") -> 1 | H126: =IF(E126>0,(100%-G126),"") -> 0 | I126: =IF(C126>0,(H126*C126/G126),"") -> 0 | J126: =IF(C126>0,(C126+I126),"") -> 0.075 | K126: =IF(D126>0,(D126*J126),"") -> 0.9375 | L126: 2 chuletas
B127: Costilla cordero * calçotada. congelada caja 3 kg. | C127: 0.075 | D127: =IF(ISNA(VLOOKUP(B127,'Listado de Artículos'!$B$16:$F$1328,5,0)),0,(VLOOKUP(B127,'Listado de Artículos'!$B$16:$F$1328,5,0))) -> 16.398 | E127: 1 | F127: 1 | G127: =IF(E127>0,(F127/E127),"") -> 1 | H127: =IF(E127>0,(100%-G127),"") -> 0 | I127: =IF(C127>0,(H127*C127/G127),"") -> 0 | J127: =IF(C127>0,(C127+I127),"") -> 0.075 | K127: =IF(D127>0,(D127*J127),"") -> 1.22985 | L127: 1 costilla
B128: Sal gruesa | C128: 0.01 | D128: =IF(ISNA(VLOOKUP(B128,'Listado de Artículos'!$B$16:$F$1328,5,0)),0,(VLOOKUP(B128,'Listado de Artículos'!$B$16:$F$1328,5,0))) -> 3.5 | E128: 1 | F128: 1 | G128: =IF(E128>0,(F128/E128),"") -> 1 | H128: =IF(E128>0,(100%-G128),"") -> 0 | I128: =IF(C128>0,(H128*C128/G128),"") -> 0 | J128: =IF(C128>0,(C128+I128),"") -> 0.01 | K128: =IF(D128>0,(D128*J128),"") -> 0.035
B129: Pimienta negra molida. | C129: 0.005 | D129: =IF(ISNA(VLOOKUP(B129,'Listado de Artículos'!$B$16:$F$1328,5,0)),0,(VLOOKUP(B129,'Listado de Artículos'!$B$16:$F$1328,5,0))) -> 0.03 | E129: 1 | F129: 1 | G129: =IF(E129>0,(F129/E129),"") -> 1 | H129: =IF(E129>0,(100%-G129),"") -> 0 | I129: =IF(C129>0,(H129*C129/G129),"") -> 0 | J129: =IF(C129>0,(C129+I129),"") -> 0.005 | K129: =IF(D129>0,(D129*J129),"") -> 0.00015
B130: ACEITE DE OLIVA SUAVE 5 LT | C130: 0.02 | D130: =IF(ISNA(VLOOKUP(B130,'Listado de Artículos'!$B$16:$F$1328,5,0)),0,(VLOOKUP(B130,'Listado de Artículos'!$B$16:$F$1328,5,0))) -> 5.95 | E130: 1 | F130: 1 | G130: =IF(E130>0,(F130/E130),"") -> 1 | H130: =IF(E130>0,(100%-G130),"") -> 0 | I130: =IF(C130>0,(H130*C130/G130),"") -> 0 | J130: =IF(C130>0,(C130+I130),"") -> 0.02 | K130: =IF(D130>0,(D130*J130),"") -> 0.119
B131: Sal negra en escamas. | C131: 0.005 | D131: =IF(ISNA(VLOOKUP(B131,'Listado de Artículos'!$B$16:$F$1328,5,0)),0,(VLOOKUP(B131,'Listado de Artículos'!$B$16:$F$1328,5,0))) -> 5.78 | E131: 1 | F131: 1 | G131: =IF(E131>0,(F131/E131),"") -> 1 | H131: =IF(E131>0,(100%-G131),"") -> 0 | I131: =IF(C131>0,(H131*C131/G131),"") -> 0 | J131: =IF(C131>0,(C131+I131),"") -> 0.005 | K131: =IF(D131>0,(D131*J131),"") -> 0.0289
C134: CALÇOTADA MAS BORONAT
C135: FICHA TÉCNICA PLATO
C138: ARTÍCULO | D138: SALSA ROMESCO PARA CALÇOTS.
C139: TAPA | D139: ELABORADOS.
C140: KG | D140: 15 | E140: Coste TOTAL | G140: =SUM(K143:K154) -> 346.638 | H140: Coste KG | J140: =G140/D140 -> 23.1092
B142: ARTICULO | C142: KG | D142: €/UN | E142: BRUTO | F142: NETO | G142: %NETO | H142: %DESP | I142: DESP | J142: SUCIO | K142: € / RACION
B143: Tomate Maduro. | C143: 12 | D143: =IF(ISNA(VLOOKUP(B143,'Listado de Artículos'!$B$16:$F$1328,5,0)),0,(VLOOKUP(B143,'Listado de Artículos'!$B$16:$F$1328,5,0))) -> 13.9 | E143: 1 | F143: 1 | G143: =IF(E143>0,(F143/E143),"") -> 1 | H143: =IF(E143>0,(100%-G143),"") -> 0 | I143: =IF(C143>0,(H143*C143/G143),"") -> 0 | J143: =IF(C143>0,(C143+I143),"") -> 12 | K143: =IF(D143>0,(D143*J143),"") -> 166.8
B144: Ajo rojo extra a granel. | C144: 1.4 | D144: =IF(ISNA(VLOOKUP(B144,'Listado de Artículos'!$B$16:$F$1328,5,0)),0,(VLOOKUP(B144,'Listado de Artículos'!$B$16:$F$1328,5,0))) -> 2 | E144: 1 | F144: 1 | G144: =IF(E144>0,(F144/E144),"") -> 1 | H144: =IF(E144>0,(100%-G144),"") -> 0 | I144: =IF(C144>0,(H144*C144/G144),"") -> 0 | J144: =IF(C144>0,(C144+I144),"") -> 1.4 | K144: =IF(D144>0,(D144*J144),"") -> 2.8
B145: ACEITE DE OLIVA SUAVE 5 LT | C145: 3 | D145: =IF(ISNA(VLOOKUP(B145,'Listado de Artículos'!$B$16:$F$1328,5,0)),0,(VLOOKUP(B145,'Listado de Artículos'!$B$16:$F$1328,5,0))) -> 5.95 | E145: 1 | F145: 1 | G145: =IF(E145>0,(F145/E145),"") -> 1 | H145: =IF(E145>0,(100%-G145),"") -> 0 | I145: =IF(C145>0,(H145*C145/G145),"") -> 0 | J145: =IF(C145>0,(C145+I145),"") -> 3 | K145: =IF(D145>0,(D145*J145),"") -> 17.85
B146: ACEITE DE OLIVA VIRGEN EXTRA SALOMO . | C146: 3 | D146: =IF(ISNA(VLOOKUP(B146,'Listado de Artículos'!$B$16:$F$1328,5,0)),0,(VLOOKUP(B146,'Listado de Artículos'!$B$16:$F$1328,5,0))) -> 8.97 | E146: 1 | F146: 1 | G146: =IF(E146>0,(F146/E146),"") -> 1 | H146: =IF(E146>0,(100%-G146),"") -> 0 | I146: =IF(C146>0,(H146*C146/G146),"") -> 0 | J146: =IF(C146>0,(C146+I146),"") -> 3 | K146: =IF(D146>0,(D146*J146),"") -> 26.91
...

Sheet Menú bbq 95€
A2: MENU BBQ 95€ 13-03-26
A4: Entrantes | B4: P.V.P | C4: NETO | D4: COSTO | E4: FOOD COST
A5: CALÇOTADA. APERITIVO CARTA | B5: GR O KG. | C5: PRECIO KG | D5: EUROS/RACION.
A6: Carpaccio de tomate con burrata y aceite albahaca | B6: 1 | C6: =IF(ISNA(VLOOKUP(A6,'Listado de Artículos'!$B$16:$F$1328,5,0)),0,(VLOOKUP(A6,'Listado de Artículos'!$B$16:$F$1328,5,0))) -> 0.16574167 | D6: =B6*C6 -> 0.16574167
A7: Huevos rotos con jamón y foie | B7: 1 | C7: =IF(ISNA(VLOOKUP(A7,'Listado de Artículos'!$B$16:$F$1328,5,0)),0,(VLOOKUP(A7,'Listado de Artículos'!$B$16:$F$1328,5,0))) -> 2.0265 | D7: =B7*C7 -> 2.0265
A8: Vaso Pulpo a la feira | B8: 1 | C8: =IF(ISNA(VLOOKUP(A8,'Listado de Artículos'!$B$16:$F$1328,5,0)),0,(VLOOKUP(A8,'Listado de Artículos'!$B$16:$F$1328,5,0))) -> 3.6789 | D8: =B8*C8 -> 3.6789
A9: Plato principal
A10: Chuleta lomo bajo con pimiento del piquillo y alcachofa | B10: 1 | C10: =IF(ISNA(VLOOKUP(A10,'Listado de Artículos'!$B$16:$F$1328,5,0)),0,(VLOOKUP(A10,'Listado de Artículos'!$B$16:$F$1328,5,0))) -> 15.2695 | D10: =B10*C10 -> 15.2695
A11: Cafe Natural. 1 kg. 120 cafes. 24,48€ .kg. 0,22 unid | B11: 1 | C11: =IF(ISNA(VLOOKUP(A11,'Listado de Artículos'!$B$16:$F$1328,5,0)),0,(VLOOKUP(A11,'Listado de Artículos'!$B$16:$F$1328,5,0))) -> 0.65 | D11: =B11*C11 -> 0.65
A12: Agua Fon vella 1 LT Caja de 12 unid. | B12: 0.3 | C12: =IF(ISNA(VLOOKUP(A12,'Listado de Artículos'!$B$16:$F$1328,5,0)),0,(VLOOKUP(A12,'Listado de Artículos'!$B$16:$F$1328,5,0))) -> 0.8 | D12: =B12*C12 -> 0.24
D13: 9
A14: ESCANDALLO | B14: 95 | C14: =B14/1.1 -> 86.363636 | D14: =SUM(D6:D13) -> 31.030642 | E14: =(D14*100/C14)/100 -> 0.35930217
C16: =C14-D14 -> 55.332995
B17: =16.5*10% -> 1.65
B18: =16.5-1.65 -> 14.85

Sheet M.P CALÇOTADA
C3: CALÇOTADA MAS BORONAT
C4: FICHA TÉCNICA PLATO
C7: ARTÍCULO | D7: Vermouth rojo
C8: TAPA | D8: ELABORADOS.
C9: unid. | D9: 1 | E9: Coste TOTAL | G9: =SUM(K12:K14) -> 1.45075 | H9: Coste KG: | J9: =G9/D9 -> 1.45075
B11: ARTICULO | C11: KG | D11: €/UN | E11: BRUTO | F11: NETO | G11: %NETO | H11: %DESP | I11: DESP | J11: SUCIO | K11: € / RACION
B12: Mirrah. rojo 15% 5 l. 15,01€ precio backin box | C12: 0.1 | D12: =IF(ISNA(VLOOKUP(B12,'Listado de Artículos'!$B$16:$F$1328,5,0)),0,(VLOOKUP(B12,'Listado de Artículos'!$B$16:$F$1328,5,0))) -> 5.62 | E12: 1 | F12: 1 | G12: =IF(E12>0,(F12/E12),"") -> 1 | H12: =IF(E12>0,(100%-G12),"") -> 0 | I12: =IF(C12>0,(H12*C12/G12),"") -> 0 | J12: =IF(C12>0,(C12+I12),"") -> 0.1 | K12: =IF(D12>0,(D12*J12),"") -> 0.562
B13: Naranja extra de mesa. | C13: 0.025 | D13: =IF(ISNA(VLOOKUP(B13,'Listado de Artículos'!$B$16:$F$1328,5,0)),0,(VLOOKUP(B13,'Listado de Artículos'!$B$16:$F$1328,5,0))) -> 17.55 | E13: 1 | F13: 1 | G13: =IF(E13>0,(F13/E13),"") -> 1 | H13: =IF(E13>0,(100%-G13),"") -> 0 | I13: =IF(C13>0,(H13*C13/G13),"") -> 0 | J13: =IF(C13>0,(C13+I13),"") -> 0.025 | K13: =IF(D13>0,(D13*J13),"") -> 0.43875
B14: OLIVAS RELLENAS GIGANTES LATA 2 KG. 4,79€ | C14: 0.05 | D14: =IF(ISNA(VLOOKUP(B14,'Listado de Artículos'!$B$16:$F$1328,5,0)),0,(VLOOKUP(B14,'Listado de Artículos'!$B$16:$F$1328,5,0))) -> 9 | E14: 1 | F14: 1 | G14: =IF(E14>0,(F14/E14),"") -> 1 | H14: =IF(E14>0,(100%-G14),"") -> 0 | I14: =IF(C14>0,(H14*C14/G14),"") -> 0 | J14: =IF(C14>0,(C14+I14),"") -> 0.05 | K14: =IF(D14>0,(D14*J14),"") -> 0.45
C19: CALÇOTADA MAS BORONAT
C20: FICHA TÉCNICA PLATO
C23: ARTÍCULO | D23: Naranja con miel
C24: TAPA | D24: ELABORADOS. | H24: COSTE UNID.
C25: PAX | D25: 1 | E25: Coste TOTAL | G25: =SUM(K28:K29) -> 2.6723 | H25: Coste unid: | J25: =G25/D25 -> 2.6723
B27: ARTICULO | C27: KG | D27: €/UN | E27: BRUTO | F27: NETO | G27: %NETO | H27: %DESP | I27: DESP | J27: SUCIO | K27: € / RACION
B28: Naranja extra de mesa. | C28: 0.15 | D28: =IF(ISNA(VLOOKUP(B28,'Listado de Artículos'!$B$16:$F$1328,5,0)),0,(VLOOKUP(B28,'Listado de Artículos'!$B$16:$F$1328,5,0))) -> 17.55 | E28: 1 | F28: 1 | G28: =IF(E28>0,(F28/E28),"") -> 1 | H28: =IF(E28>0,(100%-G28),"") -> 0 | I28: =IF(C28>0,(H28*C28/G28),"") -> 0 | J28: =IF(C28>0,(C28+I28),"") -> 0.15 | K28: =IF(D28>0,(D28*J28),"") -> 2.6325
B29: Miel del perello | C29: 0.01 | D29: =IF(ISNA(VLOOKUP(B29,'Listado de Artículos'!$B$16:$F$1328,5,0)),0,(VLOOKUP(B29,'Listado de Artículos'!$B$16:$F$1328,5,0))) -> 3.98 | E29: 1 | F29: 1 | G29: =IF(E29>0,(F29/E29),"") -> 1 | H29: =IF(E29>0,(100%-G29),"") -> 0 | I29: =IF(C29>0,(H29*C29/G29),"") -> 0 | J29: =IF(C29>0,(C29+I29),"") -> 0.01 | K29: =IF(D29>0,(D29*J29),"") -> 0.0398
C32: CALÇOTADA MAS BORONAT
C33: FICHA TÉCNICA PLATO
C36: ARTÍCULO | D36: Crema catalana.
C37: TAPA | D37: ELABORADOS | H37: PRECIO DE VENTA P.V.P
C38: unid. | D38: 7 | E38: Coste TOTAL | G38: =SUM(K41:K47) -> 5.88848 | H38: Coste UNID: | J38: =G38/D38 -> 0.84121143
B40: ARTICULO | C40: KG | D40: €/UN | E40: BRUTO | F40: NETO | G40: %NETO | H40: %DESP | I40: DESP | J40: SUCIO | K40: € / RACION
B41: Leche entera. | C41: 1 | D41: =IF(ISNA(VLOOKUP(B41,'Listado de Artículos'!$B$16:$F$1328,5,0)),0,(VLOOKUP(B41,'Listado de Artículos'!$B$16:$F$1328,5,0))) -> 2.8 | E41: 1 | F41: 1 | G41: =IF(E41>0,(F41/E41),"") -> 1 | H41: =IF(E41>0,(100%-G41),"") -> 0 | I41: =IF(C41>0,(H41*C41/G41),"") -> 0 | J41: =IF(C41>0,(C41+I41),"") -> 1 | K41: =IF(D41>0,(D41*J41),"") -> 2.8
B42: CANELA EN RAMA BOTE | C42: 0.016 | D42: =IF(ISNA(VLOOKUP(B42,'Listado de Artículos'!$B$16:$F$1328,5,0)),0,(VLOOKUP(B42,'Listado de Artículos'!$B$16:$F$1328,5,0))) -> 5.73 | E42: 1 | F42: 1 | G42: =IF(E42>0,(F42/E42),"") -> 1 | H42: =IF(E42>0,(100%-G42),"") -> 0 | I42: =IF(C42>0,(H42*C42/G42),"") -> 0 | J42: =IF(C42>0,(C42+I42),"") -> 0.016 | K42: =IF(D42>0,(D42*J42),"") -> 0.09168
B43: Naranja de zumo. | C43: 0.04 | D43: =IF(ISNA(VLOOKUP(B43,'Listado de Artículos'!$B$16:$F$1328,5,0)),0,(VLOOKUP(B43,'Listado de Artículos'!$B$16:$F$1328,5,0))) -> 21.5 | E43: 1 | F43: 1 | G43: =IF(E43>0,(F43/E43),"") -> 1 | H43: =IF(E43>0,(100%-G43),"") -> 0 | I43: =IF(C43>0,(H43*C43/G43),"") -> 0 | J43: =IF(C43>0,(C43+I43),"") -> 0.04 | K43: =IF(D43>0,(D43*J43),"") -> 0.86
B44: Limones extra. | C44: 0.04 | D44: =IF(ISNA(VLOOKUP(B44,'Listado de Artículos'!$B$16:$F$1328,5,0)),0,(VLOOKUP(B44,'Listado de Artículos'!$B$16:$F$1328,5,0))) -> 1.38 | E44: 1 | F44: 1 | G44: =IF(E44>0,(F44/E44),"") -> 1 | H44: =IF(E44>0,(100%-G44),"") -> 0 | I44: =IF(C44>0,(H44*C44/G44),"") -> 0 | J44: =IF(C44>0,(C44+I44),"") -> 0.04 | K44: =IF(D44>0,(D44*J44),"") -> 0.0552
B45: AZUCAR | C45: 0.14 | D45: =IF(ISNA(VLOOKUP(B45,'Listado de Artículos'!$B$16:$F$1328,5,0)),0,(VLOOKUP(B45,'Listado de Artículos'!$B$16:$F$1328,5,0))) -> 0.82 | E45: 1 | F45: 1 | G45: =IF(E45>0,(F45/E45),"") -> 1 | H45: =IF(E45>0,(100%-G45),"") -> 0 | I45: =IF(C45>0,(H45*C45/G45),"") -> 0 | J45: =IF(C45>0,(C45+I45),"") -> 0.14 | K45: =IF(D45>0,(D45*J45),"") -> 0.1148
B46: MAIZENA 700 GR. | C46: 0.04 | D46: =IF(ISNA(VLOOKUP(B46,'Listado de Artículos'!$B$16:$F$1328,5,0)),0,(VLOOKUP(B46,'Listado de Artículos'!$B$16:$F$1328,5,0))) -> 3.67 | E46: 1 | F46: 1 | G46: =IF(E46>0,(F46/E46),"") -> 1 | H46: =IF(E46>0,(100%-G46),"") -> 0 | I46: =IF(C46>0,(H46*C46/G46),"") -> 0 | J46: =IF(C46>0,(C46+I46),"") -> 0.04 | K46: =IF(D46>0,(D46*J46),"") -> 0.1468
B47: Huevos "L" Granja Vidal, pqt de 6 unid: 1,60€ | C47: 7 | D47: =IF(ISNA(VLOOKUP(B47,'Listado de Artículos'!$B$16:$F$1328,5,0)),0,(VLOOKUP(B47,'Listado de Artículos'!$B$16:$F$1328,5,0))) -> 0.26 | E47: 1 | F47: 1 | G47: =IF(E47>0,(F47/E47),"") -> 1 | H47: =IF(E47>0,(100%-G47),"") -> 0 | I47: =IF(C47>0,(H47*C47/G47),"") -> 0 | J47: =IF(C47>0,(C47+I47),"") -> 7 | K47: =IF(D47>0,(D47*J47),"") -> 1.82
C50: CALÇOTADA MAS BORONAT
C51: FICHA TÉCNICA PLATO
C54: ARTÍCULO | D54: Crema Catalana quemada con carquiñoli.
C55: TAPA | D55: ELABORADOS.
C56: unid. | D56: 1 | E56: Coste TOTAL | G56: =SUM(K59:K61) -> 0.7621 | H56: Coste UNID: | J56: =G56/D56 -> 0.7621
B58: ARTICULO | C58: KG | D58: €/UN | E58: BRUTO | F58: NETO | G58: %NETO | H58: %DESP | I58: DESP | J58: SUCIO | K58: € / RACION
B59: Crema Catalana. | C59: 1 | D59: =IF(ISNA(VLOOKUP(B59,'Listado de Artículos'!$B$16:$F$1328,5,0)),0,(VLOOKUP(B59,'Listado de Artículos'!$B$16:$F$1328,5,0))) -> 0.5 | E59: 1 | F59: 1 | G59: =IF(E59>0,(F59/E59),"") -> 1 | H59: =IF(E59>0,(100%-G59),"") -> 0 | I59: =IF(C59>0,(H59*C59/G59),"") -> 0 | J59: =IF(C59>0,(C59+I59),"") -> 1 | K59: =IF(D59>0,(D59*J59),"") -> 0.5
B60: AZUCAR | C60: 0.025 | D60: =IF(ISNA(VLOOKUP(B60,'Listado de Artículos'!$B$16:$F$1328,5,0)),0,(VLOOKUP(B60,'Listado de Artículos'!$B$16:$F$1328,5,0))) -> 0.82 | E60: 1 | F60: 1 | G60: =IF(E60>0,(F60/E60),"") -> 1 | H60: =IF(E60>0,(100%-G60),"") -> 0 | I60: =IF(C60>0,(H60*C60/G60),"") -> 0 | J60: =IF(C60>0,(C60+I60),"") -> 0.025 | K60: =IF(D60>0,(D60*J60),"") -> 0.0205
B61: Carquiñolis. 200 gr. 3,75€ pqt | C61: 0.01 | D61: =IF(ISNA(VLOOKUP(B61,'Listado de Artículos'!$B$16:$F$1328,5,0)),0,(VLOOKUP(B61,'Listado de Artículos'!$B$16:$F$1328,5,0))) -> 24.16 | E61: 1 | F61: 1 | G61: =IF(E61>0,(F61/E61),"") -> 1 | H61: =IF(E61>0,(100%-G61),"") -> 0 | I61: =IF(C61>0,(H61*C61/G61),"") -> 0 | J61: =IF(C61>0,(C61+I61),"") -> 0.01 | K61: =IF(D61>0,(D61*J61),"") -> 0.2416
C64: CALÇOTADA MAS BORONAT
C65: FICHA TÉCNICA PLATO
C68: ARTÍCULO | D68: Botifarra con mongetes del ganxet.
C69: TAPA | D69: ELABORADOS.
C70: unid. | D70: 1 | E70: Coste TOTAL | G70: =SUM(K73:K78) -> 0.92836 | H70: PAX | J70: =G70/D70 -> 0.92836
B72: ARTICULO | C72: KG | D72: €/UN | E72: BRUTO | F72: NETO | G72: %NETO | H72: %DESP | I72: DESP | J72: SUCIO | K72: € / RACION
B73: Mongetes del ganxet. lata de 3 kg-17,22€ | C73: 0.1 | D73: =IF(ISNA(VLOOKUP(B73,'Listado de Artículos'!$B$16:$F$1328,5,0)),0,(VLOOKUP(B73,'Listado de Artículos'!$B$16:$F$1328,5,0))) -> 0.2 | E73: 1 | F73: 1 | G73: =IF(E73>0,(F73/E73),"") -> 1 | H73: =IF(E73>0,(100%-G73),"") -> 0 | I73: =IF(C73>0,(H73*C73/G73),"") -> 0 | J73: =IF(C73>0,(C73+I73),"") -> 0.1 | K73: =IF(D73>0,(D73*J73),"") -> 0.02
B74: Butifarra fresca corta 14.cm. calçots. 90 gr porcianda | C74: 0.09 | D74: =IF(ISNA(VLOOKUP(B74,'Listado de Artículos'!$B$16:$F$1328,5,0)),0,(VLOOKUP(B74,'Listado de Artículos'!$B$16:$F$1328,5,0))) -> 6.15 | E74: 1 | F74: 1 | G74: =IF(E74>0,(F74/E74),"") -> 1 | H74: =IF(E74>0,(100%-G74),"") -> 0 | I74: =IF(C74>0,(H74*C74/G74),"") -> 0 | J74: =IF(C74>0,(C74+I74),"") -> 0.09 | K74: =IF(D74>0,(D74*J74),"") -> 0.5535
B75: Picada de ajo y perejil. | C75: 0.01 | D75: =IF(ISNA(VLOOKUP(B75,'Listado de Artículos'!$B$16:$F$1328,5,0)),0,(VLOOKUP(B75,'Listado de Artículos'!$B$16:$F$1328,5,0))) -> 23.71 | E75: 1 | F75: 1 | G75: =IF(E75>0,(F75/E75),"") -> 1 | H75: =IF(E75>0,(100%-G75),"") -> 0 | I75: =IF(C75>0,(H75*C75/G75),"") -> 0 | J75: =IF(C75>0,(C75+I75),"") -> 0.01 | K75: =IF(D75>0,(D75*J75),"") -> 0.2371
B76: Sal gruesa | C76: 0.008 | D76: =IF(ISNA(VLOOKUP(B76,'Listado de Artículos'!$B$16:$F$1328,5,0)),0,(VLOOKUP(B76,'Listado de Artículos'!$B$16:$F$1328,5,0))) -> 3.5 | E76: 1 | F76: 1 | G76: =IF(E76>0,(F76/E76),"") -> 1 | H76: =IF(E76>0,(100%-G76),"") -> 0 | I76: =IF(C76>0,(H76*C76/G76),"") -> 0 | J76: =IF(C76>0,(C76+I76),"") -> 0.008 | K76: =IF(D76>0,(D76*J76),"") -> 0.028
B77: Pimienta negra molida. | C77: 0.002 | D77: =IF(ISNA(VLOOKUP(B77,'Listado de Artículos'!$B$16:$F$1328,5,0)),0,(VLOOKUP(B77,'Listado de Artículos'!$B$16:$F$1328,5,0))) -> 0.03 | E77: 1 | F77: 1 | G77: =IF(E77>0,(F77/E77),"") -> 1 | H77: =IF(E77>0,(100%-G77),"") -> 0 | I77: =IF(C77>0,(H77*C77/G77),"") -> 0 | J77: =IF(C77>0,(C77+I77),"") -> 0.002 | K77: =IF(D77>0,(D77*J77),"") -> 6e-05
B78: ACEITE DE OLIVA VIRGEN EXTRA SALOMO . | C78: 0.01 | D78: =IF(ISNA(VLOOKUP(B78,'Listado de Artículos'!$B$16:$F$1328,5,0)),0,(VLOOKUP(B78,'Listado de Artículos'!$B$16:$F$1328,5,0))) -> 8.97 | E78: 1 | F78: 1 | G78: =IF(E78>0,(F78/E78),"") -> 1 | H78: =IF(E78>0,(100%-G78),"") -> 0 | I78: =IF(C78>0,(H78*C78/G78),"") -> 0 | J78: =IF(C78>0,(C78+I78),"") -> 0.01 | K78: =IF(D78>0,(D78*J78),"") -> 0.0897
C80: CALÇOTADA MAS BORONAT
C81: FICHA TÉCNICA PLATO
C84: ARTÍCULO | D84: Botifarra con mongetes del ganxet.
C85: TAPA | D85: ELABORADOS.
C86: unid. | D86: 1 | E86: Coste TOTAL | G86: =SUM(K89:K94) -> 3.80336 | H86: PAX | J86: =G86/D86 -> 3.80336
B88: ARTICULO | C88: KG | D88: €/UN | E88: BRUTO | F88: NETO | G88: %NETO | H88: %DESP | I88: DESP | J88: SUCIO | K88: € / RACION
B89: MONGETAS NATURALES. 3 KG( 2,89€ LATA DE 3 KG). | C89: 0.1 | D89: =IF(ISNA(VLOOKUP(B89,'Listado de Artículos'!$B$16:$F$1328,5,0)),0,(VLOOKUP(B89,'Listado de Artículos'!$B$16:$F$1328,5,0))) -> 28.95 | E89: 1 | F89: 1 | G89: =IF(E89>0,(F89/E89),"") -> 1 | H89: =IF(E89>0,(100%-G89),"") -> 0 | I89: =IF(C89>0,(H89*C89/G89),"") -> 0 | J89: =IF(C89>0,(C89+I89),"") -> 0.1 | K89: =IF(D89>0,(D89*J89),"") -> 2.895
B90: Butifarra fresca corta 14.cm. calçots. 90 gr porcianda | C90: 0.09 | D90: =IF(ISNA(VLOOKUP(B90,'Listado de Artículos'!$B$16:$F$1328,5,0)),0,(VLOOKUP(B90,'Listado de Artículos'!$B$16:$F$1328,5,0))) -> 6.15 | E90: 1 | F90: 1 | G90: =IF(E90>0,(F90/E90),"") -> 1 | H90: =IF(E90>0,(100%-G90),"") -> 0 | I90: =IF(C90>0,(H90*C90/G90),"") -> 0 | J90: =IF(C90>0,(C90+I90),"") -> 0.09 | K90: =IF(D90>0,(D90*J90),"") -> 0.5535
B91: Picada de ajo y perejil. | C91: 0.01 | D91: =IF(ISNA(VLOOKUP(B91,'Listado de Artículos'!$B$16:$F$1328,5,0)),0,(VLOOKUP(B91,'Listado de Artículos'!$B$16:$F$1328,5,0))) -> 23.71 | E91: 1 | F91: 1 | G91: =IF(E91>0,(F91/E91),"") -> 1 | H91: =IF(E91>0,(100%-G91),"") -> 0 | I91: =IF(C91>0,(H91*C91/G91),"") -> 0 | J91: =IF(C91>0,(C91+I91),"") -> 0.01 | K91: =IF(D91>0,(D91*J91),"") -> 0.2371
B92: Sal gruesa | C92: 0.008 | D92: =IF(ISNA(VLOOKUP(B92,'Listado de Artículos'!$B$16:$F$1328,5,0)),0,(VLOOKUP(B92,'Listado de Artículos'!$B$16:$F$1328,5,0))) -> 3.5 | E92: 1 | F92: 1 | G92: =IF(E92>0,(F92/E92),"") -> 1 | H92: =IF(E92>0,(100%-G92),"") -> 0 | I92: =IF(C92>0,(H92*C92/G92),"") -> 0 | J92: =IF(C92>0,(C92+I92),"") -> 0.008 | K92: =IF(D92>0,(D92*J92),"") -> 0.028
B93: Pimienta negra molida. | C93: 0.002 | D93: =IF(ISNA(VLOOKUP(B93,'Listado de Artículos'!$B$16:$F$1328,5,0)),0,(VLOOKUP(B93,'Listado de Artículos'!$B$16:$F$1328,5,0))) -> 0.03 | E93: 1 | F93: 1 | G93: =IF(E93>0,(F93/E93),"") -> 1 | H93: =IF(E93>0,(100%-G93),"") -> 0 | I93: =IF(C93>0,(H93*C93/G93),"") -> 0 | J93: =IF(C93>0,(C93+I93),"") -> 0.002 | K93: =IF(D93>0,(D93*J93),"") -> 6e-05
B94: ACEITE DE OLIVA VIRGEN EXTRA SALOMO . | C94: 0.01 | D94: =IF(ISNA(VLOOKUP(B94,'Listado de Artículos'!$B$16:$F$1328,5,0)),0,(VLOOKUP(B94,'Listado de Artículos'!$B$16:$F$1328,5,0))) -> 8.97 | E94: 1 | F94: 1 | G94: =IF(E94>0,(F94/E94),"") -> 1 | H94: =IF(E94>0,(100%-G94),"") -> 0 | I94: =IF(C94>0,(H94*C94/G94),"") -> 0 | J94: =IF(C94>0,(C94+I94),"") -> 0.01 | K94: =IF(D94>0,(D94*J94),"") -> 0.0897
C96: CALÇOTADA MAS BORONAT
C97: FICHA TÉCNICA PLATO
C100: ARTÍCULO | D100: GUARNICION DE CALÇOTADA.
C101: TAPA | D101: ELABORADOS.
C102: unid. | D102: 1 | E102: Coste TOTAL | G102: =SUM(K105:K109) -> 2.87706 | H102: Coste pax | J102: =G102/D102 -> 2.87706
B104: ARTICULO | C104: KG | D104: €/UN | E104: BRUTO | F104: NETO | G104: %NETO | H104: %DESP | I104: DESP | J104: SUCIO | K104: € / RACION
B105: Patata Monalisa. | C105: 0.24 | D105: =IF(ISNA(VLOOKUP(B105,'Listado de Artículos'!$B$16:$F$1328,5,0)),0,(VLOOKUP(B105,'Listado de Artículos'!$B$16:$F$1328,5,0))) -> 2 | E105: 1 | F105: 1 | G105: =IF(E105>0,(F105/E105),"") -> 1 | H105: =IF(E105>0,(100%-G105),"") -> 0 | I105: =IF(C105>0,(H105*C105/G105),"") -> 0 | J105: =IF(C105>0,(C105+I105),"") -> 0.24 | K105: =IF(D105>0,(D105*J105),"") -> 0.48
B106: Alcachofas. | C106: 0.18 | D106: =IF(ISNA(VLOOKUP(B106,'Listado de Artículos'!$B$16:$F$1328,5,0)),0,(VLOOKUP(B106,'Listado de Artículos'!$B$16:$F$1328,5,0))) -> 12.5 | E106: 1 | F106: 1 | G106: =IF(E106>0,(F106/E106),"") -> 1 | H106: =IF(E106>0,(100%-G106),"") -> 0 | I106: =IF(C106>0,(H106*C106/G106),"") -> 0 | J106: =IF(C106>0,(C106+I106),"") -> 0.18 | K106: =IF(D106>0,(D106*J106),"") -> 2.25
B107: ACEITE DE OLIVA SUAVE 5 LT | C107: 0.02 | D107: =IF(ISNA(VLOOKUP(B107,'Listado de Artículos'!$B$16:$F$1328,5,0)),0,(VLOOKUP(B107,'Listado de Artículos'!$B$16:$F$1328,5,0))) -> 5.95 | E107: 1 | F107: 1 | G107: =IF(E107>0,(F107/E107),"") -> 1 | H107: =IF(E107>0,(100%-G107),"") -> 0 | I107: =IF(C107>0,(H107*C107/G107),"") -> 0 | J107: =IF(C107>0,(C107+I107),"") -> 0.02 | K107: =IF(D107>0,(D107*J107),"") -> 0.119
B108: Sal gruesa | C108: 0.008 | D108: =IF(ISNA(VLOOKUP(B108,'Listado de Artículos'!$B$16:$F$1328,5,0)),0,(VLOOKUP(B108,'Listado de Artículos'!$B$16:$F$1328,5,0))) -> 3.5 | E108: 1 | F108: 1 | G108: =IF(E108>0,(F108/E108),"") -> 1 | H108: =IF(E108>0,(100%-G108),"") -> 0 | I108: =IF(C108>0,(H108*C108/G108),"") -> 0 | J108: =IF(C108>0,(C108+I108),"") -> 0.008 | K108: =IF(D108>0,(D108*J108),"") -> 0.028
B109: Pimienta negra molida. | C109: 0.002 | D109: =IF(ISNA(VLOOKUP(B109,'Listado de Artículos'!$B$16:$F$1328,5,0)),0,(VLOOKUP(B109,'Listado de Artículos'!$B$16:$F$1328,5,0))) -> 0.03 | E109: 1 | F109: 1 | G109: =IF(E109>0,(F109/E109),"") -> 1 | H109: =IF(E109>0,(100%-G109),"") -> 0 | I109: =IF(C109>0,(H109*C109/G109),"") -> 0 | J109: =IF(C109>0,(C109+I109),"") -> 0.002 | K109: =IF(D109>0,(D109*J109),"") -> 6e-05
C111: CALÇOTADA MAS BORONAT
C112: FICHA TÉCNICA PLATO
C115: ARTÍCULO | D115: CORDERO y butifarra N CALÇOTADA
C116: TAPA | D116: ELABORADOS.
C117: unid. | D117: 1 | E117: Coste TOTAL | G117: =SUM(K120:K126) -> 2.8824 | H117: Coste pax | J117: =G117/D117 -> 2.8824
B119: ARTICULO | C119: KG | D119: €/UN | E119: BRUTO | F119: NETO | G119: %NETO | H119: %DESP | I119: DESP | J119: SUCIO | K119: € / RACION
B120: Butifarra negra* calçotada racionada a 70 gr. | C120: 0.07 | D120: =IF(ISNA(VLOOKUP(B120,'Listado de Artículos'!$B$16:$F$1328,5,0)),0,(VLOOKUP(B120,'Listado de Artículos'!$B$16:$F$1328,5,0))) -> 7.6 | E120: 1 | F120: 1 | G120: =IF(E120>0,(F120/E120),"") -> 1 | H120: =IF(E120>0,(100%-G120),"") -> 0 | I120: =IF(C120>0,(H120*C120/G120),"") -> 0 | J120: =IF(C120>0,(C120+I120),"") -> 0.07 | K120: =IF(D120>0,(D120*J120),"") -> 0.532
B121: Chuleta de corderdo para calçotada con riñonada. caja 3 kg | C121: 0.075 | D121: =IF(ISNA(VLOOKUP(B121,'Listado de Artículos'!$B$16:$F$1328,5,0)),0,(VLOOKUP(B121,'Listado de Artículos'!$B$16:$F$1328,5,0))) -> 12.5 | E121: 1 | F121: 1 | G121: =IF(E121>0,(F121/E121),"") -> 1 | H121: =IF(E121>0,(100%-G121),"") -> 0 | I121: =IF(C121>0,(H121*C121/G121),"") -> 0 | J121: =IF(C121>0,(C121+I121),"") -> 0.075 | K121: =IF(D121>0,(D121*J121),"") -> 0.9375 | L121: 2 chuletas
B122: Costilla cordero * calçotada. congelada caja 3 kg. | C122: 0.075 | D122: =IF(ISNA(VLOOKUP(B122,'Listado de Artículos'!$B$16:$F$1328,5,0)),0,(VLOOKUP(B122,'Listado de Artículos'!$B$16:$F$1328,5,0))) -> 16.398 | E122: 1 | F122: 1 | G122: =IF(E122>0,(F122/E122),"") -> 1 | H122: =IF(E122>0,(100%-G122),"") -> 0 | I122: =IF(C122>0,(H122*C122/G122),"") -> 0 | J122: =IF(C122>0,(C122+I122),"") -> 0.075 | K122: =IF(D122>0,(D122*J122),"") -> 1.22985 | L122: 1 costilla
B123: Sal gruesa | C123: 0.01 | D123: =IF(ISNA(VLOOKUP(B123,'Listado de Artículos'!$B$16:$F$1328,5,0)),0,(VLOOKUP(B123,'Listado de Artículos'!$B$16:$F$1328,5,0))) -> 3.5 | E123: 1 | F123: 1 | G123: =IF(E123>0,(F123/E123),"") -> 1 | H123: =IF(E123>0,(100%-G123),"") -> 0 | I123: =IF(C123>0,(H123*C123/G123),"") -> 0 | J123: =IF(C123>0,(C123+I123),"") -> 0.01 | K123: =IF(D123>0,(D123*J123),"") -> 0.035
B124: Pimienta negra molida. | C124: 0.005 | D124: =IF(ISNA(VLOOKUP(B124,'Listado de Artículos'!$B$16:$F$1328,5,0)),0,(VLOOKUP(B124,'Listado de Artículos'!$B$16:$F$1328,5,0))) -> 0.03 | E124: 1 | F124: 1 | G124: =IF(E124>0,(F124/E124),"") -> 1 | H124: =IF(E124>0,(100%-G124),"") -> 0 | I124: =IF(C124>0,(H124*C124/G124),"") -> 0 | J124: =IF(C124>0,(C124+I124),"") -> 0.005 | K124: =IF(D124>0,(D124*J124),"") -> 0.00015
B125: ACEITE DE OLIVA SUAVE 5 LT | C125: 0.02 | D125: =IF(ISNA(VLOOKUP(B125,'Listado de Artículos'!$B$16:$F$1328,5,0)),0,(VLOOKUP(B125,'Listado de Artículos'!$B$16:$F$1328,5,0))) -> 5.95 | E125: 1 | F125: 1 | G125: =IF(E125>0,(F125/E125),"") -> 1 | H125: =IF(E125>0,(100%-G125),"") -> 0 | I125: =IF(C125>0,(H125*C125/G125),"") -> 0 | J125: =IF(C125>0,(C125+I125),"") -> 0.02 | K125: =IF(D125>0,(D125*J125),"") -> 0.119
B126: Sal negra en escamas. | C126: 0.005 | D126: =IF(ISNA(VLOOKUP(B126,'Listado de Artículos'!$B$16:$F$1328,5,0)),0,(VLOOKUP(B126,'Listado de Artículos'!$B$16:$F$1328,5,0))) -> 5.78 | E126: 1 | F126: 1 | G126: =IF(E126>0,(F126/E126),"") -> 1 | H126: =IF(E126>0,(100%-G126),"") -> 0 | I126: =IF(C126>0,(H126*C126/G126),"") -> 0 | J126: =IF(C126>0,(C126+I126),"") -> 0.005 | K126: =IF(D126>0,(D126*J126),"") -> 0.0289
C129: CALÇOTADA MAS BORONAT
C130: FICHA TÉCNICA PLATO
C133: ARTÍCULO | D133: SALSA ROMESCO PARA CALÇOTS.
C134: TAPA | D134: ELABORADOS.
C135: KG | D135: 15 | E135: Coste TOTAL | G135: =SUM(K138:K149) -> 346.638 | H135: Coste KG | J135: =G135/D135 -> 23.1092
B137: ARTICULO | C137: KG | D137: €/UN | E137: BRUTO | F137: NETO | G137: %NETO | H137: %DESP | I137: DESP | J137: SUCIO | K137: € / RACION
B138: Tomate Maduro. | C138: 12 | D138: =IF(ISNA(VLOOKUP(B138,'Listado de Artículos'!$B$16:$F$1328,5,0)),0,(VLOOKUP(B138,'Listado de Artículos'!$B$16:$F$1328,5,0))) -> 13.9 | E138: 1 | F138: 1 | G138: =IF(E138>0,(F138/E138),"") -> 1 | H138: =IF(E138>0,(100%-G138),"") -> 0 | I138: =IF(C138>0,(H138*C138/G138),"") -> 0 | J138: =IF(C138>0,(C138+I138),"") -> 12 | K138: =IF(D138>0,(D138*J138),"") -> 166.8
B139: Ajo rojo extra a granel. | C139: 1.4 | D139: =IF(ISNA(VLOOKUP(B139,'Listado de Artículos'!$B$16:$F$1328,5,0)),0,(VLOOKUP(B139,'Listado de Artículos'!$B$16:$F$1328,5,0))) -> 2 | E139: 1 | F139: 1 | G139: =IF(E139>0,(F139/E139),"") -> 1 | H139: =IF(E139>0,(100%-G139),"") -> 0 | I139: =IF(C139>0,(H139*C139/G139),"") -> 0 | J139: =IF(C139>0,(C139+I139),"") -> 1.4 | K139: =IF(D139>0,(D139*J139),"") -> 2.8
B140: ACEITE DE OLIVA SUAVE 5 LT | C140: 3 | D140: =IF(ISNA(VLOOKUP(B140,'Listado de Artículos'!$B$16:$F$1328,5,0)),0,(VLOOKUP(B140,'Listado de Artículos'!$B$16:$F$1328,5,0))) -> 5.95 | E140: 1 | F140: 1 | G140: =IF(E140>0,(F140/E140),"") -> 1 | H140: =IF(E140>0,(100%-G140),"") -> 0 | I140: =IF(C140>0,(H140*C140/G140),"") -> 0 | J140: =IF(C140>0,(C140+I140),"") -> 3 | K140: =IF(D140>0,(D140*J140),"") -> 17.85
B141: ACEITE DE OLIVA VIRGEN EXTRA SALOMO . | C141: 3 | D141: =IF(ISNA(VLOOKUP(B141,'Listado de Artículos'!$B$16:$F$1328,5,0)),0,(VLOOKUP(B141,'Listado de Artículos'!$B$16:$F$1328,5,0))) -> 8.97 | E141: 1 | F141: 1 | G141: =IF(E141>0,(F141/E141),"") -> 1 | H141: =IF(E141>0,(100%-G141),"") -> 0 | I141: =IF(C141>0,(H141*C141/G141),"") -> 0 | J141: =IF(C141>0,(C141+I141),"") -> 3 | K141: =IF(D141>0,(D141*J141),"") -> 26.91
B142: Almendra tostada repelada | C142: 1.5 | D142: =IF(ISNA(VLOOKUP(B142,'Listado de Artículos'!$B$16:$F$1328,5,0)),0,(VLOOKUP(B142,'Listado de Artículos'!$B$16:$F$1328,5,0))) -> 85.56 | E142: 1 | F142: 1 | G142: =IF(E142>0,(F142/E142),"") -> 1 | H142: =IF(E142>0,(100%-G142),"") -> 0 | I142: =IF(C142>0,(H142*C142/G142),"") -> 0 | J142: =IF(C142>0,(C142+I142),"") -> 1.5 | K142: =IF(D142>0,(D142*J142),"") -> 128.34
B143: AVELLANA TOSTADA PELADA. | C143: 1.5 | D143: =IF(ISNA(VLOOKUP(B143,'Listado de Artículos'!$B$16:$F$1328,5,0)),0,(VLOOKUP(B143,'Listado de Artículos'!$B$16:$F$1328,5,0))) -> 1.15 | E143: 1 | F143: 1 | G143: =IF(E143>0,(F143/E143),"") -> 1 | H143: =IF(E143>0,(100%-G143),"") -> 0 | I143: =IF(C143>0,(H143*C143/G143),"") -> 0 | J143: =IF(C143>0,(C143+I143),"") -> 1.5 | K143: =IF(D143>0,(D143*J143),"") -> 1.725
B144: PIMENTON DULCE DE LA VERA | C144: 0.025 | D144: =IF(ISNA(VLOOKUP(B144,'Listado de Artículos'!$B$16:$F$1328,5,0)),0,(VLOOKUP(B144,'Listado de Artículos'!$B$16:$F$1328,5,0))) -> 23 | E144: 1 | F144: 1 | G144: =IF(E144>0,(F144/E144),"") -> 1 | H144: =IF(E144>0,(100%-G144),"") -> 0 | I144: =IF(C144>0,(H144*C144/G144),"") -> 0 | J144: =IF(C144>0,(C144+I144),"") -> 0.025 | K144: =IF(D144>0,(D144*J144),"") -> 0.575
...

Sheet MENU CALÇOTADA
A2: MENU CALÇOTADA CARTA. 15-12-25
A4: APERITIVO. | B4: P.V.P | C4: NETO | D4: COSTO | E4: FOOD COST
A5: CALÇOTADA. APERITIVO CARTA | B5: GR O KG. | C5: PRECIO KG | D5: EUROS/RACION.
A6: Aperitivo completo para calçotada. | B6: 1 | C6: =IF(ISNA(VLOOKUP(A6,'Listado de Artículos'!$B$16:$F$1328,5,0)),0,(VLOOKUP(A6,'Listado de Artículos'!$B$16:$F$1328,5,0))) -> 0.44 | D6: =B6*C6 -> 0.44
A7: MENU Calçotada Vermuth | B7: 1 | C7: =IF(ISNA(VLOOKUP(A7,'Listado de Artículos'!$B$16:$F$1328,5,0)),0,(VLOOKUP(A7,'Listado de Artículos'!$B$16:$F$1328,5,0))) -> 0.47 | D7: =B7*C7 -> 0.47
A8: Agua Fon vella 1 LT Caja de 12 unid. | B8: 0.25 | C8: =IF(ISNA(VLOOKUP(A8,'Listado de Artículos'!$B$16:$F$1328,5,0)),0,(VLOOKUP(A8,'Listado de Artículos'!$B$16:$F$1328,5,0))) -> 0.8 | D8: =B8*C8 -> 0.2
A9: Vino negro Calçotada. BAG IN BOX. 20 LT. NEGRO. CELLER MAS ROIG. (35,57€). | B9: 0.35 | C9: 2.38 | D9: =B9*C9 -> 0.833
A10: CALÇOTADA ILIMITADA.
A11: Calçots Valls. Majols. crudos | B11: 15 | C11: =IF(ISNA(VLOOKUP(A11,'Listado de Artículos'!$B$16:$F$1328,5,0)),0,(VLOOKUP(A11,'Listado de Artículos'!$B$16:$F$1328,5,0))) -> 0.16 | D11: =B11*C11 -> 2.4
A12: Salsa romesco. | B12: 0.125 | C12: =IF(ISNA(VLOOKUP(A12,'Listado de Artículos'!$B$16:$F$1328,5,0)),0,(VLOOKUP(A12,'Listado de Artículos'!$B$16:$F$1328,5,0))) -> 2.94 | D12: =B12*C12 -> 0.3675
A13: EN MESA.
A14: Ensalada para calçotada terminada lechuga de pages. | B14: 1 | C14: =IF(ISNA(VLOOKUP(A14,'Listado de Artículos'!$B$16:$F$1328,5,0)),0,(VLOOKUP(A14,'Listado de Artículos'!$B$16:$F$1328,5,0))) -> 0.7 | D14: =B14*C14 -> 0.7
A15: MENU CALÇOTADA. CESTA DE PAN, TOMATE Y AJO. | B15: 1 | C15: =IF(ISNA(VLOOKUP(A15,'Listado de Artículos'!$B$16:$F$1328,5,0)),0,(VLOOKUP(A15,'Listado de Artículos'!$B$16:$F$1328,5,0))) -> 0.54 | D15: =B15*C15 -> 0.54
A16: MENU CALÇOTADA BOTIFARRA MONGETES BLANCAS | B16: 1 | C16: =IF(ISNA(VLOOKUP(A16,'Listado de Artículos'!$B$16:$F$1328,5,0)),0,(VLOOKUP(A16,'Listado de Artículos'!$B$16:$F$1328,5,0))) -> 0.84 | D16: =B16*C16 -> 0.84
A17: Salsa Allioli. natural. bote de 1 lt. | B17: 0.03 | C17: =IF(ISNA(VLOOKUP(A17,'Listado de Artículos'!$B$16:$F$1328,5,0)),0,(VLOOKUP(A17,'Listado de Artículos'!$B$16:$F$1328,5,0))) -> 3.85 | D17: =B17*C17 -> 0.1155
A18: PRINCIPAL
A19: MENU CALÇOTADA CORDERO Y BOTIFARRA NEGRA. | B19: 1 | C19: =IF(ISNA(VLOOKUP(A19,'Listado de Artículos'!$B$16:$F$1328,5,0)),0,(VLOOKUP(A19,'Listado de Artículos'!$B$16:$F$1328,5,0))) -> 2.8824 | D19: =B19*C19 -> 2.8824
A20: MENU CALÇOTADA GUARNICION DE CORDERO. | B20: 1 | C20: =IF(ISNA(VLOOKUP(A20,'Listado de Artículos'!$B$16:$F$1328,5,0)),0,(VLOOKUP(A20,'Listado de Artículos'!$B$16:$F$1328,5,0))) -> 0.96 | D20: =B20*C20 -> 0.96
A21: POSTRES
A22: Crema Catalana. | B22: 1 | C22: =IF(ISNA(VLOOKUP(A22,'Listado de Artículos'!$B$16:$F$1328,5,0)),0,(VLOOKUP(A22,'Listado de Artículos'!$B$16:$F$1328,5,0))) -> 0.5 | D22: =B22*C22 -> 0.5
A23: MENU CALÇOTADA NARANJA CON MIEL. POR PAX. | B23: 1 | C23: =IF(ISNA(VLOOKUP(A23,'Listado de Artículos'!$B$16:$F$1328,5,0)),0,(VLOOKUP(A23,'Listado de Artículos'!$B$16:$F$1328,5,0))) -> 0.37 | D23: =B23*C23 -> 0.37
A24: POSTRES
A25: CLOS PINELL TERRA TINTO ALTA | B25: 0.25 | C25: =IF(ISNA(VLOOKUP(A25,'Listado de Artículos'!$B$16:$F$1328,5,0)),0,(VLOOKUP(A25,'Listado de Artículos'!$B$16:$F$1328,5,0))) -> 0.9 | D25: =B25*C25 -> 0.225
A26: CAVA ROGER DE FLOR | B26: 0.15 | C26: =IF(ISNA(VLOOKUP(A26,'Listado de Artículos'!$B$16:$F$1328,5,0)),0,(VLOOKUP(A26,'Listado de Artículos'!$B$16:$F$1328,5,0))) -> 0 | D26: =B26*C26 -> 0
A27: Cafe Natural. 1 kg. 120 cafes. 24,48€ .kg. 0,22 unid | B27: 1 | C27: =IF(ISNA(VLOOKUP(A27,'Listado de Artículos'!$B$16:$F$1328,5,0)),0,(VLOOKUP(A27,'Listado de Artículos'!$B$16:$F$1328,5,0))) -> 0.65 | D27: =B27*C27 -> 0.65
B28: 0.3 | C28: =IF(ISNA(VLOOKUP(A28,'Listado de Artículos'!$B$16:$F$1328,5,0)),0,(VLOOKUP(A28,'Listado de Artículos'!$B$16:$F$1328,5,0))) -> 0 | D28: =B28*C28 -> 0
A30: ESCANDALLO | B30: 49.9 | C30: =B30/1.1 -> 45.363636 | D30: =SUM(D6:D29) -> 12.4934 | E30: =(D30*100/C30)/100 -> 0.27540561

Sheet Hoja 1

Sheet M.P Aperitivos
B3: Boda 31-1
B4: FICHA TÉCNICA PLATO
B7: ARTÍCULO | C7: Patatas Bravas
B8: TAPA | C8: ELABORADOS | G8: PRECIO DE VENTA P.V.P
B9: unid. | C9: 1 | D9: Coste TOTAL | F9: =SUM(J12:J18) -> 1.5774 | G9: Coste UNID: | I9: =F9/C9 -> 1.5774
A11: ARTICULO | B11: KG | C11: €/UN | D11: BRUTO | E11: NETO | F11: %NETO | G11: %DESP | H11: DESP | I11: SUCIO | J11: € / RACION
A12: Patata Monalisa. | B12: 0.35 | C12: =IF(ISNA(VLOOKUP(A12,'Listado de Artículos'!$B$16:$F$1328,5,0)),0,(VLOOKUP(A12,'Listado de Artículos'!$B$16:$F$1328,5,0))) -> 2 | D12: 1 | E12: 1 | F12: =IF(D12>0,(E12/D12),"") -> 1 | G12: 0.005 | H12: =IF(B12>0,(G12*B12/F12),"") -> 0.00175 | I12: =IF(B12>0,(B12+H12),"") -> 0.35175 | J12: =IF(C12>0,(C12*I12),"") -> 0.7035
A13: Salsa Brava. bote de 1,850. precio bote 5,20€. Coosur. | B13: 0.1 | C13: =IF(ISNA(VLOOKUP(A13,'Listado de Artículos'!$B$16:$F$1328,5,0)),0,(VLOOKUP(A13,'Listado de Artículos'!$B$16:$F$1328,5,0))) -> 1.55 | D13: 1 | E13: 1 | F13: =IF(D13>0,(E13/D13),"") -> 1 | G13: =IF(D13>0,(100%-F13),"") -> 0 | H13: =IF(B13>0,(G13*B13/F13),"") -> 0 | I13: =IF(B13>0,(B13+H13),"") -> 0.1 | J13: =IF(C13>0,(C13*I13),"") -> 0.155
A14: Sal negra en escamas. | B14: 0.005 | C14: =IF(ISNA(VLOOKUP(A14,'Listado de Artículos'!$B$16:$F$1328,5,0)),0,(VLOOKUP(A14,'Listado de Artículos'!$B$16:$F$1328,5,0))) -> 5.78 | D14: 1 | E14: 1 | F14: =IF(D14>0,(E14/D14),"") -> 1 | G14: =IF(D14>0,(100%-F14),"") -> 0 | H14: =IF(B14>0,(G14*B14/F14),"") -> 0 | I14: =IF(B14>0,(B14+H14),"") -> 0.005 | J14: =IF(C14>0,(C14*I14),"") -> 0.0289
A15: Pimiento del padron. | B15: 0.1 | C15: =IF(ISNA(VLOOKUP(A15,'Listado de Artículos'!$B$16:$F$1328,5,0)),0,(VLOOKUP(A15,'Listado de Artículos'!$B$16:$F$1328,5,0))) -> 6.9 | D15: 1 | E15: 1 | F15: =IF(D15>0,(E15/D15),"") -> 1 | G15: =IF(D15>0,(100%-F15),"") -> 0 | H15: =IF(B15>0,(G15*B15/F15),"") -> 0 | I15: =IF(B15>0,(B15+H15),"") -> 0.1 | J15: =IF(C15>0,(C15*I15),"") -> 0.69
B22: ARTÍCULO | C22: Tabla de queso con pan de cristal
B23: TAPA | C23: ELABORADOS | G23: PRECIO DE VENTA P.V.P
B24: unid. | C24: 1 | D24: Coste TOTAL | F24: =SUM(J27:J37) -> 8.791 | G24: Coste UNID: | I24: =F24/C24 -> 8.791
A26: ARTICULO | B26: KG | C26: €/UN | D26: BRUTO | E26: NETO | F26: %NETO | G26: %DESP | H26: DESP | I26: SUCIO | J26: € / RACION
A27: Queso Altejo moli de ger Vaca. | B27: 0.07 | C27: =IF(ISNA(VLOOKUP(A27,'Listado de Artículos'!$B$16:$F$1328,5,0)),0,(VLOOKUP(A27,'Listado de Artículos'!$B$16:$F$1328,5,0))) -> 0.03 | D27: 1 | E27: 1 | F27: =IF(D27>0,(E27/D27),"") -> 1 | G27: =IF(D27>0,(100%-F27),"") -> 0 | H27: =IF(B27>0,(G27*B27/F27),"") -> 0 | I27: =IF(B27>0,(B27+H27),"") -> 0.07 | J27: =IF(C27>0,(C27*I27),"") -> 0.0021
A28: Queso Garrotxa Cabra. Bauma. | B28: 0.04 | C28: =IF(ISNA(VLOOKUP(A28,'Listado de Artículos'!$B$16:$F$1328,5,0)),0,(VLOOKUP(A28,'Listado de Artículos'!$B$16:$F$1328,5,0))) -> 0.01 | D28: 1 | E28: 1 | F28: =IF(D28>0,(E28/D28),"") -> 1 | G28: =IF(D28>0,(100%-F28),"") -> 0 | H28: =IF(B28>0,(G28*B28/F28),"") -> 0 | I28: =IF(B28>0,(B28+H28),"") -> 0.04 | J28: =IF(C28>0,(C28*I28),"") -> 0.0004
A29: Queso Azul Blau Cereta. Moli de ger. | B29: 0.03 | C29: =IF(ISNA(VLOOKUP(A29,'Listado de Artículos'!$B$16:$F$1328,5,0)),0,(VLOOKUP(A29,'Listado de Artículos'!$B$16:$F$1328,5,0))) -> 2.95 | D29: 1 | E29: 1 | F29: =IF(D29>0,(E29/D29),"") -> 1 | G29: =IF(D29>0,(100%-F29),"") -> 0 | H29: =IF(B29>0,(G29*B29/F29),"") -> 0 | I29: =IF(B29>0,(B29+H29),"") -> 0.03 | J29: =IF(C29>0,(C29*I29),"") -> 0.0885
A30: Pan cristal precortado. (3,200 gr). 64 *50. 26,78€ Caja. 0,20€ medio trozo. | B30: 3 | C30: =IF(ISNA(VLOOKUP(A30,'Listado de Artículos'!$B$16:$F$1328,5,0)),0,(VLOOKUP(A30,'Listado de Artículos'!$B$16:$F$1328,5,0))) -> 2.9 | D30: 1 | E30: 1 | F30: =IF(D30>0,(E30/D30),"") -> 1 | G30: =IF(D30>0,(100%-F30),"") -> 0 | H30: =IF(B30>0,(G30*B30/F30),"") -> 0 | I30: =IF(B30>0,(B30+H30),"") -> 3 | J30: =IF(C30>0,(C30*I30),"") -> 8.7
B31: 0.3 | C31: =IF(ISNA(VLOOKUP(A31,'Listado de Artículos'!$B$16:$F$1328,5,0)),0,(VLOOKUP(A31,'Listado de Artículos'!$B$16:$F$1328,5,0))) -> 0 | D31: 1 | E31: 1 | F31: =IF(D31>0,(E31/D31),"") -> 1 | G31: =IF(D31>0,(100%-F31),"") -> 0 | H31: =IF(B31>0,(G31*B31/F31),"") -> 0 | I31: =IF(B31>0,(B31+H31),"") -> 0.3 | J31: =IF(C31>0,(C31*I31),"")
B32: 0.25 | C32: =IF(ISNA(VLOOKUP(A32,'Listado de Artículos'!$B$16:$F$1328,5,0)),0,(VLOOKUP(A32,'Listado de Artículos'!$B$16:$F$1328,5,0))) -> 0 | D32: 1 | E32: 1 | F32: =IF(D32>0,(E32/D32),"") -> 1 | G32: =IF(D32>0,(100%-F32),"") -> 0 | H32: =IF(B32>0,(G32*B32/F32),"") -> 0 | I32: =IF(B32>0,(B32+H32),"") -> 0.25 | J32: =IF(C32>0,(C32*I32),"")
B33: 1 | C33: =IF(ISNA(VLOOKUP(A33,'Listado de Artículos'!$B$16:$F$1328,5,0)),0,(VLOOKUP(A33,'Listado de Artículos'!$B$16:$F$1328,5,0))) -> 0 | D33: 1 | E33: 1 | F33: =IF(D33>0,(E33/D33),"") -> 1 | G33: =IF(D33>0,(100%-F33),"") -> 0 | H33: =IF(B33>0,(G33*B33/F33),"") -> 0 | I33: =IF(B33>0,(B33+H33),"") -> 1 | J33: =IF(C33>0,(C33*I33),"")
B34: 1 | C34: =IF(ISNA(VLOOKUP(A34,'Listado de Artículos'!$B$16:$F$1328,5,0)),0,(VLOOKUP(A34,'Listado de Artículos'!$B$16:$F$1328,5,0))) -> 0 | D34: 1 | E34: 1 | F34: =IF(D34>0,(E34/D34),"") -> 1 | G34: =IF(D34>0,(100%-F34),"") -> 0 | H34: =IF(B34>0,(G34*B34/F34),"") -> 0 | I34: =IF(B34>0,(B34+H34),"") -> 1 | J34: =IF(C34>0,(C34*I34),"")
B35: 1 | C35: =IF(ISNA(VLOOKUP(A35,'Listado de Artículos'!$B$16:$F$1328,5,0)),0,(VLOOKUP(A35,'Listado de Artículos'!$B$16:$F$1328,5,0))) -> 0 | D35: 1 | E35: 1 | F35: =IF(D35>0,(E35/D35),"") -> 1 | G35: =IF(D35>0,(100%-F35),"") -> 0 | H35: =IF(B35>0,(G35*B35/F35),"") -> 0 | I35: =IF(B35>0,(B35+H35),"") -> 1 | J35: =IF(C35>0,(C35*I35),"")
B36: 1 | C36: =IF(ISNA(VLOOKUP(A36,'Listado de Artículos'!$B$16:$F$1328,5,0)),0,(VLOOKUP(A36,'Listado de Artículos'!$B$16:$F$1328,5,0))) -> 0 | D36: 1 | E36: 1 | F36: =IF(D36>0,(E36/D36),"") -> 1 | G36: =IF(D36>0,(100%-F36),"") -> 0 | H36: =IF(B36>0,(G36*B36/F36),"") -> 0 | I36: =IF(B36>0,(B36+H36),"") -> 1 | J36: =IF(C36>0,(C36*I36),"")
B37: 2 | C37: =IF(ISNA(VLOOKUP(A37,'Listado de Artículos'!$B$16:$F$1328,5,0)),0,(VLOOKUP(A37,'Listado de Artículos'!$B$16:$F$1328,5,0))) -> 0 | D37: 1 | E37: 1 | F37: =IF(D37>0,(E37/D37),"") -> 1 | G37: =IF(D37>0,(100%-F37),"") -> 0 | H37: =IF(B37>0,(G37*B37/F37),"") -> 0 | I37: =IF(B37>0,(B37+H37),"") -> 2 | J37: =IF(C37>0,(C37*I37),"")
A39: =1500/60 -> 25
B41: ARTÍCULO | C41: Tabla de jamón iberico con pan de cristal
B42: TAPA | C42: ELABORADOS | G42: PRECIO DE VENTA P.V.P
B43: unid. | C43: 1 | D43: Coste TOTAL | F43: =SUM(J46:J48) -> 10.025 | G43: Coste UNID: | I43: =F43/C43 -> 10.025
A45: ARTICULO | B45: KG | C45: €/UN | D45: BRUTO | E45: NETO | F45: %NETO | G45: %DESP | H45: DESP | I45: SUCIO | J45: € / RACION
A46: Paletilla jamón casa marcial | B46: 0.15 | C46: =IF(ISNA(VLOOKUP(A46,'Listado de Artículos'!$B$16:$F$1328,5,0)),0,(VLOOKUP(A46,'Listado de Artículos'!$B$16:$F$1328,5,0))) -> 7.6 | D46: 1 | E46: 1 | F46: =IF(D46>0,(E46/D46),"") -> 1 | G46: =IF(D46>0,(100%-F46),"") -> 0 | H46: =IF(B46>0,(G46*B46/F46),"") -> 0 | I46: =IF(B46>0,(B46+H46),"") -> 0.15 | J46: =IF(C46>0,(C46*I46),"") -> 1.14
A47: Pan cristal precortado. (3,200 gr). 64 *50. 26,78€ Caja. 0,20€ medio trozo. | B47: 3 | C47: =IF(ISNA(VLOOKUP(A47,'Listado de Artículos'!$B$16:$F$1328,5,0)),0,(VLOOKUP(A47,'Listado de Artículos'!$B$16:$F$1328,5,0))) -> 2.9 | D47: 1 | E47: 1 | F47: =IF(D47>0,(E47/D47),"") -> 1 | G47: =IF(D47>0,(100%-F47),"") -> 0 | H47: =IF(B47>0,(G47*B47/F47),"") -> 0 | I47: =IF(B47>0,(B47+H47),"") -> 3 | J47: =IF(C47>0,(C47*I47),"") -> 8.7
A48: Tomate rallado | B48: 0.1 | C48: =IF(ISNA(VLOOKUP(A48,'Listado de Artículos'!$B$16:$F$1328,5,0)),0,(VLOOKUP(A48,'Listado de Artículos'!$B$16:$F$1328,5,0))) -> 1.85 | D48: 1 | E48: 1 | F48: =IF(D48>0,(E48/D48),"") -> 1 | G48: =IF(D48>0,(100%-F48),"") -> 0 | H48: =IF(B48>0,(G48*B48/F48),"") -> 0 | I48: =IF(B48>0,(B48+H48),"") -> 0.1 | J48: =IF(C48>0,(C48*I48),"") -> 0.185
B51: ARTÍCULO | C51: Fingers pollo
B52: TAPA | C52: ELABORADOS | G52: PRECIO DE VENTA P.V.P
B53: unid. | C53: 1 | D53: Coste TOTAL | F53: =SUM(J56:J59) -> 1.1475 | G53: Coste UNID: | I53: =F53/C53 -> 1.1475
A55: ARTICULO | B55: KG | C55: €/UN | D55: BRUTO | E55: NETO | F55: %NETO | G55: %DESP | H55: DESP | I55: SUCIO | J55: € / RACION
A56: Finger solomillo pollo rebozado. caja de 4 kg. 45,19€ | B56: 0.15 | C56: =IF(ISNA(VLOOKUP(A56,'Listado de Artículos'!$B$16:$F$1328,5,0)),0,(VLOOKUP(A56,'Listado de Artículos'!$B$16:$F$1328,5,0))) -> 6.25 | D56: 1 | E56: 1 | F56: =IF(D56>0,(E56/D56),"") -> 1 | G56: =IF(D56>0,(100%-F56),"") -> 0 | H56: =IF(B56>0,(G56*B56/F56),"") -> 0 | I56: =IF(B56>0,(B56+H56),"") -> 0.15 | J56: =IF(C56>0,(C56*I56),"") -> 0.9375
A57: Mayonesa. bote 750 ml. MAKRO. | B57: 0.2 | C57: =IF(ISNA(VLOOKUP(A57,'Listado de Artículos'!$B$16:$F$1328,5,0)),0,(VLOOKUP(A57,'Listado de Artículos'!$B$16:$F$1328,5,0))) -> 1.05 | D57: 1 | E57: 1 | F57: =IF(D57>0,(E57/D57),"") -> 1 | G57: =IF(D57>0,(100%-F57),"") -> 0 | H57: =IF(B57>0,(G57*B57/F57),"") -> 0 | I57: =IF(B57>0,(B57+H57),"") -> 0.2 | J57: =IF(C57>0,(C57*I57),"") -> 0.21
B58: 0.04 | C58: =IF(ISNA(VLOOKUP(A58,'Listado de Artículos'!$B$16:$F$1328,5,0)),0,(VLOOKUP(A58,'Listado de Artículos'!$B$16:$F$1328,5,0))) -> 0 | D58: 1 | E58: 1 | F58: =IF(D58>0,(E58/D58),"") -> 1 | G58: =IF(D58>0,(100%-F58),"") -> 0 | H58: =IF(B58>0,(G58*B58/F58),"") -> 0 | I58: =IF(B58>0,(B58+H58),"") -> 0.04 | J58: =IF(C58>0,(C58*I58),"")
B59: 2 | C59: =IF(ISNA(VLOOKUP(A59,'Listado de Artículos'!$B$16:$F$1328,5,0)),0,(VLOOKUP(A59,'Listado de Artículos'!$B$16:$F$1328,5,0))) -> 0 | D59: 1 | E59: 1 | F59: =IF(D59>0,(E59/D59),"") -> 1 | G59: =IF(D59>0,(100%-F59),"") -> 0 | H59: =IF(B59>0,(G59*B59/F59),"") -> 0 | I59: =IF(B59>0,(B59+H59),"") -> 2 | J59: =IF(C59>0,(C59*I59),"")
M60: =9.25/32 -> 0.2890625
B62: ARTÍCULO | C62: Pulpo a la gallega
B63: TAPA | C63: ELABORADOS | G63: PRECIO DE VENTA P.V.P
B64: unid. | C64: 1 | D64: Coste TOTAL | F64: =SUM(J67:J69) -> 6.2985 | G64: Coste UNID: | I64: =F64/C64 -> 6.2985
A66: ARTICULO | B66: KG | C66: €/UN | D66: BRUTO | E66: NETO | F66: %NETO | G66: %DESP | H66: DESP | I66: SUCIO | J66: € / RACION
A67: Pata pulpo 250g | B67: 0.5 | C67: =IF(ISNA(VLOOKUP(A67,'Listado de Artículos'!$B$16:$F$1328,5,0)),0,(VLOOKUP(A67,'Listado de Artículos'!$B$16:$F$1328,5,0))) -> 10.5 | D67: 1 | E67: 1 | F67: =IF(D67>0,(E67/D67),"") -> 1 | G67: =IF(D67>0,(100%-F67),"") -> 0 | H67: =IF(B67>0,(G67*B67/F67),"") -> 0 | I67: =IF(B67>0,(B67+H67),"") -> 0.5 | J67: =IF(C67>0,(C67*I67),"") -> 5.25
A68: Patata Monalisa. | B68: 0.3 | C68: =IF(ISNA(VLOOKUP(A68,'Listado de Artículos'!$B$16:$F$1328,5,0)),0,(VLOOKUP(A68,'Listado de Artículos'!$B$16:$F$1328,5,0))) -> 2 | D68: 1 | E68: 1 | F68: =IF(D68>0,(E68/D68),"") -> 1 | G68: =IF(D68>0,(100%-F68),"") -> 0 | H68: =IF(B68>0,(G68*B68/F68),"") -> 0 | I68: =IF(B68>0,(B68+H68),"") -> 0.3 | J68: =IF(C68>0,(C68*I68),"") -> 0.6
A69: ACEITE DE OLIVA VIRGEN EXTRA SALOMO . | B69: 0.05 | C69: =IF(ISNA(VLOOKUP(A69,'Listado de Artículos'!$B$16:$F$1328,5,0)),0,(VLOOKUP(A69,'Listado de Artículos'!$B$16:$F$1328,5,0))) -> 8.97 | D69: 1 | E69: 1 | F69: =IF(D69>0,(E69/D69),"") -> 1 | G69: =IF(D69>0,(100%-F69),"") -> 0 | H69: =IF(B69>0,(G69*B69/F69),"") -> 0 | I69: =IF(B69>0,(B69+H69),"") -> 0.05 | J69: =IF(C69>0,(C69*I69),"") -> 0.4485
B73: ARTÍCULO | C73: Tabla de quesos
B74: TAPA | C74: ELABORADOS | G74: PRECIO DE VENTA P.V.P
B75: unid. | C75: 10 | D75: Coste TOTAL | F75: =SUM(J78:J82) -> 9.134 | G75: Coste UNID: | I75: =F75/C75 -> 0.9134
A77: ARTICULO | B77: KG | C77: €/UN | D77: BRUTO | E77: NETO | F77: %NETO | G77: %DESP | H77: DESP | I77: SUCIO | J77: € / RACION
A78: Queso Altejo moli de ger Vaca. | B78: 0.4 | C78: =IF(ISNA(VLOOKUP(A78,'Listado de Artículos'!$B$16:$F$1328,5,0)),0,(VLOOKUP(A78,'Listado de Artículos'!$B$16:$F$1328,5,0))) -> 0.03 | D78: 1 | E78: 1 | F78: =IF(D78>0,(E78/D78),"") -> 1 | G78: =IF(D78>0,(100%-F78),"") -> 0 | H78: =IF(B78>0,(G78*B78/F78),"") -> 0 | I78: =IF(B78>0,(B78+H78),"") -> 0.4 | J78: =IF(C78>0,(C78*I78),"") -> 0.012
A79: Queso Garrotxa Cabra. Bauma. | B79: 0.7 | C79: =IF(ISNA(VLOOKUP(A79,'Listado de Artículos'!$B$16:$F$1328,5,0)),0,(VLOOKUP(A79,'Listado de Artículos'!$B$16:$F$1328,5,0))) -> 0.01 | D79: 1 | E79: 1 | F79: =IF(D79>0,(E79/D79),"") -> 1 | G79: =IF(D79>0,(100%-F79),"") -> 0 | H79: =IF(B79>0,(G79*B79/F79),"") -> 0 | I79: =IF(B79>0,(B79+H79),"") -> 0.7 | J79: =IF(C79>0,(C79*I79),"") -> 0.007
A80: Queso Azul Blau Cereta. Moli de ger. | B80: 0.2 | C80: =IF(ISNA(VLOOKUP(A80,'Listado de Artículos'!$B$16:$F$1328,5,0)),0,(VLOOKUP(A80,'Listado de Artículos'!$B$16:$F$1328,5,0))) -> 2.95 | D80: 1 | E80: 1 | F80: =IF(D80>0,(E80/D80),"") -> 1 | G80: =IF(D80>0,(100%-F80),"") -> 0 | H80: =IF(B80>0,(G80*B80/F80),"") -> 0 | I80: =IF(B80>0,(B80+H80),"") -> 0.2 | J80: =IF(C80>0,(C80*I80),"") -> 0.59
A81: Palitos pan | B81: 0.5 | C81: =IF(ISNA(VLOOKUP(A81,'Listado de Artículos'!$B$16:$F$1328,5,0)),0,(VLOOKUP(A81,'Listado de Artículos'!$B$16:$F$1328,5,0))) -> 17.05 | D81: 1 | E81: 1 | F81: =IF(D81>0,(E81/D81),"") -> 1 | G81: =IF(D81>0,(100%-F81),"") -> 0 | H81: =IF(B81>0,(G81*B81/F81),"") -> 0 | I81: =IF(B81>0,(B81+H81),"") -> 0.5 | J81: =IF(C81>0,(C81*I81),"") -> 8.525
A82: A.AAAAA | B82: 0.14 | C82: =IF(ISNA(VLOOKUP(A82,'Listado de Artículos'!$B$16:$F$1328,5,0)),0,(VLOOKUP(A82,'Listado de Artículos'!$B$16:$F$1328,5,0))) -> 0 | D82: 1 | E82: 1 | F82: =IF(D82>0,(E82/D82),"") -> 1 | G82: =IF(D82>0,(100%-F82),"") -> 0 | H82: =IF(B82>0,(G82*B82/F82),"") -> 0 | I82: =IF(B82>0,(B82+H82),"") -> 0.14 | J82: =IF(C82>0,(C82*I82),"")
B86: ARTÍCULO | C86: Brocheta langostino
B87: TAPA | C87: ELABORADOS | G87: PRECIO DE VENTA P.V.P
B88: unid. | C88: 58 | D88: Coste TOTAL | F88: =SUM(J91:J96) -> 43.856 | G88: Coste UNID: | I88: =F88/C88 -> 0.75613793
A90: ARTICULO | B90: KG | C90: €/UN | D90: BRUTO | E90: NETO | F90: %NETO | G90: %DESP | H90: DESP | I90: SUCIO | J90: € / RACION
A91: Gamba paella | B91: 3 | C91: =IF(ISNA(VLOOKUP(A91,'Listado de Artículos'!$B$16:$F$1328,5,0)),0,(VLOOKUP(A91,'Listado de Artículos'!$B$16:$F$1328,5,0))) -> 10.5 | D91: 1 | E91: 1 | F91: =IF(D91>0,(E91/D91),"") -> 1 | G91: =IF(D91>0,(100%-F91),"") -> 0 | H91: =IF(B91>0,(G91*B91/F91),"") -> 0 | I91: =IF(B91>0,(B91+H91),"") -> 3 | J91: =IF(C91>0,(C91*I91),"") -> 31.5
A92: Panko | B92: 1 | C92: =IF(ISNA(VLOOKUP(A92,'Listado de Artículos'!$B$16:$F$1328,5,0)),0,(VLOOKUP(A92,'Listado de Artículos'!$B$16:$F$1328,5,0))) -> 6.35 | D92: 1 | E92: 1 | F92: =IF(D92>0,(E92/D92),"") -> 1 | G92: =IF(D92>0,(100%-F92),"") -> 0 | H92: =IF(B92>0,(G92*B92/F92),"") -> 0 | I92: =IF(B92>0,(B92+H92),"") -> 1 | J92: =IF(C92>0,(C92*I92),"") -> 6.35
A93: Huevos pqt 6 Gavaldà | B93: 0.5 | C93: =IF(ISNA(VLOOKUP(A93,'Listado de Artículos'!$B$16:$F$1328,5,0)),0,(VLOOKUP(A93,'Listado de Artículos'!$B$16:$F$1328,5,0))) -> 2.19 | D93: 1 | E93: 1 | F93: =IF(D93>0,(E93/D93),"") -> 1 | G93: =IF(D93>0,(100%-F93),"") -> 0 | H93: =IF(B93>0,(G93*B93/F93),"") -> 0 | I93: =IF(B93>0,(B93+H93),"") -> 0.5 | J93: =IF(C93>0,(C93*I93),"") -> 1.095
A94: Aguacate | B94: 0.5 | C94: =IF(ISNA(VLOOKUP(A94,'Listado de Artículos'!$B$16:$F$1328,5,0)),0,(VLOOKUP(A94,'Listado de Artículos'!$B$16:$F$1328,5,0))) -> 5.65 | D94: 1 | E94: 1 | F94: =IF(D94>0,(E94/D94),"") -> 1 | G94: =IF(D94>0,(100%-F94),"") -> 0 | H94: =IF(B94>0,(G94*B94/F94),"") -> 0 | I94: =IF(B94>0,(B94+H94),"") -> 0.5 | J94: =IF(C94>0,(C94*I94),"") -> 2.825
A95: Mayonesa 2,2kg | B95: 0.1 | C95: =IF(ISNA(VLOOKUP(A95,'Listado de Artículos'!$B$16:$F$1328,5,0)),0,(VLOOKUP(A95,'Listado de Artículos'!$B$16:$F$1328,5,0))) -> 16.72 | D95: 1 | E95: 1 | F95: =IF(D95>0,(E95/D95),"") -> 1 | G95: =IF(D95>0,(100%-F95),"") -> 0 | H95: =IF(B95>0,(G95*B95/F95),"") -> 0 | I95: =IF(B95>0,(B95+H95),"") -> 0.1 | J95: =IF(C95>0,(C95*I95),"") -> 1.672
A96: Limones extra. | B96: 0.3 | C96: =IF(ISNA(VLOOKUP(A96,'Listado de Artículos'!$B$16:$F$1328,5,0)),0,(VLOOKUP(A96,'Listado de Artículos'!$B$16:$F$1328,5,0))) -> 1.38 | D96: 1 | E96: 1 | F96: =IF(D96>0,(E96/D96),"") -> 1 | G96: =IF(D96>0,(100%-F96),"") -> 0 | H96: =IF(B96>0,(G96*B96/F96),"") -> 0 | I96: =IF(B96>0,(B96+H96),"") -> 0.3 | J96: =IF(C96>0,(C96*I96),"") -> 0.414
B100: ARTÍCULO | C100: Crema calenta de tomàquet
B101: TAPA | C101: ELABORADOS | G101: PRECIO DE VENTA P.V.P
B102: unid. | C102: 58 | D102: Coste TOTAL | F102: =SUM(J105:J113) -> 101.8475 | G102: Coste UNID: | I102: =F102/C102 -> 1.7559914
A104: ARTICULO | B104: KG | C104: €/UN | D104: BRUTO | E104: NETO | F104: %NETO | G104: %DESP | H104: DESP | I104: SUCIO | J104: € / RACION
A105: Tomate Pera. | B105: 15 | C105: =IF(ISNA(VLOOKUP(A105,'Listado de Artículos'!$B$16:$F$1328,5,0)),0,(VLOOKUP(A105,'Listado de Artículos'!$B$16:$F$1328,5,0))) -> 1.5 | D105: 1 | E105: 1 | F105: =IF(D105>0,(E105/D105),"") -> 1 | G105: =IF(D105>0,(100%-F105),"") -> 0 | H105: =IF(B105>0,(G105*B105/F105),"") -> 0 | I105: =IF(B105>0,(B105+H105),"") -> 15 | J105: =IF(C105>0,(C105*I105),"") -> 22.5
A106: Ajo rojo pelado. pqt 1 kg. | B106: 0.2 | C106: =IF(ISNA(VLOOKUP(A106,'Listado de Artículos'!$B$16:$F$1328,5,0)),0,(VLOOKUP(A106,'Listado de Artículos'!$B$16:$F$1328,5,0))) -> 28.59 | D106: 1 | E106: 1 | F106: =IF(D106>0,(E106/D106),"") -> 1 | G106: =IF(D106>0,(100%-F106),"") -> 0 | H106: =IF(B106>0,(G106*B106/F106),"") -> 0 | I106: =IF(B106>0,(B106+H106),"") -> 0.2 | J106: =IF(C106>0,(C106*I106),"") -> 5.718
A107: Cebolla blanca. | B107: 3 | C107: =IF(ISNA(VLOOKUP(A107,'Listado de Artículos'!$B$16:$F$1328,5,0)),0,(VLOOKUP(A107,'Listado de Artículos'!$B$16:$F$1328,5,0))) -> 4.5 | D107: 1 | E107: 1 | F107: =IF(D107>0,(E107/D107),"") -> 1 | G107: =IF(D107>0,(100%-F107),"") -> 0 | H107: =IF(B107>0,(G107*B107/F107),"") -> 0 | I107: =IF(B107>0,(B107+H107),"") -> 3 | J107: =IF(C107>0,(C107*I107),"") -> 13.5
A108: ACEITE DE OLIVA SUAVE 5 LT | B108: 0.35 | C108: =IF(ISNA(VLOOKUP(A108,'Listado de Artículos'!$B$16:$F$1328,5,0)),0,(VLOOKUP(A108,'Listado de Artículos'!$B$16:$F$1328,5,0))) -> 5.95 | D108: 1 | E108: 1 | F108: =IF(D108>0,(E108/D108),"") -> 1 | G108: =IF(D108>0,(100%-F108),"") -> 0 | H108: =IF(B108>0,(G108*B108/F108),"") -> 0 | I108: =IF(B108>0,(B108+H108),"") -> 0.35 | J108: =IF(C108>0,(C108*I108),"") -> 2.0825
A109: Tomillo | B109: 0.14 | C109: =IF(ISNA(VLOOKUP(A109,'Listado de Artículos'!$B$16:$F$1328,5,0)),0,(VLOOKUP(A109,'Listado de Artículos'!$B$16:$F$1328,5,0))) -> 1.2 | D109: 1 | E109: 1 | F109: =IF(D109>0,(E109/D109),"") -> 1 | G109: =IF(D109>0,(100%-F109),"") -> 0 | H109: =IF(B109>0,(G109*B109/F109),"") -> 0 | I109: =IF(B109>0,(B109+H109),"") -> 0.14 | J109: =IF(C109>0,(C109*I109),"") -> 0.168
A110: AZUCAR | B110: 0.05 | C110: =IF(ISNA(VLOOKUP(A110,'Listado de Artículos'!$B$16:$F$1328,5,0)),0,(VLOOKUP(A110,'Listado de Artículos'!$B$16:$F$1328,5,0))) -> 0.82 | D110: 1 | E110: 1 | F110: =IF(D110>0,(E110/D110),"") -> 1 | G110: =IF(D110>0,(100%-F110),"") -> 0 | H110: =IF(B110>0,(G110*B110/F110),"") -> 0 | I110: =IF(B110>0,(B110+H110),"") -> 0.05 | J110: =IF(C110>0,(C110*I110),"") -> 0.041
A111: Variado de verduras. para caldo. makro | B111: 2 | C111: =IF(ISNA(VLOOKUP(A111,'Listado de Artículos'!$B$16:$F$1328,5,0)),0,(VLOOKUP(A111,'Listado de Artículos'!$B$16:$F$1328,5,0))) -> 1.99 | D111: 1 | E111: 1 | F111: =IF(D111>0,(E111/D111),"") -> 1 | G111: =IF(D111>0,(100%-F111),"") -> 0 | H111: =IF(B111>0,(G111*B111/F111),"") -> 0 | I111: =IF(B111>0,(B111+H111),"") -> 2 | J111: =IF(C111>0,(C111*I111),"") -> 3.98
A112: Picatiostes | B112: 0.2 | C112: =IF(ISNA(VLOOKUP(A112,'Listado de Artículos'!$B$16:$F$1328,5,0)),0,(VLOOKUP(A112,'Listado de Artículos'!$B$16:$F$1328,5,0))) -> 17.29 | D112: 1 | E112: 1 | F112: =IF(D112>0,(E112/D112),"") -> 1 | G112: =IF(D112>0,(100%-F112),"") -> 0 | H112: =IF(B112>0,(G112*B112/F112),"") -> 0 | I112: =IF(B112>0,(B112+H112),"") -> 0.2 | J112: =IF(C112>0,(C112*I112),"") -> 3.458
A113: Albahaca | B113: 2 | C113: =IF(ISNA(VLOOKUP(A113,'Listado de Artículos'!$B$16:$F$1328,5,0)),0,(VLOOKUP(A113,'Listado de Artículos'!$B$16:$F$1328,5,0))) -> 25.2 | D113: 1 | E113: 1 | F113: =IF(D113>0,(E113/D113),"") -> 1 | G113: =IF(D113>0,(100%-F113),"") -> 0 | H113: =IF(B113>0,(G113*B113/F113),"") -> 0 | I113: =IF(B113>0,(B113+H113),"") -> 2 | J113: =IF(C113>0,(C113*I113),"") -> 50.4
B117: ARTÍCULO | C117: Flor de alcachofa con jamón
B118: TAPA | C118: ELABORADOS | G118: PRECIO DE VENTA P.V.P
B119: unid. | C119: 58 | D119: Coste TOTAL | F119: =SUM(J122:J124) -> 22.85 | G119: Coste UNID: | I119: =F119/C119 -> 0.39396552
A121: ARTICULO | B121: KG | C121: €/UN | D121: BRUTO | E121: NETO | F121: %NETO | G121: %DESP | H121: DESP | I121: SUCIO | J121: € / RACION
A122: Carxofa confitada flor | B122: 6 | C122: =IF(ISNA(VLOOKUP(A122,'Listado de Artículos'!$B$16:$F$1328,5,0)),0,(VLOOKUP(A122,'Listado de Artículos'!$B$16:$F$1328,5,0))) -> 2.5 | D122: 1 | E122: 1 | F122: =IF(D122>0,(E122/D122),"") -> 1 | G122: =IF(D122>0,(100%-F122),"") -> 0 | H122: =IF(B122>0,(G122*B122/F122),"") -> 0 | I122: =IF(B122>0,(B122+H122),"") -> 6 | J122: =IF(C122>0,(C122*I122),"") -> 15
A123: Paletilla jamón casa marcial | B123: 0.25 | C123: =IF(ISNA(VLOOKUP(A123,'Listado de Artículos'!$B$16:$F$1328,5,0)),0,(VLOOKUP(A123,'Listado de Artículos'!$B$16:$F$1328,5,0))) -> 7.6 | D123: 1 | E123: 1 | F123: =IF(D123>0,(E123/D123),"") -> 1 | G123: =IF(D123>0,(100%-F123),"") -> 0 | H123: =IF(B123>0,(G123*B123/F123),"") -> 0 | I123: =IF(B123>0,(B123+H123),"") -> 0.25 | J123: =IF(C123>0,(C123*I123),"") -> 1.9
A124: ACEITE DE OLIVA SUAVE 5 LT | B124: 1 | C124: =IF(ISNA(VLOOKUP(A124,'Listado de Artículos'!$B$16:$F$1328,5,0)),0,(VLOOKUP(A124,'Listado de Artículos'!$B$16:$F$1328,5,0))) -> 5.95 | D124: 1 | E124: 1 | F124: =IF(D124>0,(E124/D124),"") -> 1 | G124: =IF(D124>0,(100%-F124),"") -> 0 | H124: =IF(B124>0,(G124*B124/F124),"") -> 0 | I124: =IF(B124>0,(B124+H124),"") -> 1 | J124: =IF(C124>0,(C124*I124),"") -> 5.95
B129: ARTÍCULO | C129: Solomillo de cerdo
B130: TAPA | C130: ELABORADOS | G130: PRECIO DE VENTA P.V.P
B131: unid. | C131: 58 | D131: Coste TOTAL | F131: =SUM(J134:J138) -> 82.805 | G131: Coste UNID: | I131: =F131/C131 -> 1.4276724
A133: ARTICULO | B133: KG | C133: €/UN | D133: BRUTO | E133: NETO | F133: %NETO | G133: %DESP | H133: DESP | I133: SUCIO | J133: € / RACION
A134: Solomillo cerdo | B134: 8 | C134: =IF(ISNA(VLOOKUP(A134,'Listado de Artículos'!$B$16:$F$1328,5,0)),0,(VLOOKUP(A134,'Listado de Artículos'!$B$16:$F$1328,5,0))) -> 0.36 | D134: 1 | E134: 1 | F134: =IF(D134>0,(E134/D134),"") -> 1 | G134: =IF(D134>0,(100%-F134),"") -> 0 | H134: =IF(B134>0,(G134*B134/F134),"") -> 0 | I134: =IF(B134>0,(B134+H134),"") -> 8 | J134: =IF(C134>0,(C134*I134),"") -> 2.88
A135: Ajo rojo pelado. pqt 1 kg. | B135: 0.5 | C135: =IF(ISNA(VLOOKUP(A135,'Listado de Artículos'!$B$16:$F$1328,5,0)),0,(VLOOKUP(A135,'Listado de Artículos'!$B$16:$F$1328,5,0))) -> 28.59 | D135: 1 | E135: 1 | F135: =IF(D135>0,(E135/D135),"") -> 1 | G135: =IF(D135>0,(100%-F135),"") -> 0 | H135: =IF(B135>0,(G135*B135/F135),"") -> 0 | I135: =IF(B135>0,(B135+H135),"") -> 0.5 | J135: =IF(C135>0,(C135*I135),"") -> 14.295
A136: Patata Monalisa. | B136: 15 | C136: =IF(ISNA(VLOOKUP(A136,'Listado de Artículos'!$B$16:$F$1328,5,0)),0,(VLOOKUP(A136,'Listado de Artículos'!$B$16:$F$1328,5,0))) -> 2 | D136: 1 | E136: 1 | F136: =IF(D136>0,(E136/D136),"") -> 1 | G136: =IF(D136>0,(100%-F136),"") -> 0 | H136: =IF(B136>0,(G136*B136/F136),"") -> 0 | I136: =IF(B136>0,(B136+H136),"") -> 15 | J136: =IF(C136>0,(C136*I136),"") -> 30
A137: Salsa naranja | B137: 1 | C137: =IF(ISNA(VLOOKUP(A137,'Listado de Artículos'!$B$16:$F$1328,5,0)),0,(VLOOKUP(A137,'Listado de Artículos'!$B$16:$F$1328,5,0))) -> 31.53 | D137: 1 | E137: 1 | F137: =IF(D137>0,(E137/D137),"") -> 1 | G137: =IF(D137>0,(100%-F137),"") -> 0 | H137: =IF(B137>0,(G137*B137/F137),"") -> 0 | I137: =IF(B137>0,(B137+H137),"") -> 1 | J137: =IF(C137>0,(C137*I137),"") -> 31.53
A138: Microbrotes | B138: 1 | C138: =IF(ISNA(VLOOKUP(A138,'Listado de Artículos'!$B$16:$F$1328,5,0)),0,(VLOOKUP(A138,'Listado de Artículos'!$B$16:$F$1328,5,0))) -> 4.1 | D138: 1 | E138: 1 | F138: =IF(D138>0,(E138/D138),"") -> 1 | G138: =IF(D138>0,(100%-F138),"") -> 0 | H138: =IF(B138>0,(G138*B138/F138),"") -> 0 | I138: =IF(B138>0,(B138+H138),"") -> 1 | J138: =IF(C138>0,(C138*I138),"") -> 4.1
B142: ARTÍCULO | C142: Salsa naranja
B143: TAPA | C143: ELABORADOS | G143: PRECIO DE VENTA P.V.P
B144: unid. | C144: 1 | D144: Coste TOTAL | F144: =SUM(J147:J151) -> 86.445 | G144: Coste UNID: | I144: =F144/C144 -> 86.445
...

Sheet MP boda 31-1
B3: Boda 31-1
B4: FICHA TÉCNICA PLATO
B7: ARTÍCULO | C7: Ceviche de corvina
B8: TAPA | C8: ELABORADOS | G8: PRECIO DE VENTA P.V.P
B9: unid. | C9: 58 | D9: Coste TOTAL | F9: =SUM(J12:J18) -> 34.4878 | G9: Coste UNID: | I9: =F9/C9 -> 0.59461724
A11: ARTICULO | B11: KG | C11: €/UN | D11: BRUTO | E11: NETO | F11: %NETO | G11: %DESP | H11: DESP | I11: SUCIO | J11: € / RACION
A12: Corvina fileteada | B12: 7 | C12: =IF(ISNA(VLOOKUP(A12,'Listado de Artículos'!$B$16:$F$1328,5,0)),0,(VLOOKUP(A12,'Listado de Artículos'!$B$16:$F$1328,5,0))) -> 3.2 | D12: 1 | E12: 1 | F12: =IF(D12>0,(E12/D12),"") -> 1 | G12: =IF(D12>0,(100%-F12),"") -> 0 | H12: =IF(B12>0,(G12*B12/F12),"") -> 0 | I12: =IF(B12>0,(B12+H12),"") -> 7 | J12: =IF(C12>0,(C12*I12),"") -> 22.4
A13: Limones extra. | B13: 2 | C13: =IF(ISNA(VLOOKUP(A13,'Listado de Artículos'!$B$16:$F$1328,5,0)),0,(VLOOKUP(A13,'Listado de Artículos'!$B$16:$F$1328,5,0))) -> 1.38 | D13: 1 | E13: 1 | F13: =IF(D13>0,(E13/D13),"") -> 1 | G13: =IF(D13>0,(100%-F13),"") -> 0 | H13: =IF(B13>0,(G13*B13/F13),"") -> 0 | I13: =IF(B13>0,(B13+H13),"") -> 2 | J13: =IF(C13>0,(C13*I13),"") -> 2.76
A14: Cebolla morada. | B14: 1 | C14: =IF(ISNA(VLOOKUP(A14,'Listado de Artículos'!$B$16:$F$1328,5,0)),0,(VLOOKUP(A14,'Listado de Artículos'!$B$16:$F$1328,5,0))) -> 4.85 | D14: 1 | E14: 1 | F14: =IF(D14>0,(E14/D14),"") -> 1 | G14: =IF(D14>0,(100%-F14),"") -> 0 | H14: =IF(B14>0,(G14*B14/F14),"") -> 0 | I14: =IF(B14>0,(B14+H14),"") -> 1 | J14: =IF(C14>0,(C14*I14),"") -> 4.85
A15: Ají limo | B15: 0.5 | C15: =IF(ISNA(VLOOKUP(A15,'Listado de Artículos'!$B$16:$F$1328,5,0)),0,(VLOOKUP(A15,'Listado de Artículos'!$B$16:$F$1328,5,0))) -> 6 | D15: 1 | E15: 1 | F15: =IF(D15>0,(E15/D15),"") -> 1 | G15: =IF(D15>0,(100%-F15),"") -> 0 | H15: =IF(B15>0,(G15*B15/F15),"") -> 0 | I15: =IF(B15>0,(B15+H15),"") -> 0.5 | J15: =IF(C15>0,(C15*I15),"") -> 3
A16: Cilantro | B16: 0.2 | C16: =IF(ISNA(VLOOKUP(A16,'Listado de Artículos'!$B$16:$F$1328,5,0)),0,(VLOOKUP(A16,'Listado de Artículos'!$B$16:$F$1328,5,0))) -> 0.55 | D16: 1 | E16: 1 | F16: =IF(D16>0,(E16/D16),"") -> 1 | G16: =IF(D16>0,(100%-F16),"") -> 0 | H16: =IF(B16>0,(G16*B16/F16),"") -> 0 | I16: =IF(B16>0,(B16+H16),"") -> 0.2 | J16: =IF(C16>0,(C16*I16),"") -> 0.11
A17: Ajo rojo pelado. pqt 1 kg. | B17: 0.02 | C17: =IF(ISNA(VLOOKUP(A17,'Listado de Artículos'!$B$16:$F$1328,5,0)),0,(VLOOKUP(A17,'Listado de Artículos'!$B$16:$F$1328,5,0))) -> 28.59 | D17: 1 | E17: 1 | F17: =IF(D17>0,(E17/D17),"") -> 1 | G17: =IF(D17>0,(100%-F17),"") -> 0 | H17: =IF(B17>0,(G17*B17/F17),"") -> 0 | I17: =IF(B17>0,(B17+H17),"") -> 0.02 | J17: =IF(C17>0,(C17*I17),"") -> 0.5718
A18: Jenjibre bandeja de 500 gr. | B18: 0.2 | C18: =IF(ISNA(VLOOKUP(A18,'Listado de Artículos'!$B$16:$F$1328,5,0)),0,(VLOOKUP(A18,'Listado de Artículos'!$B$16:$F$1328,5,0))) -> 3.98 | D18: 1 | E18: 1 | F18: =IF(D18>0,(E18/D18),"") -> 1 | G18: =IF(D18>0,(100%-F18),"") -> 0 | H18: =IF(B18>0,(G18*B18/F18),"") -> 0 | I18: =IF(B18>0,(B18+H18),"") -> 0.2 | J18: =IF(C18>0,(C18*I18),"") -> 0.796
B22: ARTÍCULO | C22: Taco de carrillera
B23: TAPA | C23: ELABORADOS | G23: PRECIO DE VENTA P.V.P
B24: unid. | C24: 58 | D24: Coste TOTAL | F24: =SUM(J27:J37) -> 1739.934 | G24: Coste UNID: | I24: =F24/C24 -> 29.998862
A26: ARTICULO | B26: KG | C26: €/UN | D26: BRUTO | E26: NETO | F26: %NETO | G26: %DESP | H26: DESP | I26: SUCIO | J26: € / RACION
A27: Galtes porc | B27: 9 | C27: =IF(ISNA(VLOOKUP(A27,'Listado de Artículos'!$B$16:$F$1328,5,0)),0,(VLOOKUP(A27,'Listado de Artículos'!$B$16:$F$1328,5,0))) -> 5.35 | D27: 1 | E27: 1 | F27: =IF(D27>0,(E27/D27),"") -> 1 | G27: =IF(D27>0,(100%-F27),"") -> 0 | H27: =IF(B27>0,(G27*B27/F27),"") -> 0 | I27: =IF(B27>0,(B27+H27),"") -> 9 | J27: =IF(C27>0,(C27*I27),"") -> 48.15
A28: Ajo rojo pelado. pqt 1 kg. | B28: 0.1 | C28: =IF(ISNA(VLOOKUP(A28,'Listado de Artículos'!$B$16:$F$1328,5,0)),0,(VLOOKUP(A28,'Listado de Artículos'!$B$16:$F$1328,5,0))) -> 28.59 | D28: 1 | E28: 1 | F28: =IF(D28>0,(E28/D28),"") -> 1 | G28: =IF(D28>0,(100%-F28),"") -> 0 | H28: =IF(B28>0,(G28*B28/F28),"") -> 0 | I28: =IF(B28>0,(B28+H28),"") -> 0.1 | J28: =IF(C28>0,(C28*I28),"") -> 2.859
A29: Cebolla blanca. | B29: 1 | C29: =IF(ISNA(VLOOKUP(A29,'Listado de Artículos'!$B$16:$F$1328,5,0)),0,(VLOOKUP(A29,'Listado de Artículos'!$B$16:$F$1328,5,0))) -> 4.5 | D29: 1 | E29: 1 | F29: =IF(D29>0,(E29/D29),"") -> 1 | G29: =IF(D29>0,(100%-F29),"") -> 0 | H29: =IF(B29>0,(G29*B29/F29),"") -> 0 | I29: =IF(B29>0,(B29+H29),"") -> 1 | J29: =IF(C29>0,(C29*I29),"") -> 4.5
A30: Zanahorias. | B30: 0.14 | C30: =IF(ISNA(VLOOKUP(A30,'Listado de Artículos'!$B$16:$F$1328,5,0)),0,(VLOOKUP(A30,'Listado de Artículos'!$B$16:$F$1328,5,0))) -> 4.25 | D30: 1 | E30: 1 | F30: =IF(D30>0,(E30/D30),"") -> 1 | G30: =IF(D30>0,(100%-F30),"") -> 0 | H30: =IF(B30>0,(G30*B30/F30),"") -> 0 | I30: =IF(B30>0,(B30+H30),"") -> 0.14 | J30: =IF(C30>0,(C30*I30),"") -> 0.595
A31: Puerro limpio. | B31: 0.3 | C31: =IF(ISNA(VLOOKUP(A31,'Listado de Artículos'!$B$16:$F$1328,5,0)),0,(VLOOKUP(A31,'Listado de Artículos'!$B$16:$F$1328,5,0))) -> 19.9 | D31: 1 | E31: 1 | F31: =IF(D31>0,(E31/D31),"") -> 1 | G31: =IF(D31>0,(100%-F31),"") -> 0 | H31: =IF(B31>0,(G31*B31/F31),"") -> 0 | I31: =IF(B31>0,(B31+H31),"") -> 0.3 | J31: =IF(C31>0,(C31*I31),"") -> 5.97
A32: Mayonesa 2,2kg | B32: 0.25 | C32: =IF(ISNA(VLOOKUP(A32,'Listado de Artículos'!$B$16:$F$1328,5,0)),0,(VLOOKUP(A32,'Listado de Artículos'!$B$16:$F$1328,5,0))) -> 16.72 | D32: 1 | E32: 1 | F32: =IF(D32>0,(E32/D32),"") -> 1 | G32: =IF(D32>0,(100%-F32),"") -> 0 | H32: =IF(B32>0,(G32*B32/F32),"") -> 0 | I32: =IF(B32>0,(B32+H32),"") -> 0.25 | J32: =IF(C32>0,(C32*I32),"") -> 4.18
A33: Pico de gallo | B33: 1 | C33: =IF(ISNA(VLOOKUP(A33,'Listado de Artículos'!$B$16:$F$1328,5,0)),0,(VLOOKUP(A33,'Listado de Artículos'!$B$16:$F$1328,5,0))) -> 6.75 | D33: 1 | E33: 1 | F33: =IF(D33>0,(E33/D33),"") -> 1 | G33: =IF(D33>0,(100%-F33),"") -> 0 | H33: =IF(B33>0,(G33*B33/F33),"") -> 0 | I33: =IF(B33>0,(B33+H33),"") -> 1 | J33: =IF(C33>0,(C33*I33),"") -> 6.75
A34: Salsa Valentina | B34: 1 | C34: =IF(ISNA(VLOOKUP(A34,'Listado de Artículos'!$B$16:$F$1328,5,0)),0,(VLOOKUP(A34,'Listado de Artículos'!$B$16:$F$1328,5,0))) -> 1660 | D34: 1 | E34: 1 | F34: =IF(D34>0,(E34/D34),"") -> 1 | G34: =IF(D34>0,(100%-F34),"") -> 0 | H34: =IF(B34>0,(G34*B34/F34),"") -> 0 | I34: =IF(B34>0,(B34+H34),"") -> 1 | J34: =IF(C34>0,(C34*I34),"") -> 1660
A35: Salsa Verde | B35: 1 | C35: =IF(ISNA(VLOOKUP(A35,'Listado de Artículos'!$B$16:$F$1328,5,0)),0,(VLOOKUP(A35,'Listado de Artículos'!$B$16:$F$1328,5,0))) -> 3.15 | D35: 1 | E35: 1 | F35: =IF(D35>0,(E35/D35),"") -> 1 | G35: =IF(D35>0,(100%-F35),"") -> 0 | H35: =IF(B35>0,(G35*B35/F35),"") -> 0 | I35: =IF(B35>0,(B35+H35),"") -> 1 | J35: =IF(C35>0,(C35*I35),"") -> 3.15
A36: Limones extra. | B36: 1 | C36: =IF(ISNA(VLOOKUP(A36,'Listado de Artículos'!$B$16:$F$1328,5,0)),0,(VLOOKUP(A36,'Listado de Artículos'!$B$16:$F$1328,5,0))) -> 1.38 | D36: 1 | E36: 1 | F36: =IF(D36>0,(E36/D36),"") -> 1 | G36: =IF(D36>0,(100%-F36),"") -> 0 | H36: =IF(B36>0,(G36*B36/F36),"") -> 0 | I36: =IF(B36>0,(B36+H36),"") -> 1 | J36: =IF(C36>0,(C36*I36),"") -> 1.38
A37: Tortillas maiz | B37: 2 | C37: =IF(ISNA(VLOOKUP(A37,'Listado de Artículos'!$B$16:$F$1328,5,0)),0,(VLOOKUP(A37,'Listado de Artículos'!$B$16:$F$1328,5,0))) -> 1.2 | D37: 1 | E37: 1 | F37: =IF(D37>0,(E37/D37),"") -> 1 | G37: =IF(D37>0,(100%-F37),"") -> 0 | H37: =IF(B37>0,(G37*B37/F37),"") -> 0 | I37: =IF(B37>0,(B37+H37),"") -> 2 | J37: =IF(C37>0,(C37*I37),"") -> 2.4
B41: ARTÍCULO | C41: Pico de gallo
B42: TAPA | C42: ELABORADOS | G42: PRECIO DE VENTA P.V.P
B43: unid. | C43: 1 | D43: Coste TOTAL | F43: =SUM(J46:J48) -> 7.775 | G43: Coste UNID: | I43: =F43/C43 -> 7.775
A45: ARTICULO | B45: KG | C45: €/UN | D45: BRUTO | E45: NETO | F45: %NETO | G45: %DESP | H45: DESP | I45: SUCIO | J45: € / RACION
A46: Cebolla blanca. | B46: 1 | C46: =IF(ISNA(VLOOKUP(A46,'Listado de Artículos'!$B$16:$F$1328,5,0)),0,(VLOOKUP(A46,'Listado de Artículos'!$B$16:$F$1328,5,0))) -> 4.5 | D46: 1 | E46: 1 | F46: =IF(D46>0,(E46/D46),"") -> 1 | G46: =IF(D46>0,(100%-F46),"") -> 0 | H46: =IF(B46>0,(G46*B46/F46),"") -> 0 | I46: =IF(B46>0,(B46+H46),"") -> 1 | J46: =IF(C46>0,(C46*I46),"") -> 4.5
A47: Cilantro | B47: 0.5 | C47: =IF(ISNA(VLOOKUP(A47,'Listado de Artículos'!$B$16:$F$1328,5,0)),0,(VLOOKUP(A47,'Listado de Artículos'!$B$16:$F$1328,5,0))) -> 0.55 | D47: 1 | E47: 1 | F47: =IF(D47>0,(E47/D47),"") -> 1 | G47: =IF(D47>0,(100%-F47),"") -> 0 | H47: =IF(B47>0,(G47*B47/F47),"") -> 0 | I47: =IF(B47>0,(B47+H47),"") -> 0.5 | J47: =IF(C47>0,(C47*I47),"") -> 0.275
A48: Tomate Pera. | B48: 2 | C48: =IF(ISNA(VLOOKUP(A48,'Listado de Artículos'!$B$16:$F$1328,5,0)),0,(VLOOKUP(A48,'Listado de Artículos'!$B$16:$F$1328,5,0))) -> 1.5 | D48: 1 | E48: 1 | F48: =IF(D48>0,(E48/D48),"") -> 1 | G48: =IF(D48>0,(100%-F48),"") -> 0 | H48: =IF(B48>0,(G48*B48/F48),"") -> 0 | I48: =IF(B48>0,(B48+H48),"") -> 2 | J48: =IF(C48>0,(C48*I48),"") -> 3
B51: ARTÍCULO | C51: Guacamole i totopos
B52: TAPA | C52: ELABORADOS | G52: PRECIO DE VENTA P.V.P
B53: unid. | C53: 58 | D53: Coste TOTAL | F53: =SUM(J56:J59) -> 48.55 | G53: Coste UNID: | I53: =F53/C53 -> 0.83706897
A55: ARTICULO | B55: KG | C55: €/UN | D55: BRUTO | E55: NETO | F55: %NETO | G55: %DESP | H55: DESP | I55: SUCIO | J55: € / RACION
A56: Aguacate | B56: 8 | C56: =IF(ISNA(VLOOKUP(A56,'Listado de Artículos'!$B$16:$F$1328,5,0)),0,(VLOOKUP(A56,'Listado de Artículos'!$B$16:$F$1328,5,0))) -> 5.65 | D56: 1 | E56: 1 | F56: =IF(D56>0,(E56/D56),"") -> 1 | G56: =IF(D56>0,(100%-F56),"") -> 0 | H56: =IF(B56>0,(G56*B56/F56),"") -> 0 | I56: =IF(B56>0,(B56+H56),"") -> 8 | J56: =IF(C56>0,(C56*I56),"") -> 45.2
A57: Nachos 750g | B57: 0.5 | C57: =IF(ISNA(VLOOKUP(A57,'Listado de Artículos'!$B$16:$F$1328,5,0)),0,(VLOOKUP(A57,'Listado de Artículos'!$B$16:$F$1328,5,0))) -> 0.82 | D57: 1 | E57: 1 | F57: =IF(D57>0,(E57/D57),"") -> 1 | G57: =IF(D57>0,(100%-F57),"") -> 0 | H57: =IF(B57>0,(G57*B57/F57),"") -> 0 | I57: =IF(B57>0,(B57+H57),"") -> 0.5 | J57: =IF(C57>0,(C57*I57),"") -> 0.41
A58: Cebolla blanca. | B58: 0.04 | C58: =IF(ISNA(VLOOKUP(A58,'Listado de Artículos'!$B$16:$F$1328,5,0)),0,(VLOOKUP(A58,'Listado de Artículos'!$B$16:$F$1328,5,0))) -> 4.5 | D58: 1 | E58: 1 | F58: =IF(D58>0,(E58/D58),"") -> 1 | G58: =IF(D58>0,(100%-F58),"") -> 0 | H58: =IF(B58>0,(G58*B58/F58),"") -> 0 | I58: =IF(B58>0,(B58+H58),"") -> 0.04 | J58: =IF(C58>0,(C58*I58),"") -> 0.18
A59: Limones extra. | B59: 2 | C59: =IF(ISNA(VLOOKUP(A59,'Listado de Artículos'!$B$16:$F$1328,5,0)),0,(VLOOKUP(A59,'Listado de Artículos'!$B$16:$F$1328,5,0))) -> 1.38 | D59: 1 | E59: 1 | F59: =IF(D59>0,(E59/D59),"") -> 1 | G59: =IF(D59>0,(100%-F59),"") -> 0 | H59: =IF(B59>0,(G59*B59/F59),"") -> 0 | I59: =IF(B59>0,(B59+H59),"") -> 2 | J59: =IF(C59>0,(C59*I59),"") -> 2.76
B62: ARTÍCULO | C62: Pan de cristal con jamón
B63: TAPA | C63: ELABORADOS | G63: PRECIO DE VENTA P.V.P
B64: unid. | C64: 1 | D64: Coste TOTAL | F64: =SUM(J67:J69) -> 3.1085 | G64: Coste UNID: | I64: =F64/C64 -> 3.1085
A66: ARTICULO | B66: KG | C66: €/UN | D66: BRUTO | E66: NETO | F66: %NETO | G66: %DESP | H66: DESP | I66: SUCIO | J66: € / RACION
A67: Paletilla jamón casa marcial | B67: 0.025 | C67: =IF(ISNA(VLOOKUP(A67,'Listado de Artículos'!$B$16:$F$1328,5,0)),0,(VLOOKUP(A67,'Listado de Artículos'!$B$16:$F$1328,5,0))) -> 7.6 | D67: 1 | E67: 1 | F67: =IF(D67>0,(E67/D67),"") -> 1 | G67: =IF(D67>0,(100%-F67),"") -> 0 | H67: =IF(B67>0,(G67*B67/F67),"") -> 0 | I67: =IF(B67>0,(B67+H67),"") -> 0.025 | J67: =IF(C67>0,(C67*I67),"") -> 0.19
A68: Pan cristal precortado. (3,200 gr). 64 *50. 26,78€ Caja. 0,20€ medio trozo. | B68: 1 | C68: =IF(ISNA(VLOOKUP(A68,'Listado de Artículos'!$B$16:$F$1328,5,0)),0,(VLOOKUP(A68,'Listado de Artículos'!$B$16:$F$1328,5,0))) -> 2.9 | D68: 1 | E68: 1 | F68: =IF(D68>0,(E68/D68),"") -> 1 | G68: =IF(D68>0,(100%-F68),"") -> 0 | H68: =IF(B68>0,(G68*B68/F68),"") -> 0 | I68: =IF(B68>0,(B68+H68),"") -> 1 | J68: =IF(C68>0,(C68*I68),"") -> 2.9
A69: Tomate rallado | B69: 0.01 | C69: =IF(ISNA(VLOOKUP(A69,'Listado de Artículos'!$B$16:$F$1328,5,0)),0,(VLOOKUP(A69,'Listado de Artículos'!$B$16:$F$1328,5,0))) -> 1.85 | D69: 1 | E69: 1 | F69: =IF(D69>0,(E69/D69),"") -> 1 | G69: =IF(D69>0,(100%-F69),"") -> 0 | H69: =IF(B69>0,(G69*B69/F69),"") -> 0 | I69: =IF(B69>0,(B69+H69),"") -> 0.01 | J69: =IF(C69>0,(C69*I69),"") -> 0.0185 | L69: =1300/58 -> 22.413793
L71: =1.22*4 -> 4.88
B73: ARTÍCULO | C73: Tabla de quesos
B74: TAPA | C74: ELABORADOS | G74: PRECIO DE VENTA P.V.P
B75: unid. | C75: 58 | D75: Coste TOTAL | F75: =SUM(J78:J82) -> 9.134 | G75: Coste UNID: | I75: =F75/C75 -> 0.15748276
A77: ARTICULO | B77: KG | C77: €/UN | D77: BRUTO | E77: NETO | F77: %NETO | G77: %DESP | H77: DESP | I77: SUCIO | J77: € / RACION
A78: Queso Altejo moli de ger Vaca. | B78: 0.4 | C78: =IF(ISNA(VLOOKUP(A78,'Listado de Artículos'!$B$16:$F$1328,5,0)),0,(VLOOKUP(A78,'Listado de Artículos'!$B$16:$F$1328,5,0))) -> 0.03 | D78: 1 | E78: 1 | F78: =IF(D78>0,(E78/D78),"") -> 1 | G78: =IF(D78>0,(100%-F78),"") -> 0 | H78: =IF(B78>0,(G78*B78/F78),"") -> 0 | I78: =IF(B78>0,(B78+H78),"") -> 0.4 | J78: =IF(C78>0,(C78*I78),"") -> 0.012
A79: Queso Garrotxa Cabra. Bauma. | B79: 0.7 | C79: =IF(ISNA(VLOOKUP(A79,'Listado de Artículos'!$B$16:$F$1328,5,0)),0,(VLOOKUP(A79,'Listado de Artículos'!$B$16:$F$1328,5,0))) -> 0.01 | D79: 1 | E79: 1 | F79: =IF(D79>0,(E79/D79),"") -> 1 | G79: =IF(D79>0,(100%-F79),"") -> 0 | H79: =IF(B79>0,(G79*B79/F79),"") -> 0 | I79: =IF(B79>0,(B79+H79),"") -> 0.7 | J79: =IF(C79>0,(C79*I79),"") -> 0.007
A80: Queso Azul Blau Cereta. Moli de ger. | B80: 0.2 | C80: =IF(ISNA(VLOOKUP(A80,'Listado de Artículos'!$B$16:$F$1328,5,0)),0,(VLOOKUP(A80,'Listado de Artículos'!$B$16:$F$1328,5,0))) -> 2.95 | D80: 1 | E80: 1 | F80: =IF(D80>0,(E80/D80),"") -> 1 | G80: =IF(D80>0,(100%-F80),"") -> 0 | H80: =IF(B80>0,(G80*B80/F80),"") -> 0 | I80: =IF(B80>0,(B80+H80),"") -> 0.2 | J80: =IF(C80>0,(C80*I80),"") -> 0.59
A81: Palitos pan | B81: 0.5 | C81: =IF(ISNA(VLOOKUP(A81,'Listado de Artículos'!$B$16:$F$1328,5,0)),0,(VLOOKUP(A81,'Listado de Artículos'!$B$16:$F$1328,5,0))) -> 17.05 | D81: 1 | E81: 1 | F81: =IF(D81>0,(E81/D81),"") -> 1 | G81: =IF(D81>0,(100%-F81),"") -> 0 | H81: =IF(B81>0,(G81*B81/F81),"") -> 0 | I81: =IF(B81>0,(B81+H81),"") -> 0.5 | J81: =IF(C81>0,(C81*I81),"") -> 8.525
A82: A.AAAAA | B82: 0.14 | C82: =IF(ISNA(VLOOKUP(A82,'Listado de Artículos'!$B$16:$F$1328,5,0)),0,(VLOOKUP(A82,'Listado de Artículos'!$B$16:$F$1328,5,0))) -> 0 | D82: 1 | E82: 1 | F82: =IF(D82>0,(E82/D82),"") -> 1 | G82: =IF(D82>0,(100%-F82),"") -> 0 | H82: =IF(B82>0,(G82*B82/F82),"") -> 0 | I82: =IF(B82>0,(B82+H82),"") -> 0.14 | J82: =IF(C82>0,(C82*I82),"")
B86: ARTÍCULO | C86: Brocheta langostino
B87: TAPA | C87: ELABORADOS | G87: PRECIO DE VENTA P.V.P
B88: unid. | C88: 58 | D88: Coste TOTAL | F88: =SUM(J91:J96) -> 43.856 | G88: Coste UNID: | I88: =F88/C88 -> 0.75613793
A90: ARTICULO | B90: KG | C90: €/UN | D90: BRUTO | E90: NETO | F90: %NETO | G90: %DESP | H90: DESP | I90: SUCIO | J90: € / RACION
A91: Gamba paella | B91: 3 | C91: =IF(ISNA(VLOOKUP(A91,'Listado de Artículos'!$B$16:$F$1328,5,0)),0,(VLOOKUP(A91,'Listado de Artículos'!$B$16:$F$1328,5,0))) -> 10.5 | D91: 1 | E91: 1 | F91: =IF(D91>0,(E91/D91),"") -> 1 | G91: =IF(D91>0,(100%-F91),"") -> 0 | H91: =IF(B91>0,(G91*B91/F91),"") -> 0 | I91: =IF(B91>0,(B91+H91),"") -> 3 | J91: =IF(C91>0,(C91*I91),"") -> 31.5
A92: Panko | B92: 1 | C92: =IF(ISNA(VLOOKUP(A92,'Listado de Artículos'!$B$16:$F$1328,5,0)),0,(VLOOKUP(A92,'Listado de Artículos'!$B$16:$F$1328,5,0))) -> 6.35 | D92: 1 | E92: 1 | F92: =IF(D92>0,(E92/D92),"") -> 1 | G92: =IF(D92>0,(100%-F92),"") -> 0 | H92: =IF(B92>0,(G92*B92/F92),"") -> 0 | I92: =IF(B92>0,(B92+H92),"") -> 1 | J92: =IF(C92>0,(C92*I92),"") -> 6.35
A93: Huevos pqt 6 Gavaldà | B93: 0.5 | C93: =IF(ISNA(VLOOKUP(A93,'Listado de Artículos'!$B$16:$F$1328,5,0)),0,(VLOOKUP(A93,'Listado de Artículos'!$B$16:$F$1328,5,0))) -> 2.19 | D93: 1 | E93: 1 | F93: =IF(D93>0,(E93/D93),"") -> 1 | G93: =IF(D93>0,(100%-F93),"") -> 0 | H93: =IF(B93>0,(G93*B93/F93),"") -> 0 | I93: =IF(B93>0,(B93+H93),"") -> 0.5 | J93: =IF(C93>0,(C93*I93),"") -> 1.095
A94: Aguacate | B94: 0.5 | C94: =IF(ISNA(VLOOKUP(A94,'Listado de Artículos'!$B$16:$F$1328,5,0)),0,(VLOOKUP(A94,'Listado de Artículos'!$B$16:$F$1328,5,0))) -> 5.65 | D94: 1 | E94: 1 | F94: =IF(D94>0,(E94/D94),"") -> 1 | G94: =IF(D94>0,(100%-F94),"") -> 0 | H94: =IF(B94>0,(G94*B94/F94),"") -> 0 | I94: =IF(B94>0,(B94+H94),"") -> 0.5 | J94: =IF(C94>0,(C94*I94),"") -> 2.825
A95: Mayonesa 2,2kg | B95: 0.1 | C95: =IF(ISNA(VLOOKUP(A95,'Listado de Artículos'!$B$16:$F$1328,5,0)),0,(VLOOKUP(A95,'Listado de Artículos'!$B$16:$F$1328,5,0))) -> 16.72 | D95: 1 | E95: 1 | F95: =IF(D95>0,(E95/D95),"") -> 1 | G95: =IF(D95>0,(100%-F95),"") -> 0 | H95: =IF(B95>0,(G95*B95/F95),"") -> 0 | I95: =IF(B95>0,(B95+H95),"") -> 0.1 | J95: =IF(C95>0,(C95*I95),"") -> 1.672
A96: Limones extra. | B96: 0.3 | C96: =IF(ISNA(VLOOKUP(A96,'Listado de Artículos'!$B$16:$F$1328,5,0)),0,(VLOOKUP(A96,'Listado de Artículos'!$B$16:$F$1328,5,0))) -> 1.38 | D96: 1 | E96: 1 | F96: =IF(D96>0,(E96/D96),"") -> 1 | G96: =IF(D96>0,(100%-F96),"") -> 0 | H96: =IF(B96>0,(G96*B96/F96),"") -> 0 | I96: =IF(B96>0,(B96+H96),"") -> 0.3 | J96: =IF(C96>0,(C96*I96),"") -> 0.414
B100: ARTÍCULO | C100: Crema calenta de tomàquet
B101: TAPA | C101: ELABORADOS | G101: PRECIO DE VENTA P.V.P
B102: unid. | C102: 58 | D102: Coste TOTAL | F102: =SUM(J105:J113) -> 101.8475 | G102: Coste UNID: | I102: =F102/C102 -> 1.7559914
A104: ARTICULO | B104: KG | C104: €/UN | D104: BRUTO | E104: NETO | F104: %NETO | G104: %DESP | H104: DESP | I104: SUCIO | J104: € / RACION
A105: Tomate Pera. | B105: 15 | C105: =IF(ISNA(VLOOKUP(A105,'Listado de Artículos'!$B$16:$F$1328,5,0)),0,(VLOOKUP(A105,'Listado de Artículos'!$B$16:$F$1328,5,0))) -> 1.5 | D105: 1 | E105: 1 | F105: =IF(D105>0,(E105/D105),"") -> 1 | G105: =IF(D105>0,(100%-F105),"") -> 0 | H105: =IF(B105>0,(G105*B105/F105),"") -> 0 | I105: =IF(B105>0,(B105+H105),"") -> 15 | J105: =IF(C105>0,(C105*I105),"") -> 22.5
A106: Ajo rojo pelado. pqt 1 kg. | B106: 0.2 | C106: =IF(ISNA(VLOOKUP(A106,'Listado de Artículos'!$B$16:$F$1328,5,0)),0,(VLOOKUP(A106,'Listado de Artículos'!$B$16:$F$1328,5,0))) -> 28.59 | D106: 1 | E106: 1 | F106: =IF(D106>0,(E106/D106),"") -> 1 | G106: =IF(D106>0,(100%-F106),"") -> 0 | H106: =IF(B106>0,(G106*B106/F106),"") -> 0 | I106: =IF(B106>0,(B106+H106),"") -> 0.2 | J106: =IF(C106>0,(C106*I106),"") -> 5.718
A107: Cebolla blanca. | B107: 3 | C107: =IF(ISNA(VLOOKUP(A107,'Listado de Artículos'!$B$16:$F$1328,5,0)),0,(VLOOKUP(A107,'Listado de Artículos'!$B$16:$F$1328,5,0))) -> 4.5 | D107: 1 | E107: 1 | F107: =IF(D107>0,(E107/D107),"") -> 1 | G107: =IF(D107>0,(100%-F107),"") -> 0 | H107: =IF(B107>0,(G107*B107/F107),"") -> 0 | I107: =IF(B107>0,(B107+H107),"") -> 3 | J107: =IF(C107>0,(C107*I107),"") -> 13.5
A108: ACEITE DE OLIVA SUAVE 5 LT | B108: 0.35 | C108: =IF(ISNA(VLOOKUP(A108,'Listado de Artículos'!$B$16:$F$1328,5,0)),0,(VLOOKUP(A108,'Listado de Artículos'!$B$16:$F$1328,5,0))) -> 5.95 | D108: 1 | E108: 1 | F108: =IF(D108>0,(E108/D108),"") -> 1 | G108: =IF(D108>0,(100%-F108),"") -> 0 | H108: =IF(B108>0,(G108*B108/F108),"") -> 0 | I108: =IF(B108>0,(B108+H108),"") -> 0.35 | J108: =IF(C108>0,(C108*I108),"") -> 2.0825
A109: Tomillo | B109: 0.14 | C109: =IF(ISNA(VLOOKUP(A109,'Listado de Artículos'!$B$16:$F$1328,5,0)),0,(VLOOKUP(A109,'Listado de Artículos'!$B$16:$F$1328,5,0))) -> 1.2 | D109: 1 | E109: 1 | F109: =IF(D109>0,(E109/D109),"") -> 1 | G109: =IF(D109>0,(100%-F109),"") -> 0 | H109: =IF(B109>0,(G109*B109/F109),"") -> 0 | I109: =IF(B109>0,(B109+H109),"") -> 0.14 | J109: =IF(C109>0,(C109*I109),"") -> 0.168
A110: AZUCAR | B110: 0.05 | C110: =IF(ISNA(VLOOKUP(A110,'Listado de Artículos'!$B$16:$F$1328,5,0)),0,(VLOOKUP(A110,'Listado de Artículos'!$B$16:$F$1328,5,0))) -> 0.82 | D110: 1 | E110: 1 | F110: =IF(D110>0,(E110/D110),"") -> 1 | G110: =IF(D110>0,(100%-F110),"") -> 0 | H110: =IF(B110>0,(G110*B110/F110),"") -> 0 | I110: =IF(B110>0,(B110+H110),"") -> 0.05 | J110: =IF(C110>0,(C110*I110),"") -> 0.041
A111: Variado de verduras. para caldo. makro | B111: 2 | C111: =IF(ISNA(VLOOKUP(A111,'Listado de Artículos'!$B$16:$F$1328,5,0)),0,(VLOOKUP(A111,'Listado de Artículos'!$B$16:$F$1328,5,0))) -> 1.99 | D111: 1 | E111: 1 | F111: =IF(D111>0,(E111/D111),"") -> 1 | G111: =IF(D111>0,(100%-F111),"") -> 0 | H111: =IF(B111>0,(G111*B111/F111),"") -> 0 | I111: =IF(B111>0,(B111+H111),"") -> 2 | J111: =IF(C111>0,(C111*I111),"") -> 3.98
A112: Picatiostes | B112: 0.2 | C112: =IF(ISNA(VLOOKUP(A112,'Listado de Artículos'!$B$16:$F$1328,5,0)),0,(VLOOKUP(A112,'Listado de Artículos'!$B$16:$F$1328,5,0))) -> 17.29 | D112: 1 | E112: 1 | F112: =IF(D112>0,(E112/D112),"") -> 1 | G112: =IF(D112>0,(100%-F112),"") -> 0 | H112: =IF(B112>0,(G112*B112/F112),"") -> 0 | I112: =IF(B112>0,(B112+H112),"") -> 0.2 | J112: =IF(C112>0,(C112*I112),"") -> 3.458
A113: Albahaca | B113: 2 | C113: =IF(ISNA(VLOOKUP(A113,'Listado de Artículos'!$B$16:$F$1328,5,0)),0,(VLOOKUP(A113,'Listado de Artículos'!$B$16:$F$1328,5,0))) -> 25.2 | D113: 1 | E113: 1 | F113: =IF(D113>0,(E113/D113),"") -> 1 | G113: =IF(D113>0,(100%-F113),"") -> 0 | H113: =IF(B113>0,(G113*B113/F113),"") -> 0 | I113: =IF(B113>0,(B113+H113),"") -> 2 | J113: =IF(C113>0,(C113*I113),"") -> 50.4
B117: ARTÍCULO | C117: Flor de alcachofa con jamón
B118: TAPA | C118: ELABORADOS | G118: PRECIO DE VENTA P.V.P
B119: unid. | C119: 58 | D119: Coste TOTAL | F119: =SUM(J122:J124) -> 22.85 | G119: Coste UNID: | I119: =F119/C119 -> 0.39396552
A121: ARTICULO | B121: KG | C121: €/UN | D121: BRUTO | E121: NETO | F121: %NETO | G121: %DESP | H121: DESP | I121: SUCIO | J121: € / RACION
A122: Carxofa confitada flor | B122: 6 | C122: =IF(ISNA(VLOOKUP(A122,'Listado de Artículos'!$B$16:$F$1328,5,0)),0,(VLOOKUP(A122,'Listado de Artículos'!$B$16:$F$1328,5,0))) -> 2.5 | D122: 1 | E122: 1 | F122: =IF(D122>0,(E122/D122),"") -> 1 | G122: =IF(D122>0,(100%-F122),"") -> 0 | H122: =IF(B122>0,(G122*B122/F122),"") -> 0 | I122: =IF(B122>0,(B122+H122),"") -> 6 | J122: =IF(C122>0,(C122*I122),"") -> 15
A123: Paletilla jamón casa marcial | B123: 0.25 | C123: =IF(ISNA(VLOOKUP(A123,'Listado de Artículos'!$B$16:$F$1328,5,0)),0,(VLOOKUP(A123,'Listado de Artículos'!$B$16:$F$1328,5,0))) -> 7.6 | D123: 1 | E123: 1 | F123: =IF(D123>0,(E123/D123),"") -> 1 | G123: =IF(D123>0,(100%-F123),"") -> 0 | H123: =IF(B123>0,(G123*B123/F123),"") -> 0 | I123: =IF(B123>0,(B123+H123),"") -> 0.25 | J123: =IF(C123>0,(C123*I123),"") -> 1.9
A124: ACEITE DE OLIVA SUAVE 5 LT | B124: 1 | C124: =IF(ISNA(VLOOKUP(A124,'Listado de Artículos'!$B$16:$F$1328,5,0)),0,(VLOOKUP(A124,'Listado de Artículos'!$B$16:$F$1328,5,0))) -> 5.95 | D124: 1 | E124: 1 | F124: =IF(D124>0,(E124/D124),"") -> 1 | G124: =IF(D124>0,(100%-F124),"") -> 0 | H124: =IF(B124>0,(G124*B124/F124),"") -> 0 | I124: =IF(B124>0,(B124+H124),"") -> 1 | J124: =IF(C124>0,(C124*I124),"") -> 5.95
B129: ARTÍCULO | C129: Solomillo de cerdo
B130: TAPA | C130: ELABORADOS | G130: PRECIO DE VENTA P.V.P
B131: unid. | C131: 58 | D131: Coste TOTAL | F131: =SUM(J134:J138) -> 82.805 | G131: Coste UNID: | I131: =F131/C131 -> 1.4276724
A133: ARTICULO | B133: KG | C133: €/UN | D133: BRUTO | E133: NETO | F133: %NETO | G133: %DESP | H133: DESP | I133: SUCIO | J133: € / RACION
A134: Solomillo cerdo | B134: 8 | C134: =IF(ISNA(VLOOKUP(A134,'Listado de Artículos'!$B$16:$F$1328,5,0)),0,(VLOOKUP(A134,'Listado de Artículos'!$B$16:$F$1328,5,0))) -> 0.36 | D134: 1 | E134: 1 | F134: =IF(D134>0,(E134/D134),"") -> 1 | G134: =IF(D134>0,(100%-F134),"") -> 0 | H134: =IF(B134>0,(G134*B134/F134),"") -> 0 | I134: =IF(B134>0,(B134+H134),"") -> 8 | J134: =IF(C134>0,(C134*I134),"") -> 2.88
A135: Ajo rojo pelado. pqt 1 kg. | B135: 0.5 | C135: =IF(ISNA(VLOOKUP(A135,'Listado de Artículos'!$B$16:$F$1328,5,0)),0,(VLOOKUP(A135,'Listado de Artículos'!$B$16:$F$1328,5,0))) -> 28.59 | D135: 1 | E135: 1 | F135: =IF(D135>0,(E135/D135),"") -> 1 | G135: =IF(D135>0,(100%-F135),"") -> 0 | H135: =IF(B135>0,(G135*B135/F135),"") -> 0 | I135: =IF(B135>0,(B135+H135),"") -> 0.5 | J135: =IF(C135>0,(C135*I135),"") -> 14.295
A136: Patata Monalisa. | B136: 15 | C136: =IF(ISNA(VLOOKUP(A136,'Listado de Artículos'!$B$16:$F$1328,5,0)),0,(VLOOKUP(A136,'Listado de Artículos'!$B$16:$F$1328,5,0))) -> 2 | D136: 1 | E136: 1 | F136: =IF(D136>0,(E136/D136),"") -> 1 | G136: =IF(D136>0,(100%-F136),"") -> 0 | H136: =IF(B136>0,(G136*B136/F136),"") -> 0 | I136: =IF(B136>0,(B136+H136),"") -> 15 | J136: =IF(C136>0,(C136*I136),"") -> 30
A137: Salsa naranja | B137: 1 | C137: =IF(ISNA(VLOOKUP(A137,'Listado de Artículos'!$B$16:$F$1328,5,0)),0,(VLOOKUP(A137,'Listado de Artículos'!$B$16:$F$1328,5,0))) -> 31.53 | D137: 1 | E137: 1 | F137: =IF(D137>0,(E137/D137),"") -> 1 | G137: =IF(D137>0,(100%-F137),"") -> 0 | H137: =IF(B137>0,(G137*B137/F137),"") -> 0 | I137: =IF(B137>0,(B137+H137),"") -> 1 | J137: =IF(C137>0,(C137*I137),"") -> 31.53
A138: Microbrotes | B138: 1 | C138: =IF(ISNA(VLOOKUP(A138,'Listado de Artículos'!$B$16:$F$1328,5,0)),0,(VLOOKUP(A138,'Listado de Artículos'!$B$16:$F$1328,5,0))) -> 4.1 | D138: 1 | E138: 1 | F138: =IF(D138>0,(E138/D138),"") -> 1 | G138: =IF(D138>0,(100%-F138),"") -> 0 | H138: =IF(B138>0,(G138*B138/F138),"") -> 0 | I138: =IF(B138>0,(B138+H138),"") -> 1 | J138: =IF(C138>0,(C138*I138),"") -> 4.1
B142: ARTÍCULO | C142: Salsa naranja
...

Sheet MENU BODA 31-1
A2: MENU BODA
A4: APERITIVO. | B4: P.V.P | C4: NETO | D4: COSTO | E4: FOOD COST
A5: COCTEL BIENVENIDA EN LA PLAZA 1 HORA | B5: GR O KG. | C5: PRECIO KG | D5: EUROS/RACION.
A6: Ceviche de corvina | B6: 1 | C6: =IF(ISNA(VLOOKUP(A6,'Listado de Artículos'!$B$16:$F$1328,5,0)),0,(VLOOKUP(A6,'Listado de Artículos'!$B$16:$F$1328,5,0))) -> 0.59461724 | D6: =B6*C6 -> 0.59461724
A7: Taco de Carrillera porc | B7: 1 | C7: =IF(ISNA(VLOOKUP(A7,'Listado de Artículos'!$B$16:$F$1328,5,0)),0,(VLOOKUP(A7,'Listado de Artículos'!$B$16:$F$1328,5,0))) -> 29.998862 | D7: =B7*C7 -> 29.998862
A8: Guacamole y totopos | B8: 1 | C8: =IF(ISNA(VLOOKUP(A8,'Listado de Artículos'!$B$16:$F$1328,5,0)),0,(VLOOKUP(A8,'Listado de Artículos'!$B$16:$F$1328,5,0))) -> 0.83706897 | D8: =B8*C8 -> 0.83706897
A9: Brocheta langostino | B9: 1 | C9: =IF(ISNA(VLOOKUP(A9,'Listado de Artículos'!$B$16:$F$1328,5,0)),0,(VLOOKUP(A9,'Listado de Artículos'!$B$16:$F$1328,5,0))) -> 0.75613793 | D9: =B9*C9 -> 0.75613793
A10: Pan de cristal con jamón | B10: 1 | C10: =IF(ISNA(VLOOKUP(A10,'Listado de Artículos'!$B$16:$F$1328,5,0)),0,(VLOOKUP(A10,'Listado de Artículos'!$B$16:$F$1328,5,0))) -> 3.1085 | D10: =B10*C10 -> 3.1085
A11: Tabla de quesos | B11: 1 | C11: =IF(ISNA(VLOOKUP(A11,'Listado de Artículos'!$B$16:$F$1328,5,0)),0,(VLOOKUP(A11,'Listado de Artículos'!$B$16:$F$1328,5,0))) -> 0.15748276 | D11: =B11*C11 -> 0.15748276
A12: Agua de jamaica | B12: 1 | C12: =IF(ISNA(VLOOKUP(A12,'Listado de Artículos'!$B$16:$F$1328,5,0)),0,(VLOOKUP(A12,'Listado de Artículos'!$B$16:$F$1328,5,0))) -> 0.1256 | D12: =B12*C12 -> 0.1256
A13: Agua de limón | B13: 1 | C13: =IF(ISNA(VLOOKUP(A13,'Listado de Artículos'!$B$16:$F$1328,5,0)),0,(VLOOKUP(A13,'Listado de Artículos'!$B$16:$F$1328,5,0))) -> 0.13982759 | D13: =B13*C13 -> 0.13982759
A14: Entrante
A15: Crema calenta tomàquet | B15: 1 | C15: =IF(ISNA(VLOOKUP(A15,'Listado de Artículos'!$B$16:$F$1328,5,0)),0,(VLOOKUP(A15,'Listado de Artículos'!$B$16:$F$1328,5,0))) -> 1.7559914 | D15: =B15*C15 -> 1.7559914
A16: PRIMERO.
A17: Flor de alcachofa con jamón | B17: 1 | C17: =IF(ISNA(VLOOKUP(A17,'Listado de Artículos'!$B$16:$F$1328,5,0)),0,(VLOOKUP(A17,'Listado de Artículos'!$B$16:$F$1328,5,0))) -> 0.39396552 | D17: =B17*C17 -> 0.39396552
A18: SEGUNDO
A19: Solomillo de cerdo con parmentier patata i salsa naranja | B19: 1 | C19: =IF(ISNA(VLOOKUP(A19,'Listado de Artículos'!$B$16:$F$1328,5,0)),0,(VLOOKUP(A19,'Listado de Artículos'!$B$16:$F$1328,5,0))) -> 1.4276724 | D19: =B19*C19 -> 1.4276724
A20: POSTRE
A21: Sorbete mandarina boda | B21: 1 | C21: =IF(ISNA(VLOOKUP(A21,'Listado de Artículos'!$B$16:$F$1328,5,0)),0,(VLOOKUP(A21,'Listado de Artículos'!$B$16:$F$1328,5,0))) -> 0.24931034 | D21: =B21*C21 -> 0.24931034
A22: BODEGA, PAN, VINO Y CAFES.
A23: Pan individual rombo makro | B23: 0.05 | C23: =IF(ISNA(VLOOKUP(A23,'Listado de Artículos'!$B$16:$F$1328,5,0)),0,(VLOOKUP(A23,'Listado de Artículos'!$B$16:$F$1328,5,0))) -> 3.85 | D23: =B23*C23 -> 0.1925
A29: ESCANDALLO | B29: 75 | C29: =+B29-(B29*0.1) -> 67.5 | D29: =SUM(D6:D27) -> 39.737536 | E29: =(D29*100/B29)/100 -> 0.52983382
D31: =B29-D29 -> 35.262464 | E31: Benefici

Sheet COMUNION  ALEJANDRO FERNANDEZ 
A2: MENU COCTEL.
A4: APERITIVO. | B4: P.V.P | C4: NETO | D4: COSTO | E4: FOOD COST
A5: FRIOS | B5: GR O KG. | C5: PRECIO KG | D5: EUROS/RACION. | F5: FRIOS.
A6: Tabla de embutidos y quesos variados. | B6: 1 | C6: 1.1 | D6: =B6*C6 -> 1.1 | F6: Montadito de pan de cristal con jamon iberico | G6: 40
A7: A.P JAMON AL CENTRO EVENTOS SOCIALES. | B7: 1 | C7: =IF(ISNA(VLOOKUP(A7,'Listado de Artículos'!$B$8:$F$306,5,0)),0,VLOOKUP(A7,'Listado de Artículos'!$B$8:$F$306,5,0)) -> 1.44 | D7: =B7*C7 -> 1.44 | F7: Surtido de quesos variados y embutidos variados | G7: 50
A8: Croqueta cocido . ( caja 4 kg). 30,49€ | B8: 0.03 | C8: =IF(ISNA(VLOOKUP(A8,'Listado de Artículos'!$B$16:$F$1328,5,0)),0,(VLOOKUP(A8,'Listado de Artículos'!$B$16:$F$1328,5,0))) -> 12.5 | D8: =B8*C8 -> 0.375 | F8: Croqueta de jamon iberico. | G8: 30
A9: A.P GAZPACHO DE FRAMBUESA Y BITER KAS. | B9: 1 | C9: =IF(ISNA(VLOOKUP(A9,'Listado de Artículos'!$B$16:$F$1328,5,0)),0,(VLOOKUP(A9,'Listado de Artículos'!$B$16:$F$1328,5,0))) -> 0.18 | D9: =B9*C9 -> 0.18 | F9: Gazpacho de frambuesa y bitter kas. | G9: 30
A10: A.P CREMA DE AJO BLANCO, SARDINA Y UVA. | B10: 1 | C10: 0.7 | D10: =B10*C10 -> 0.7 | F10: Crema de ajo blanco de coco, con sardina y uva. | G10: 30
A11: A.P SALMOREJO DE SANDIA. | B11: 1 | C11: 0.55 | D11: =B11*C11 -> 0.55 | F11: Salmorejo de sandia. | G11: 30
A12: A.P TARTAR DE SALMON MARINADO. | B12: 1 | C12: 0.75 | D12: =B12*C12 -> 0.75 | F12: Canape de salmon ahumado y queso a las finas hierbas. | G12: 20
A13: A.P DEGUSTACION DE FIDEOS ROSSOS. | B13: 1 | C13: =IF(ISNA(VLOOKUP(A13,'Listado de Artículos'!$B$16:$F$1328,5,0)),0,(VLOOKUP(A13,'Listado de Artículos'!$B$16:$F$1328,5,0))) -> 0.65 | D13: =B13*C13 -> 0.65 | F13: Ostra del delta en escabeche de citricos y gel de fruta de la pasion. | G13: 30
A14: A.P DEGUSTACION DE ARROZ NEGRO. | B14: 1 | C14: =IF(ISNA(VLOOKUP(A14,'Listado de Artículos'!$B$16:$F$1328,5,0)),0,(VLOOKUP(A14,'Listado de Artículos'!$B$16:$F$1328,5,0))) -> 0.8 | D14: =B14*C14 -> 0.8 | F14: CALIENTE.
A15: A.P MINI BURGUER DE PAN DE SESAMO. | B15: 1 | C15: =IF(ISNA(VLOOKUP(A15,'Listado de Artículos'!$B$16:$F$1328,5,0)),0,(VLOOKUP(A15,'Listado de Artículos'!$B$16:$F$1328,5,0))) -> 0.68 | D15: =B15*C15 -> 0.68 | F15: Lagrimita de pollo con salsa de mostaza, miel y curri. | G15: 30
A16: A.P BROCHETA DE POLLO CON SALSA KARE. | B16: 1 | C16: 0.6 | D16: =B16*C16 -> 0.6 | F16: Mini burguer con queso y salsa chedar. | G16: 30
A17: A.P OSTRA DEL DELTA, EN ESCABECHE DE CITRICOS Y GEL DE FRUTA DE LA PASION. | B17: 1 | C17: =IF(ISNA(VLOOKUP(A17,'Listado de Artículos'!$B$16:$F$1328,5,0)),0,(VLOOKUP(A17,'Listado de Artículos'!$B$16:$F$1328,5,0))) -> 1.48 | D17: =B17*C17 -> 1.48 | F17: brocheta de pollo con salsa tandori. | G17: 25
A18: POSTRES | F18: Degustacion de arroz negro. | G18: 60
A19: Tarta de celebracion CAL JAN | B19: 1 | C19: =IF(ISNA(VLOOKUP(A19,'Listado de Artículos'!$B$16:$F$1328,5,0)),0,(VLOOKUP(A19,'Listado de Artículos'!$B$16:$F$1328,5,0))) -> 3 | D19: =B19*C19 -> 3 | F19: Degustacion de fideua de marisco. | G19: 60
A20: POSTRES | F20: brocheta de pollo con salsa tandori. | G20: 25
A21: CLOS PINELL TERRA TINTO ALTA | B21: 0.25 | C21: =IF(ISNA(VLOOKUP(A21,'Listado de Artículos'!$B$16:$F$1328,5,0)),0,(VLOOKUP(A21,'Listado de Artículos'!$B$16:$F$1328,5,0))) -> 0.9 | D21: =B21*C21 -> 0.225 | F21: Degustacion de arroz negro. | G21: 60
A22: CAVA ROGER DE FLOR | B22: 0.2 | C22: =IF(ISNA(VLOOKUP(A22,'Listado de Artículos'!$B$16:$F$1328,5,0)),0,(VLOOKUP(A22,'Listado de Artículos'!$B$16:$F$1328,5,0))) -> 0 | D22: =B22*C22 -> 0 | F22: Degustacion de fideua de marisco. | G22: 60
A23: Aquarius Limon lata 33cl*24 | B23: 1 | C23: =IF(ISNA(VLOOKUP(A23,'Listado de Artículos'!$B$16:$F$1328,5,0)),0,(VLOOKUP(A23,'Listado de Artículos'!$B$16:$F$1328,5,0))) -> 7.95 | D23: =B23*C23 -> 7.95
A24: Caña de cerveza | B24: 2 | C24: 0.8 | D24: =B24*C24 -> 1.6 | F24: tarta de celebracion. Lemon pie, massini o sacher. | G24: 100
A25: MENU Calçotada Vermuth | B25: 1 | C25: =IF(ISNA(VLOOKUP(A25,'Listado de Artículos'!$B$16:$F$1328,5,0)),0,(VLOOKUP(A25,'Listado de Artículos'!$B$16:$F$1328,5,0))) -> 0.47 | D25: =B25*C25 -> 0.47 | F25: TOTAL GRAMOS. | G25: =SUM(G6:G24) -> 710
A26: Agua Fon vella 1 LT Caja de 12 unid. | B26: 0.5 | C26: =IF(ISNA(VLOOKUP(A26,'Listado de Artículos'!$B$16:$F$1328,5,0)),0,(VLOOKUP(A26,'Listado de Artículos'!$B$16:$F$1328,5,0))) -> 0.8 | D26: =B26*C26 -> 0.4
A27: Pan de pages de Forn Virgili. Precio kg | B27: 0.05 | C27: =IF(ISNA(VLOOKUP(A27,'Listado de Artículos'!$B$16:$F$1328,5,0)),0,(VLOOKUP(A27,'Listado de Artículos'!$B$16:$F$1328,5,0))) -> 2.85 | D27: =B27*C27 -> 0.1425
A28: Cafe Natural. 1 kg. 120 cafes. 24,48€ .kg. 0,22 unid | B28: 1 | C28: =IF(ISNA(VLOOKUP(A28,'Listado de Artículos'!$B$16:$F$1328,5,0)),0,(VLOOKUP(A28,'Listado de Artículos'!$B$16:$F$1328,5,0))) -> 0.65 | D28: =B28*C28 -> 0.65
A30: ESCANDALLO | B30: 55 | C30: =+B30-(B30*0.1) -> 49.5 | D30: =SUM(D6:D28) -> 23.7425 | E30: =(D30*100/C30)/100 -> 0.47964646
A33: MENU BBQ COMUNION.
A35: A COMPARTIR | B35: P.V.P | C35: NETO | D35: COSTO | E35: FOOD COST
B36: GR O KG. | C36: PRECIO KG | D36: EUROS/RACION.
A37: Patatas Bravas. menu BBQ. Precio pax. | B37: 1 | C37: =IF(ISNA(VLOOKUP(A37,'Listado de Artículos'!$B$16:$F$1328,5,0)),0,(VLOOKUP(A37,'Listado de Artículos'!$B$16:$F$1328,5,0))) -> 5.27 | D37: =B37*C37 -> 5.27
A38: Pimiento del padron. | B38: 0.075 | C38: =IF(ISNA(VLOOKUP(A38,'Listado de Artículos'!$B$16:$F$1328,5,0)),0,(VLOOKUP(A38,'Listado de Artículos'!$B$16:$F$1328,5,0))) -> 6.9 | D38: =B38*C38 -> 0.5175
A39: Pollo muslo fresco. | B39: 0.15 | C39: =IF(ISNA(VLOOKUP(A39,'Listado de Artículos'!$B$16:$F$1328,5,0)),0,(VLOOKUP(A39,'Listado de Artículos'!$B$16:$F$1328,5,0))) -> 2.88 | D39: =B39*C39 -> 0.432
A40: Butifarra fresca corta 14.cm. calçots. 90 gr porcianda | B40: 0.09 | C40: =IF(ISNA(VLOOKUP(A40,'Listado de Artículos'!$B$16:$F$1328,5,0)),0,(VLOOKUP(A40,'Listado de Artículos'!$B$16:$F$1328,5,0))) -> 6.15 | D40: =B40*C40 -> 0.5535
A41: Salsa Allioli. natural. bote de 1 lt. | B41: 0.03 | C41: =IF(ISNA(VLOOKUP(A41,'Listado de Artículos'!$B$16:$F$1328,5,0)),0,(VLOOKUP(A41,'Listado de Artículos'!$B$16:$F$1328,5,0))) -> 3.85 | D41: =B41*C41 -> 0.1155
A42: CALÇOTADA EN MESA ENSALADA. LECHUGA UNID. | B42: 1 | C42: =IF(ISNA(VLOOKUP(A42,'Listado de Artículos'!$B$16:$F$1328,5,0)),0,(VLOOKUP(A42,'Listado de Artículos'!$B$16:$F$1328,5,0))) -> 0 | D42: =B42*C42 -> 0
A43: MENU CALÇOTADA. CESTA DE PAN, TOMATE Y AJO. | B43: 1 | C43: =IF(ISNA(VLOOKUP(A43,'Listado de Artículos'!$B$16:$F$1328,5,0)),0,(VLOOKUP(A43,'Listado de Artículos'!$B$16:$F$1328,5,0))) -> 0.54 | D43: =B43*C43 -> 0.54
A44: Parrillada de verduras. Precio Pax. | B44: 1 | C44: =IF(ISNA(VLOOKUP(A44,'Listado de Artículos'!$B$16:$F$1328,5,0)),0,(VLOOKUP(A44,'Listado de Artículos'!$B$16:$F$1328,5,0))) -> 2.33 | D44: =B44*C44 -> 2.33
A45: POSTRES
A46: Crema Catalana. | B46: 0.5 | C46: =IF(ISNA(VLOOKUP(A46,'Listado de Artículos'!$B$16:$F$1328,5,0)),0,(VLOOKUP(A46,'Listado de Artículos'!$B$16:$F$1328,5,0))) -> 0.5 | D46: =B46*C46 -> 0.25
A47: PAN, AGUA, SELECCION DE VINOS Y CAFES
A48: CLOS PINELL TERRA TINTO ALTA | B48: 0.25 | C48: =IF(ISNA(VLOOKUP(A48,'Listado de Artículos'!$B$16:$F$1328,5,0)),0,(VLOOKUP(A48,'Listado de Artículos'!$B$16:$F$1328,5,0))) -> 0.9 | D48: =B48*C48 -> 0.225
A49: Agua Fon vella 1 LT Caja de 12 unid. | B49: 0.3 | C49: =IF(ISNA(VLOOKUP(A49,'Listado de Artículos'!$B$16:$F$1328,5,0)),0,(VLOOKUP(A49,'Listado de Artículos'!$B$16:$F$1328,5,0))) -> 0.8 | D49: =B49*C49 -> 0.24
A50: Cafe Natural. 1 kg. 120 cafes. 24,48€ .kg. 0,22 unid | B50: 1 | C50: =IF(ISNA(VLOOKUP(A50,'Listado de Artículos'!$B$16:$F$1328,5,0)),0,(VLOOKUP(A50,'Listado de Artículos'!$B$16:$F$1328,5,0))) -> 0.65 | D50: =B50*C50 -> 0.65
A52: ESCANDALLO | B52: 20 | C52: =+B52-(B52*0.1) -> 18 | D52: =SUM(D37:D50) -> 11.1235 | E52: =(D52*100/C52)/100 -> 0.61797222
A57: Propuesta de coctel Comunion Alejandro Fernandez. 16-05-25
A58: APERITIVOS FRIOS. | B58: MENU INFANTIL ALMUERZO.
A59: 1.- Montadito de pan de cristal y jamon iberico.
A60: 2.- Surtido de quesos internaciones y nacionales con embutidos ibericos. | B60: Jamon iberico a compartir y pan con tomate.
A61: 3.- Gazpacho de Frambuesa y bitter kas. | B61: Macarrones napolitana con parmesano rallado.
A62: 4.- Ajo blanco de coco, con sardina ahumada y uva. | B62: hamburguesa con patatas fritas.
A63: 5.- Salmorejo de sandia con polvo de jamon. | B63: Tarta de celebracion.
A64: 6.- Canape de salmon ahumado y queso a las finas hierbas. | B64: refrescos.
A65: 7.- Ostra del delta en escabeche de citricos con alga wakame. | B65: pan, agua mineral.
A67: APERITIVOS CALIENTES. | B67: MENU INFANTIL CENA A COMPARTIR
A68: 8.- Croqueta de jamon iberico.
A69: 9.- Lagrimita de pollo con salsa de mostaza, miel y curry. | B69: Jamon iberico a compartir y pan con tomate.
A70: 10.- Miniburguer de ternera con queso emmental y salsa cheddar | B70: Pizza napolitana.
A71: 11.- Brocheta de pollo con salsa tandori. | B71: Nuguets con patatas fritas.
A72: 12.- Degustacion de arroz negro. | B72: helado de vainilla y chocolate.a
A73: 13.- Degustacion de Fideua de marisco. | B73: refrescos.
B74: pan, agua mineral.
A75: POSTRE TARTA DE CELEBRACION A SELECCIONAR.
A77: tarta de celebracion. Lemon pie, massini o sacher.
A79: BEBIDAS Y VARIOS.
A80: Refresco, cerveza y vermouth.
A81: Clos pinell blanco D.O terra alta.
A82: Clos pinell tinto. D.O Terra alta.
A83: Copa de cava.
A84: Pan, agua mineral y cafes.
A90: Propuesta de menu bbq cena. comunion alejandro.
A91: Todo a compartir.
A92: 1.- Cesta de pan tostado, tomaco y ajo.
A93: 2.- Ensalada verde a compartir.
... A101: Clos pinell tinto. D.O Terra alta.

Sheet PLANTILLA COSTE MENU
A2: MENU CALÇOTADA CARTA. 15-12-25
A4: APERITIVO. | B4: P.V.P | C4: NETO | D4: COSTO | E4: FOOD COST
A5: CALÇOTADA. APERITIVO CARTA | B5: GR O KG. | C5: PRECIO KG | D5: EUROS/RACION.
A6: CALÇOTADA. APERITIVO CARTA | B6: 1 | C6: =IF(ISNA(VLOOKUP(A6,'Listado de Artículos'!$B$16:$F$1328,5,0)),0,(VLOOKUP(A6,'Listado de Artículos'!$B$16:$F$1328,5,0))) -> 0 | D6: =B6*C6 -> 0
A7: MENU Calçotada Vermuth | B7: 1 | C7: =IF(ISNA(VLOOKUP(A7,'Listado de Artículos'!$B$16:$F$1328,5,0)),0,(VLOOKUP(A7,'Listado de Artículos'!$B$16:$F$1328,5,0))) -> 0.47 | D7: =B7*C7 -> 0.47
A8: Agua Fon vella 1 LT Caja de 12 unid. | B8: 0.25 | C8: =IF(ISNA(VLOOKUP(A8,'Listado de Artículos'!$B$16:$F$1328,5,0)),0,(VLOOKUP(A8,'Listado de Artículos'!$B$16:$F$1328,5,0))) -> 0.8 | D8: =B8*C8 -> 0.2
A9: Vino negro Calçotada. BAG IN BOX. 20 LT. NEGRO. CELLER MAS ROIG. (35,57€). | B9: 0.35 | C9: =IF(ISNA(VLOOKUP(A9,'Listado de Artículos'!$B$16:$F$1328,5,0)),0,(VLOOKUP(A9,'Listado de Artículos'!$B$16:$F$1328,5,0))) -> 1.77 | D9: =B9*C9 -> 0.6195
A10: CALÇOTADA ILIMITADA.
A11: Calçots Valls. Majols. crudos | B11: 15 | C11: =IF(ISNA(VLOOKUP(A11,'Listado de Artículos'!$B$16:$F$1328,5,0)),0,(VLOOKUP(A11,'Listado de Artículos'!$B$16:$F$1328,5,0))) -> 0.16 | D11: =B11*C11 -> 2.4
A12: Salsa romesco. | B12: 0.125 | C12: =IF(ISNA(VLOOKUP(A12,'Listado de Artículos'!$B$16:$F$1328,5,0)),0,(VLOOKUP(A12,'Listado de Artículos'!$B$16:$F$1328,5,0))) -> 2.94 | D12: =B12*C12 -> 0.3675
A13: EN MESA. | F13: PESCADO.
A14: CALÇOTADA EN MESA ENSALADA. LECHUGA UNID. | B14: 1 | C14: =IF(ISNA(VLOOKUP(A14,'Listado de Artículos'!$B$16:$F$1328,5,0)),0,(VLOOKUP(A14,'Listado de Artículos'!$B$16:$F$1328,5,0))) -> 0 | D14: =B14*C14 -> 0
A15: MENU CALÇOTADA. CESTA DE PAN, TOMATE Y AJO. | B15: 1 | C15: =IF(ISNA(VLOOKUP(A15,'Listado de Artículos'!$B$16:$F$1328,5,0)),0,(VLOOKUP(A15,'Listado de Artículos'!$B$16:$F$1328,5,0))) -> 0.54 | D15: =B15*C15 -> 0.54
A16: MENU CALÇOTADA BOTIFARRA MONGETES BLANCAS | B16: 1 | C16: =IF(ISNA(VLOOKUP(A16,'Listado de Artículos'!$B$16:$F$1328,5,0)),0,(VLOOKUP(A16,'Listado de Artículos'!$B$16:$F$1328,5,0))) -> 0.84 | D16: =B16*C16 -> 0.84
A17: Salsa Allioli. natural. bote de 1 lt. | B17: 0.03 | C17: =IF(ISNA(VLOOKUP(A17,'Listado de Artículos'!$B$16:$F$1328,5,0)),0,(VLOOKUP(A17,'Listado de Artículos'!$B$16:$F$1328,5,0))) -> 3.85 | D17: =B17*C17 -> 0.1155
A18: PRINCIPAL | F18: CARNE
A19: MENU CALÇOTADA CORDERO Y BOTIFARRA NEGRA. | B19: 1 | C19: =IF(ISNA(VLOOKUP(A19,'Listado de Artículos'!$B$16:$F$1328,5,0)),0,(VLOOKUP(A19,'Listado de Artículos'!$B$16:$F$1328,5,0))) -> 2.8824 | D19: =B19*C19 -> 2.8824 | F19: Tournedo de solomillo Rossini.
A20: MENU CALÇOTADA GUARNICION DE CORDERO. | B20: 1 | C20: =IF(ISNA(VLOOKUP(A20,'Listado de Artículos'!$B$16:$F$1328,5,0)),0,(VLOOKUP(A20,'Listado de Artículos'!$B$16:$F$1328,5,0))) -> 0.96 | D20: =B20*C20 -> 0.96
A21: POSTRES
A22: Crema Catalana. | B22: 1 | C22: =IF(ISNA(VLOOKUP(A22,'Listado de Artículos'!$B$16:$F$1328,5,0)),0,(VLOOKUP(A22,'Listado de Artículos'!$B$16:$F$1328,5,0))) -> 0.5 | D22: =B22*C22 -> 0.5
A23: MENU CALÇOTADA NARANJA CON MIEL. POR PAX. | B23: 1 | C23: =IF(ISNA(VLOOKUP(A23,'Listado de Artículos'!$B$16:$F$1328,5,0)),0,(VLOOKUP(A23,'Listado de Artículos'!$B$16:$F$1328,5,0))) -> 0.37 | D23: =B23*C23 -> 0.37
A24: POSTRES
A25: CLOS PINELL TERRA TINTO ALTA | B25: 0.25 | C25: =IF(ISNA(VLOOKUP(A25,'Listado de Artículos'!$B$16:$F$1328,5,0)),0,(VLOOKUP(A25,'Listado de Artículos'!$B$16:$F$1328,5,0))) -> 0.9 | D25: =B25*C25 -> 0.225
A26: CAVA ROGER DE FLOR | B26: 0.15 | C26: =IF(ISNA(VLOOKUP(A26,'Listado de Artículos'!$B$16:$F$1328,5,0)),0,(VLOOKUP(A26,'Listado de Artículos'!$B$16:$F$1328,5,0))) -> 0 | D26: =B26*C26 -> 0
A27: Cafe Natural. 1 kg. 120 cafes. 24,48€ .kg. 0,22 unid | B27: 1 | C27: =IF(ISNA(VLOOKUP(A27,'Listado de Artículos'!$B$16:$F$1328,5,0)),0,(VLOOKUP(A27,'Listado de Artículos'!$B$16:$F$1328,5,0))) -> 0.65 | D27: =B27*C27 -> 0.65
A28: Agua Fon vella 1 LT Caja de 12 unid. | B28: 0.3 | C28: =IF(ISNA(VLOOKUP(A28,'Listado de Artículos'!$B$16:$F$1328,5,0)),0,(VLOOKUP(A28,'Listado de Artículos'!$B$16:$F$1328,5,0))) -> 0.8 | D28: =B28*C28 -> 0.24
A29: Cafe Natural. 1 kg. 120 cafes. 24,48€ .kg. 0,22 unid
A30: ESCANDALLO | B30: 75 | C30: =+B30-(B30*0.1) -> 67.5 | D30: =SUM(D6:D29) -> 11.3799 | E30: =(D30*100/C30)/100 -> 0.16859111

Sheet MENU FIN DE AÑO
A2: MENU FIN DE AÑO 2025 | G2: MENU EMBARAZADA RON | H2: MENU CUMPLEAÑOS PETER 4 PAX CENA 29-12
A4: APERITIVO. | B4: P.V.P | C4: NETO | D4: COSTO | E4: FOOD COST
A5: CALÇOTADA. APERITIVO CARTA | B5: GR O KG. | C5: PRECIO KG | D5: EUROS/RACION. | F5: APERITIVO | G5: APERITIVO | H5: APERITIVO
A6: Jamon de bellota. corta a cuchillo. sobre de 80 gr. unid. 149.35 precio kg. ojo cambiar | B6: 0.05 | C6: =IF(ISNA(VLOOKUP(A6,'Listado de Artículos'!$B$16:$F$1328,5,0)),0,(VLOOKUP(A6,'Listado de Artículos'!$B$16:$F$1328,5,0))) -> 12.16 | D6: =B6*C6 -> 0.608 | F6: Jamon de bellota y pan de cristal | G6: brocheta de verduras.
A7: A.P TARTAR DE SALMON MARINADO. | B7: 1 | C7: =IF(ISNA(VLOOKUP(A7,'Listado de Artículos'!$B$16:$F$1328,5,0)),0,(VLOOKUP(A7,'Listado de Artículos'!$B$16:$F$1328,5,0))) -> 0.58 | D7: =B7*C7 -> 0.58 | F7: blinis de salmon marinado, raifort y caviar de salmon | G7: mejillones. | H7: BITTERBALLEN A LA ESPAÑOLA. croquetas
A8: A.P ESPUMA DE ALLIPEBRE CON PULPO. | B8: 1 | C8: =IF(ISNA(VLOOKUP(A8,'Listado de Artículos'!$B$16:$F$1328,5,0)),0,(VLOOKUP(A8,'Listado de Artículos'!$B$16:$F$1328,5,0))) -> 0.78 | D8: =B8*C8 -> 0.78 | F8: Manzana con anguila ahumada y foie de pato. | G8: tartar de tomate con aguacate.
A9: ENTRANTE. | F9: PRIMERO. | G9: PRIMERO. | H9: PRIMERO.
B10: 1 | C10: 2.25 | D10: =B10*C10 -> 2.25 | F10: Crema de marisco, vieras con bombon de coco y curri. | G10: Crema de marisco, vieras con bombon de coco y curri. | H10: crema de calabaza.
A11: PESCADO. | F11: PESCADO. | G11: PESCADO. | H11: PESCADO.
B12: 1 | C12: 4.5 | D12: =B12*C12 -> 4.5 | F12: Lenguado a la menier de yondu con hinojo y avellanas | G12: Lenguado a la menier de yondu con hinojo y avellanas | H12: bacalao con muselina de alioli y trinchat de col y patata
A13: PRINCIPAL | F13: CARNE | G13: CARNE | H13: CARNE
B14: 1 | C14: 5.2 | D14: =B14*C14 -> 5.2 | F14: Tournedo de solomillo Rossini con chalotas glaseadas. | G14: pluma de cerdo iberico de bellota.. con chalotas glaseadas. | H14: Chuleta de cerdo madurado, con parrillada de verduras
A16: POSTRES | F16: POSTRE | G16: POSTRE | H16: POSTRE
B17: 1 | C17: 2.25 | D17: =B17*C17 -> 2.25 | F17: lingote de ferrero rocher, espuma de baeylis, y frambuesa liofilizada | G17: lingote de ferrero rocher, espuma de baeylis, y frambuesa liofilizada | H17: HELADO
B18: 1 | C18: 1.5 | D18: =B18*C18 -> 1.5 | F18: COTILLON | G18: COTILLON
A19: BODEGA | F19: UVAS COTILLON. | G19: UVAS COTILLON. | H19: UVAS COTILLON.
A20: Cava Petit Instant. Botella | B20: 0.2 | C20: =IF(ISNA(VLOOKUP(A20,'Listado de Artículos'!$B$16:$F$1328,5,0)),0,(VLOOKUP(A20,'Listado de Artículos'!$B$16:$F$1328,5,0))) -> 5.38 | D20: =B20*C20 -> 1.076
B21: 0.2 | C21: 5.9 | D21: =B21*C21 -> 1.18 | F21: TURRONES Y NEULAS. | G21: TURRONES Y NEULAS. | H21: TURRONES Y NEULAS.
B22: 0.2 | C22: 6.5 | D22: =B22*C22 -> 1.3 | F22: mas cabellut tinto. | G22: mas cabellut tinto. | H22: mas cabellut tinto.
A23: Agua Fon vella 1 LT Caja de 12 unid. | B23: 0.3 | C23: =IF(ISNA(VLOOKUP(A23,'Listado de Artículos'!$B$16:$F$1328,5,0)),0,(VLOOKUP(A23,'Listado de Artículos'!$B$16:$F$1328,5,0))) -> 0.8 | D23: =B23*C23 -> 0.24 | F23: L'oratge blanco. | G23: L'oratge blanco. | H23: L'oratge blanco.
A24: Cafe Natural. 1 kg. 120 cafes. 24,48€ .kg. 0,22 unid | B24: 1 | C24: =IF(ISNA(VLOOKUP(A24,'Listado de Artículos'!$B$16:$F$1328,5,0)),0,(VLOOKUP(A24,'Listado de Artículos'!$B$16:$F$1328,5,0))) -> 0.65 | D24: =B24*C24 -> 0.65
A25: Cafe Natural. 1 kg. 120 cafes. 24,48€ .kg. 0,22 unid
A26: ESCANDALLO | B26: 75 | C26: =+B26-(B26*0.1) -> 67.5 | D26: =SUM(D6:D24) -> 22.114 | E26: =(D26*100/C26)/100 -> 0.32761481

Sheet MENU AGENCIA 25€ CALÇOTADA
A2: MENU CALÇOTADA CARTA. 15-12-25
A4: APERITIVO. | B4: P.V.P | C4: NETO | D4: COSTO | E4: FOOD COST
A5: CALÇOTADA. APERITIVO CARTA | B5: GR O KG. | C5: PRECIO KG | D5: EUROS/RACION.
A6: OLIVAS ARBERQUINAS EXTRA. 10 KG. 24,90€ BOTE DE 10 KG | B6: 0.01 | C6: =IF(ISNA(VLOOKUP(A6,'Listado de Artículos'!$B$16:$F$1328,5,0)),0,(VLOOKUP(A6,'Listado de Artículos'!$B$16:$F$1328,5,0))) -> 8.5 | D6: =B6*C6 -> 0.085
A7: Fuet cortado bandeja de 1 kg* calçotada. | B7: 0.01 | C7: =IF(ISNA(VLOOKUP(A7,'Listado de Artículos'!$B$16:$F$1328,5,0)),0,(VLOOKUP(A7,'Listado de Artículos'!$B$16:$F$1328,5,0))) -> 15.87 | D7: =B7*C7 -> 0.1587
A8: AVELLANA APERITIVO TOSTADA REPELADA | B8: 0.01 | C8: =IF(ISNA(VLOOKUP(A8,'Listado de Artículos'!$B$16:$F$1328,5,0)),0,(VLOOKUP(A8,'Listado de Artículos'!$B$16:$F$1328,5,0))) -> 522.05 | D8: =B8*C8 -> 5.2205
A9: CALÇOTADA ILIMITADA.
A10: Calçots Valls. Majols. crudos | B10: 15 | C10: =IF(ISNA(VLOOKUP(A10,'Listado de Artículos'!$B$16:$F$1328,5,0)),0,(VLOOKUP(A10,'Listado de Artículos'!$B$16:$F$1328,5,0))) -> 0.16 | D10: =B10*C10 -> 2.4
A11: Salsa romesco. | B11: 0.125 | C11: =IF(ISNA(VLOOKUP(A11,'Listado de Artículos'!$B$16:$F$1328,5,0)),0,(VLOOKUP(A11,'Listado de Artículos'!$B$16:$F$1328,5,0))) -> 2.94 | D11: =B11*C11 -> 0.3675
A12: EN MESA.
A13: MENU CALÇOTADA. CESTA DE PAN, TOMATE Y AJO. | B13: 1 | C13: =IF(ISNA(VLOOKUP(A13,'Listado de Artículos'!$B$16:$F$1328,5,0)),0,(VLOOKUP(A13,'Listado de Artículos'!$B$16:$F$1328,5,0))) -> 0.54 | D13: =B13*C13 -> 0.54
A14: MENU CALÇOTADA BOTIFARRA MONGETES BLANCAS | B14: 1 | C14: =IF(ISNA(VLOOKUP(A14,'Listado de Artículos'!$B$16:$F$1328,5,0)),0,(VLOOKUP(A14,'Listado de Artículos'!$B$16:$F$1328,5,0))) -> 0.84 | D14: =B14*C14 -> 0.84
A15: Pollo muslo fresco. | B15: 0.1 | C15: =IF(ISNA(VLOOKUP(A15,'Listado de Artículos'!$B$16:$F$1328,5,0)),0,(VLOOKUP(A15,'Listado de Artículos'!$B$16:$F$1328,5,0))) -> 2.88 | D15: =B15*C15 -> 0.288
A16: Butifarra negra* calçotada racionada a 70 gr. | B16: 0.07 | C16: =IF(ISNA(VLOOKUP(A16,'Listado de Artículos'!$B$16:$F$1328,5,0)),0,(VLOOKUP(A16,'Listado de Artículos'!$B$16:$F$1328,5,0))) -> 7.6 | D16: =B16*C16 -> 0.532
A17: Patata Monalisa. | B17: 0.15 | C17: =IF(ISNA(VLOOKUP(A17,'Listado de Artículos'!$B$16:$F$1328,5,0)),0,(VLOOKUP(A17,'Listado de Artículos'!$B$16:$F$1328,5,0))) -> 2 | D17: =B17*C17 -> 0.3
A18: POSTRES
A19: Crema Catalana. | B19: 1 | C19: =IF(ISNA(VLOOKUP(A19,'Listado de Artículos'!$B$16:$F$1328,5,0)),0,(VLOOKUP(A19,'Listado de Artículos'!$B$16:$F$1328,5,0))) -> 0.5 | D19: =B19*C19 -> 0.5
A20: POSTRES
A21: Vino negro Calçotada. BAG IN BOX. 20 LT. NEGRO. CELLER MAS ROIG. (35,57€). | B21: 0.2 | C21: =IF(ISNA(VLOOKUP(A21,'Listado de Artículos'!$B$16:$F$1328,5,0)),0,(VLOOKUP(A21,'Listado de Artículos'!$B$16:$F$1328,5,0))) -> 1.77 | D21: =B21*C21 -> 0.354
A22: Cafe Natural. 1 kg. 120 cafes. 24,48€ .kg. 0,22 unid | B22: 1 | C22: =IF(ISNA(VLOOKUP(A22,'Listado de Artículos'!$B$16:$F$1328,5,0)),0,(VLOOKUP(A22,'Listado de Artículos'!$B$16:$F$1328,5,0))) -> 0.65 | D22: =B22*C22 -> 0.65
A23: Agua Fon vella 1 LT Caja de 12 unid. | B23: 0.3 | C23: =IF(ISNA(VLOOKUP(A23,'Listado de Artículos'!$B$16:$F$1328,5,0)),0,(VLOOKUP(A23,'Listado de Artículos'!$B$16:$F$1328,5,0))) -> 0.8 | D23: =B23*C23 -> 0.24
B24: 0.15 | C24: =IF(ISNA(VLOOKUP(A24,'Listado de Artículos'!$B$16:$F$1328,5,0)),0,(VLOOKUP(A24,'Listado de Artículos'!$B$16:$F$1328,5,0))) -> 0 | D24: =B24*C24 -> 0
A26: ESCANDALLO | B26: 25 | C26: =B26/1.1 -> 22.727273 | D26: =SUM(D8:D24) -> 12.232 | E26: =(D26*100/C26)/100 -> 0.538208

Sheet Menú calçotada niños
A2: MENU CALÇOTADA CARTA. 15-12-25
A4: APERITIVO. | B4: P.V.P | C4: NETO | D4: COSTO | E4: FOOD COST
A5: CALÇOTADA. APERITIVO CARTA | B5: GR O KG. | C5: PRECIO KG | D5: EUROS/RACION.
B6: 1 | C6: =IF(ISNA(VLOOKUP(A6,'Listado de Artículos'!$B$16:$F$1328,5,0)),0,(VLOOKUP(A6,'Listado de Artículos'!$B$16:$F$1328,5,0))) -> 0 | D6: =B6*C6 -> 0
A7: Coca-cola Lata 33cl*24. sin cargo 3 pqt | B7: 1 | C7: =IF(ISNA(VLOOKUP(A7,'Listado de Artículos'!$B$16:$F$1328,5,0)),0,(VLOOKUP(A7,'Listado de Artículos'!$B$16:$F$1328,5,0))) -> 22.75 | D7: =B7*C7 -> 22.75
A8: Agua Fon vella 1 LT Caja de 12 unid. | B8: 0.25 | C8: =IF(ISNA(VLOOKUP(A8,'Listado de Artículos'!$B$16:$F$1328,5,0)),0,(VLOOKUP(A8,'Listado de Artículos'!$B$16:$F$1328,5,0))) -> 0.8 | D8: =B8*C8 -> 0.2
B9: 0.25 | C9: =IF(ISNA(VLOOKUP(A9,'Listado de Artículos'!$B$16:$F$1328,5,0)),0,(VLOOKUP(A9,'Listado de Artículos'!$B$16:$F$1328,5,0))) -> 0 | D9: =B9*C9 -> 0
A10: CALÇOTADA ILIMITADA.
B11: 15 | C11: =IF(ISNA(VLOOKUP(A11,'Listado de Artículos'!$B$16:$F$1328,5,0)),0,(VLOOKUP(A11,'Listado de Artículos'!$B$16:$F$1328,5,0))) -> 0 | D11: =B11*C11 -> 0
B12: 0.125 | C12: =IF(ISNA(VLOOKUP(A12,'Listado de Artículos'!$B$16:$F$1328,5,0)),0,(VLOOKUP(A12,'Listado de Artículos'!$B$16:$F$1328,5,0))) -> 0 | D12: =B12*C12 -> 0
A13: EN MESA.
B14: 1 | C14: =IF(ISNA(VLOOKUP(A14,'Listado de Artículos'!$B$16:$F$1328,5,0)),0,(VLOOKUP(A14,'Listado de Artículos'!$B$16:$F$1328,5,0))) -> 0 | D14: =B14*C14 -> 0
A15: MENU CALÇOTADA. CESTA DE PAN, TOMATE Y AJO. | B15: 1 | C15: =IF(ISNA(VLOOKUP(A15,'Listado de Artículos'!$B$16:$F$1328,5,0)),0,(VLOOKUP(A15,'Listado de Artículos'!$B$16:$F$1328,5,0))) -> 0.54 | D15: =B15*C15 -> 0.54
A16: M.P menú infantil Pollo rebozado con patatas | B16: 1 | C16: =IF(ISNA(VLOOKUP(A16,'Listado de Artículos'!$B$16:$F$1328,5,0)),0,(VLOOKUP(A16,'Listado de Artículos'!$B$16:$F$1328,5,0))) -> 1.5 | D16: =B16*C16 -> 1.5
A17: Salsa Allioli. natural. bote de 1 lt. | B17: 0.03 | C17: =IF(ISNA(VLOOKUP(A17,'Listado de Artículos'!$B$16:$F$1328,5,0)),0,(VLOOKUP(A17,'Listado de Artículos'!$B$16:$F$1328,5,0))) -> 3.85 | D17: =B17*C17 -> 0.1155
A18: M.P Menú infantil Boloñesa | B18: 1 | C18: =IF(ISNA(VLOOKUP(A18,'Listado de Artículos'!$B$16:$F$1328,5,0)),0,(VLOOKUP(A18,'Listado de Artículos'!$B$16:$F$1328,5,0))) -> 2 | D18: =B18*C18 -> 2
A19: PRINCIPAL
B20: 1 | C20: =IF(ISNA(VLOOKUP(A20,'Listado de Artículos'!$B$16:$F$1328,5,0)),0,(VLOOKUP(A20,'Listado de Artículos'!$B$16:$F$1328,5,0))) -> 0 | D20: =B20*C20 -> 0
B21: 1 | C21: =IF(ISNA(VLOOKUP(A21,'Listado de Artículos'!$B$16:$F$1328,5,0)),0,(VLOOKUP(A21,'Listado de Artículos'!$B$16:$F$1328,5,0))) -> 0 | D21: =B21*C21 -> 0
A22: POSTRES
A24: Crema Catalana. | B24: 1 | C24: =IF(ISNA(VLOOKUP(A24,'Listado de Artículos'!$B$16:$F$1328,5,0)),0,(VLOOKUP(A24,'Listado de Artículos'!$B$16:$F$1328,5,0))) -> 0.5 | D24: =B24*C24 -> 0.5
A25: POSTRES
B26: 0.25 | C26: =IF(ISNA(VLOOKUP(A26,'Listado de Artículos'!$B$16:$F$1328,5,0)),0,(VLOOKUP(A26,'Listado de Artículos'!$B$16:$F$1328,5,0))) -> 0 | D26: =B26*C26 -> 0
B27: 0.15 | C27: =IF(ISNA(VLOOKUP(A27,'Listado de Artículos'!$B$16:$F$1328,5,0)),0,(VLOOKUP(A27,'Listado de Artículos'!$B$16:$F$1328,5,0))) -> 0 | D27: =B27*C27 -> 0
B28: 1 | C28: =IF(ISNA(VLOOKUP(A28,'Listado de Artículos'!$B$16:$F$1328,5,0)),0,(VLOOKUP(A28,'Listado de Artículos'!$B$16:$F$1328,5,0))) -> 0 | D28: =B28*C28 -> 0
B29: 0.3 | C29: =IF(ISNA(VLOOKUP(A29,'Listado de Artículos'!$B$16:$F$1328,5,0)),0,(VLOOKUP(A29,'Listado de Artículos'!$B$16:$F$1328,5,0))) -> 0 | D29: =B29*C29 -> 0
A30: Cafe Natural. 1 kg. 120 cafes. 24,48€ .kg. 0,22 unid
A31: ESCANDALLO | B31: 22 | C31: =+B31-(B31*0.1) -> 19.8 | D31: =SUM(D6:D30) -> 27.6055 | E31: =(D31*100/C31)/100 -> 1.3942172

Sheet Menú calçotada vegano
A2: MENU CALÇOTADA CARTA. 15-12-25
A4: APERITIVO. | B4: P.V.P | C4: NETO | D4: COSTO | E4: FOOD COST
A5: CALÇOTADA. APERITIVO CARTA | B5: GR O KG. | C5: PRECIO KG | D5: EUROS/RACION.
A6: Aperitivo completo para calçotada. | B6: 1 | C6: =IF(ISNA(VLOOKUP(A6,'Listado de Artículos'!$B$16:$F$1328,5,0)),0,(VLOOKUP(A6,'Listado de Artículos'!$B$16:$F$1328,5,0))) -> 0.44 | D6: =B6*C6 -> 0.44
A7: MENU Calçotada Vermuth | B7: 1 | C7: =IF(ISNA(VLOOKUP(A7,'Listado de Artículos'!$B$16:$F$1328,5,0)),0,(VLOOKUP(A7,'Listado de Artículos'!$B$16:$F$1328,5,0))) -> 0.47 | D7: =B7*C7 -> 0.47
A8: Agua Fon vella 1 LT Caja de 12 unid. | B8: 0.25 | C8: =IF(ISNA(VLOOKUP(A8,'Listado de Artículos'!$B$16:$F$1328,5,0)),0,(VLOOKUP(A8,'Listado de Artículos'!$B$16:$F$1328,5,0))) -> 0.8 | D8: =B8*C8 -> 0.2
B9: 0.35 | C9: =IF(ISNA(VLOOKUP(A9,'Listado de Artículos'!$B$16:$F$1328,5,0)),0,(VLOOKUP(A9,'Listado de Artículos'!$B$16:$F$1328,5,0))) -> 0 | D9: =B9*C9 -> 0
A10: CALÇOTADA ILIMITADA.
A11: Calçots Valls. Majols. crudos | B11: 15 | C11: =IF(ISNA(VLOOKUP(A11,'Listado de Artículos'!$B$16:$F$1328,5,0)),0,(VLOOKUP(A11,'Listado de Artículos'!$B$16:$F$1328,5,0))) -> 0.16 | D11: =B11*C11 -> 2.4
A12: Salsa romesco. | B12: 0.125 | C12: =IF(ISNA(VLOOKUP(A12,'Listado de Artículos'!$B$16:$F$1328,5,0)),0,(VLOOKUP(A12,'Listado de Artículos'!$B$16:$F$1328,5,0))) -> 2.94 | D12: =B12*C12 -> 0.3675
A13: EN MESA.
A14: Ensalada para calçotada terminada lechuga de pages. | B14: 1 | C14: =IF(ISNA(VLOOKUP(A14,'Listado de Artículos'!$B$16:$F$1328,5,0)),0,(VLOOKUP(A14,'Listado de Artículos'!$B$16:$F$1328,5,0))) -> 0.7 | D14: =B14*C14 -> 0.7
A15: MENU CALÇOTADA. CESTA DE PAN, TOMATE Y AJO. | B15: 1 | C15: =IF(ISNA(VLOOKUP(A15,'Listado de Artículos'!$B$16:$F$1328,5,0)),0,(VLOOKUP(A15,'Listado de Artículos'!$B$16:$F$1328,5,0))) -> 0.54 | D15: =B15*C15 -> 0.54
A16: MONGETAS NATURALES. 3 KG( 2,89€ LATA DE 3 KG). | B16: 0.8 | C16: =IF(ISNA(VLOOKUP(A16,'Listado de Artículos'!$B$16:$F$1328,5,0)),0,(VLOOKUP(A16,'Listado de Artículos'!$B$16:$F$1328,5,0))) -> 28.95 | D16: =B16*C16 -> 23.16
A17: Salsa Allioli. natural. bote de 1 lt. | B17: 0.03 | C17: =IF(ISNA(VLOOKUP(A17,'Listado de Artículos'!$B$16:$F$1328,5,0)),0,(VLOOKUP(A17,'Listado de Artículos'!$B$16:$F$1328,5,0))) -> 3.85 | D17: =B17*C17 -> 0.1155
A18: PRINCIPAL
A19: Hamburguesa vegana | B19: 1 | C19: =IF(ISNA(VLOOKUP(A19,'Listado de Artículos'!$B$16:$F$1328,5,0)),0,(VLOOKUP(A19,'Listado de Artículos'!$B$16:$F$1328,5,0))) -> 2.5 | D19: =B19*C19 -> 2.5
A20: MENU CALÇOTADA GUARNICION DE CORDERO. | B20: 1 | C20: =IF(ISNA(VLOOKUP(A20,'Listado de Artículos'!$B$16:$F$1328,5,0)),0,(VLOOKUP(A20,'Listado de Artículos'!$B$16:$F$1328,5,0))) -> 0.96 | D20: =B20*C20 -> 0.96
A21: POSTRES
A22: Crema Catalana. | B22: 1 | C22: =IF(ISNA(VLOOKUP(A22,'Listado de Artículos'!$B$16:$F$1328,5,0)),0,(VLOOKUP(A22,'Listado de Artículos'!$B$16:$F$1328,5,0))) -> 0.5 | D22: =B22*C22 -> 0.5
A23: MENU CALÇOTADA NARANJA CON MIEL. POR PAX. | B23: 1 | C23: =IF(ISNA(VLOOKUP(A23,'Listado de Artículos'!$B$16:$F$1328,5,0)),0,(VLOOKUP(A23,'Listado de Artículos'!$B$16:$F$1328,5,0))) -> 0.37 | D23: =B23*C23 -> 0.37
A24: POSTRES
A25: CLOS PINELL TERRA TINTO ALTA | B25: 0.25 | C25: =IF(ISNA(VLOOKUP(A25,'Listado de Artículos'!$B$16:$F$1328,5,0)),0,(VLOOKUP(A25,'Listado de Artículos'!$B$16:$F$1328,5,0))) -> 0.9 | D25: =B25*C25 -> 0.225
A26: CAVA ROGER DE FLOR | B26: 0.15 | C26: =IF(ISNA(VLOOKUP(A26,'Listado de Artículos'!$B$16:$F$1328,5,0)),0,(VLOOKUP(A26,'Listado de Artículos'!$B$16:$F$1328,5,0))) -> 0 | D26: =B26*C26 -> 0
A27: Cafe Natural. 1 kg. 120 cafes. 24,48€ .kg. 0,22 unid | B27: 1 | C27: =IF(ISNA(VLOOKUP(A27,'Listado de Artículos'!$B$16:$F$1328,5,0)),0,(VLOOKUP(A27,'Listado de Artículos'!$B$16:$F$1328,5,0))) -> 0.65 | D27: =B27*C27 -> 0.65
A28: Agua Fon vella 1 LT Caja de 12 unid. | B28: 0.3 | C28: =IF(ISNA(VLOOKUP(A28,'Listado de Artículos'!$B$16:$F$1328,5,0)),0,(VLOOKUP(A28,'Listado de Artículos'!$B$16:$F$1328,5,0))) -> 0.8 | D28: =B28*C28 -> 0.24
A30: ESCANDALLO | B30: 45 | C30: =+B30-(B30*0.1) -> 40.5 | D30: =SUM(D6:D29) -> 33.838 | E30: =(D30*100/C30)/100 -> 0.83550617

Sheet M.P COCTEL COMUNIONES.
C2: CALÇOTADA MAS BORONAT
C3: FICHA TÉCNICA PLATO
C6: ARTÍCULO | D6: SALSA ROMESCO PARA CALÇOTS.
C7: TAPA | D7: ELABORADOS.
C8: KG | D8: 15 | E8: Coste TOTAL | G8: =SUM(K11:K22) -> 346.638 | H8: Coste KG | J8: =G8/D8 -> 23.1092
B10: ARTICULO | C10: KG | D10: €/UN | E10: BRUTO | F10: NETO | G10: %NETO | H10: %DESP | I10: DESP | J10: SUCIO | K10: € / RACION
B11: Tomate Maduro. | C11: 12 | D11: =IF(ISNA(VLOOKUP(B11,'Listado de Artículos'!$B$16:$F$1328,5,0)),0,(VLOOKUP(B11,'Listado de Artículos'!$B$16:$F$1328,5,0))) -> 13.9 | E11: 1 | F11: 1 | G11: =IF(E11>0,(F11/E11),"") -> 1 | H11: =IF(E11>0,(100%-G11),"") -> 0 | I11: =IF(C11>0,(H11*C11/G11),"") -> 0 | J11: =IF(C11>0,(C11+I11),"") -> 12 | K11: =IF(D11>0,(D11*J11),"") -> 166.8
B12: Ajo rojo extra a granel. | C12: 1.4 | D12: =IF(ISNA(VLOOKUP(B12,'Listado de Artículos'!$B$16:$F$1328,5,0)),0,(VLOOKUP(B12,'Listado de Artículos'!$B$16:$F$1328,5,0))) -> 2 | E12: 1 | F12: 1 | G12: =IF(E12>0,(F12/E12),"") -> 1 | H12: =IF(E12>0,(100%-G12),"") -> 0 | I12: =IF(C12>0,(H12*C12/G12),"") -> 0 | J12: =IF(C12>0,(C12+I12),"") -> 1.4 | K12: =IF(D12>0,(D12*J12),"") -> 2.8
B13: ACEITE DE OLIVA SUAVE 5 LT | C13: 3 | D13: =IF(ISNA(VLOOKUP(B13,'Listado de Artículos'!$B$16:$F$1328,5,0)),0,(VLOOKUP(B13,'Listado de Artículos'!$B$16:$F$1328,5,0))) -> 5.95 | E13: 1 | F13: 1 | G13: =IF(E13>0,(F13/E13),"") -> 1 | H13: =IF(E13>0,(100%-G13),"") -> 0 | I13: =IF(C13>0,(H13*C13/G13),"") -> 0 | J13: =IF(C13>0,(C13+I13),"") -> 3 | K13: =IF(D13>0,(D13*J13),"") -> 17.85
B14: ACEITE DE OLIVA VIRGEN EXTRA SALOMO . | C14: 3 | D14: =IF(ISNA(VLOOKUP(B14,'Listado de Artículos'!$B$16:$F$1328,5,0)),0,(VLOOKUP(B14,'Listado de Artículos'!$B$16:$F$1328,5,0))) -> 8.97 | E14: 1 | F14: 1 | G14: =IF(E14>0,(F14/E14),"") -> 1 | H14: =IF(E14>0,(100%-G14),"") -> 0 | I14: =IF(C14>0,(H14*C14/G14),"") -> 0 | J14: =IF(C14>0,(C14+I14),"") -> 3 | K14: =IF(D14>0,(D14*J14),"") -> 26.91
B15: Almendra tostada repelada | C15: 1.5 | D15: =IF(ISNA(VLOOKUP(B15,'Listado de Artículos'!$B$16:$F$1328,5,0)),0,(VLOOKUP(B15,'Listado de Artículos'!$B$16:$F$1328,5,0))) -> 85.56 | E15: 1 | F15: 1 | G15: =IF(E15>0,(F15/E15),"") -> 1 | H15: =IF(E15>0,(100%-G15),"") -> 0 | I15: =IF(C15>0,(H15*C15/G15),"") -> 0 | J15: =IF(C15>0,(C15+I15),"") -> 1.5 | K15: =IF(D15>0,(D15*J15),"") -> 128.34
B16: AVELLANA TOSTADA PELADA. | C16: 1.5 | D16: =IF(ISNA(VLOOKUP(B16,'Listado de Artículos'!$B$16:$F$1328,5,0)),0,(VLOOKUP(B16,'Listado de Artículos'!$B$16:$F$1328,5,0))) -> 1.15 | E16: 1 | F16: 1 | G16: =IF(E16>0,(F16/E16),"") -> 1 | H16: =IF(E16>0,(100%-G16),"") -> 0 | I16: =IF(C16>0,(H16*C16/G16),"") -> 0 | J16: =IF(C16>0,(C16+I16),"") -> 1.5 | K16: =IF(D16>0,(D16*J16),"") -> 1.725
B17: PIMENTON DULCE DE LA VERA | C17: 0.025 | D17: =IF(ISNA(VLOOKUP(B17,'Listado de Artículos'!$B$16:$F$1328,5,0)),0,(VLOOKUP(B17,'Listado de Artículos'!$B$16:$F$1328,5,0))) -> 23 | E17: 1 | F17: 1 | G17: =IF(E17>0,(F17/E17),"") -> 1 | H17: =IF(E17>0,(100%-G17),"") -> 0 | I17: =IF(C17>0,(H17*C17/G17),"") -> 0 | J17: =IF(C17>0,(C17+I17),"") -> 0.025 | K17: =IF(D17>0,(D17*J17),"") -> 0.575
B18: Vinagre de modena garrafa de 5 lt. | C18: 0.25 | D18: =IF(ISNA(VLOOKUP(B18,'Listado de Artículos'!$B$16:$F$1328,5,0)),0,(VLOOKUP(B18,'Listado de Artículos'!$B$16:$F$1328,5,0))) -> 1 | E18: 1 | F18: 1 | G18: =IF(E18>0,(F18/E18),"") -> 1 | H18: =IF(E18>0,(100%-G18),"") -> 0 | I18: =IF(C18>0,(H18*C18/G18),"") -> 0 | J18: =IF(C18>0,(C18+I18),"") -> 0.25 | K18: =IF(D18>0,(D18*J18),"") -> 0.25
B19: Vinagre de jerez | C19: 0.05 | D19: =IF(ISNA(VLOOKUP(B19,'Listado de Artículos'!$B$16:$F$1328,5,0)),0,(VLOOKUP(B19,'Listado de Artículos'!$B$16:$F$1328,5,0))) -> 4.5 | E19: 1 | F19: 1 | G19: =IF(E19>0,(F19/E19),"") -> 1 | H19: =IF(E19>0,(100%-G19),"") -> 0 | I19: =IF(C19>0,(H19*C19/G19),"") -> 0 | J19: =IF(C19>0,(C19+I19),"") -> 0.05 | K19: =IF(D19>0,(D19*J19),"") -> 0.225
B20: Cayena entera. | C20: 0.01 | D20: =IF(ISNA(VLOOKUP(B20,'Listado de Artículos'!$B$16:$F$1328,5,0)),0,(VLOOKUP(B20,'Listado de Artículos'!$B$16:$F$1328,5,0))) -> 1.55 | E20: 1 | F20: 1 | G20: =IF(E20>0,(F20/E20),"") -> 1 | H20: =IF(E20>0,(100%-G20),"") -> 0 | I20: =IF(C20>0,(H20*C20/G20),"") -> 0 | J20: =IF(C20>0,(C20+I20),"") -> 0.01 | K20: =IF(D20>0,(D20*J20),"") -> 0.0155
B21: Sal gruesa | C21: 0.06 | D21: =IF(ISNA(VLOOKUP(B21,'Listado de Artículos'!$B$16:$F$1328,5,0)),0,(VLOOKUP(B21,'Listado de Artículos'!$B$16:$F$1328,5,0))) -> 3.5 | E21: 1 | F21: 1 | G21: =IF(E21>0,(F21/E21),"") -> 1 | H21: =IF(E21>0,(100%-G21),"") -> 0 | I21: =IF(C21>0,(H21*C21/G21),"") -> 0 | J21: =IF(C21>0,(C21+I21),"") -> 0.06 | K21: =IF(D21>0,(D21*J21),"") -> 0.21
B22: Cane de ñora " la legua". bote 650 gr. | C22: 0.05 | D22: =IF(ISNA(VLOOKUP(B22,'Listado de Artículos'!$B$16:$F$1328,5,0)),0,(VLOOKUP(B22,'Listado de Artículos'!$B$16:$F$1328,5,0))) -> 18.75 | E22: 1 | F22: 1 | G22: =IF(E22>0,(F22/E22),"") -> 1 | H22: =IF(E22>0,(100%-G22),"") -> 0 | I22: =IF(C22>0,(H22*C22/G22),"") -> 0 | J22: =IF(C22>0,(C22+I22),"") -> 0.05 | K22: =IF(D22>0,(D22*J22),"") -> 0.9375
A24: M.P
C28: CALÇOTADA MAS BORONAT
C29: FICHA TÉCNICA PLATO
C32: ARTÍCULO | D32: SALSA ROMESCO PARA CALÇOTS.
C33: TAPA | D33: ELABORADOS.
C34: KG | D34: 1 | E34: Coste TOTAL | G34: =SUM(K37:K48) -> 2.3225 | H34: Coste KG | J34: =G34/D34 -> 2.3225
B36: ARTICULO | C36: KG | D36: €/UN | E36: BRUTO | F36: NETO | G36: %NETO | H36: %DESP | I36: DESP | J36: SUCIO | K36: € / RACION
B37: Butifarra fresca corta 14.cm. calçots. 90 gr porcianda | C37: 0.18 | D37: =IF(ISNA(VLOOKUP(B37,'Listado de Artículos'!$B$16:$F$1328,5,0)),0,(VLOOKUP(B37,'Listado de Artículos'!$B$16:$F$1328,5,0))) -> 6.15 | E37: 1 | F37: 1 | G37: =IF(E37>0,(F37/E37),"") -> 1 | H37: =IF(E37>0,(100%-G37),"") -> 0 | I37: =IF(C37>0,(H37*C37/G37),"") -> 0 | J37: =IF(C37>0,(C37+I37),"") -> 0.18 | K37: =IF(D37>0,(D37*J37),"") -> 1.107
B38: Mongetes del ganxet. lata de 3 kg-17,22€ | C38: 0.15 | D38: =IF(ISNA(VLOOKUP(B38,'Listado de Artículos'!$B$16:$F$1328,5,0)),0,(VLOOKUP(B38,'Listado de Artículos'!$B$16:$F$1328,5,0))) -> 0.2 | E38: 1 | F38: 1 | G38: =IF(E38>0,(F38/E38),"") -> 1 | H38: =IF(E38>0,(100%-G38),"") -> 0 | I38: =IF(C38>0,(H38*C38/G38),"") -> 0 | J38: =IF(C38>0,(C38+I38),"") -> 0.15 | K38: =IF(D38>0,(D38*J38),"") -> 0.03
B39: Picada de ajo y perejil. | C39: 0.05 | D39: =IF(ISNA(VLOOKUP(B39,'Listado de Artículos'!$B$16:$F$1328,5,0)),0,(VLOOKUP(B39,'Listado de Artículos'!$B$16:$F$1328,5,0))) -> 23.71 | E39: 1 | F39: 1 | G39: =IF(E39>0,(F39/E39),"") -> 1 | H39: =IF(E39>0,(100%-G39),"") -> 0 | I39: =IF(C39>0,(H39*C39/G39),"") -> 0 | J39: =IF(C39>0,(C39+I39),"") -> 0.05 | K39: =IF(D39>0,(D39*J39),"") -> 1.1855
C40: 3 | D40: =IF(ISNA(VLOOKUP(B40,'Listado de Artículos'!$B$16:$F$1328,5,0)),0,(VLOOKUP(B40,'Listado de Artículos'!$B$16:$F$1328,5,0))) -> 0 | E40: 1 | F40: 1 | G40: =IF(E40>0,(F40/E40),"") -> 1 | H40: =IF(E40>0,(100%-G40),"") -> 0 | I40: =IF(C40>0,(H40*C40/G40),"") -> 0 | J40: =IF(C40>0,(C40+I40),"") -> 3 | K40: =IF(D40>0,(D40*J40),"")
C41: 1.5 | D41: =IF(ISNA(VLOOKUP(B41,'Listado de Artículos'!$B$16:$F$1328,5,0)),0,(VLOOKUP(B41,'Listado de Artículos'!$B$16:$F$1328,5,0))) -> 0 | E41: 1 | F41: 1 | G41: =IF(E41>0,(F41/E41),"") -> 1 | H41: =IF(E41>0,(100%-G41),"") -> 0 | I41: =IF(C41>0,(H41*C41/G41),"") -> 0 | J41: =IF(C41>0,(C41+I41),"") -> 1.5 | K41: =IF(D41>0,(D41*J41),"")
C42: 1.5 | D42: =IF(ISNA(VLOOKUP(B42,'Listado de Artículos'!$B$16:$F$1328,5,0)),0,(VLOOKUP(B42,'Listado de Artículos'!$B$16:$F$1328,5,0))) -> 0 | E42: 1 | F42: 1 | G42: =IF(E42>0,(F42/E42),"") -> 1 | H42: =IF(E42>0,(100%-G42),"") -> 0 | I42: =IF(C42>0,(H42*C42/G42),"") -> 0 | J42: =IF(C42>0,(C42+I42),"") -> 1.5 | K42: =IF(D42>0,(D42*J42),"")
C43: 0.025 | D43: =IF(ISNA(VLOOKUP(B43,'Listado de Artículos'!$B$16:$F$1328,5,0)),0,(VLOOKUP(B43,'Listado de Artículos'!$B$16:$F$1328,5,0))) -> 0 | E43: 1 | F43: 1 | G43: =IF(E43>0,(F43/E43),"") -> 1 | H43: =IF(E43>0,(100%-G43),"") -> 0 | I43: =IF(C43>0,(H43*C43/G43),"") -> 0 | J43: =IF(C43>0,(C43+I43),"") -> 0.025 | K43: =IF(D43>0,(D43*J43),"")
C44: 0.25 | D44: =IF(ISNA(VLOOKUP(B44,'Listado de Artículos'!$B$16:$F$1328,5,0)),0,(VLOOKUP(B44,'Listado de Artículos'!$B$16:$F$1328,5,0))) -> 0 | E44: 1 | F44: 1 | G44: =IF(E44>0,(F44/E44),"") -> 1 | H44: =IF(E44>0,(100%-G44),"") -> 0 | I44: =IF(C44>0,(H44*C44/G44),"") -> 0 | J44: =IF(C44>0,(C44+I44),"") -> 0.25 | K44: =IF(D44>0,(D44*J44),"")
C45: 0.05 | D45: =IF(ISNA(VLOOKUP(B45,'Listado de Artículos'!$B$16:$F$1328,5,0)),0,(VLOOKUP(B45,'Listado de Artículos'!$B$16:$F$1328,5,0))) -> 0 | E45: 1 | F45: 1 | G45: =IF(E45>0,(F45/E45),"") -> 1 | H45: =IF(E45>0,(100%-G45),"") -> 0 | I45: =IF(C45>0,(H45*C45/G45),"") -> 0 | J45: =IF(C45>0,(C45+I45),"") -> 0.05 | K45: =IF(D45>0,(D45*J45),"")
C46: 0.01 | D46: =IF(ISNA(VLOOKUP(B46,'Listado de Artículos'!$B$16:$F$1328,5,0)),0,(VLOOKUP(B46,'Listado de Artículos'!$B$16:$F$1328,5,0))) -> 0 | E46: 1 | F46: 1 | G46: =IF(E46>0,(F46/E46),"") -> 1 | H46: =IF(E46>0,(100%-G46),"") -> 0 | I46: =IF(C46>0,(H46*C46/G46),"") -> 0 | J46: =IF(C46>0,(C46+I46),"") -> 0.01 | K46: =IF(D46>0,(D46*J46),"")
C47: 0.06 | D47: =IF(ISNA(VLOOKUP(B47,'Listado de Artículos'!$B$16:$F$1328,5,0)),0,(VLOOKUP(B47,'Listado de Artículos'!$B$16:$F$1328,5,0))) -> 0 | E47: 1 | F47: 1 | G47: =IF(E47>0,(F47/E47),"") -> 1 | H47: =IF(E47>0,(100%-G47),"") -> 0 | I47: =IF(C47>0,(H47*C47/G47),"") -> 0 | J47: =IF(C47>0,(C47+I47),"") -> 0.06 | K47: =IF(D47>0,(D47*J47),"")
C48: 0.05 | D48: =IF(ISNA(VLOOKUP(B48,'Listado de Artículos'!$B$16:$F$1328,5,0)),0,(VLOOKUP(B48,'Listado de Artículos'!$B$16:$F$1328,5,0))) -> 0 | E48: 1 | F48: 1 | G48: =IF(E48>0,(F48/E48),"") -> 1 | H48: =IF(E48>0,(100%-G48),"") -> 0 | I48: =IF(C48>0,(H48*C48/G48),"") -> 0 | J48: =IF(C48>0,(C48+I48),"") -> 0.05 | K48: =IF(D48>0,(D48*J48),"")
A50: M.P

Sheet M.P MENU BBQ.
C3: MENU BBQ MAS BORONAT
C4: FICHA TÉCNICA PLATO
C7: ARTÍCULO | D7: TABLA DE QUESOS Y EMBUTIDOS.
C8: TAPA | D8: ELABORADOS.
C9: unid. | D9: 1 | E9: Coste TOTAL | G9: =SUM(K12:K19) -> 0.4142 | H9: Coste KG: | J9: =G9/D9 -> 0.4142
B11: ARTICULO | C11: KG | D11: €/UN | E11: BRUTO | F11: NETO | G11: %NETO | H11: %DESP | I11: DESP | J11: SUCIO | K11: € / RACION
B12: Queso Garrotxa Cabra. Bauma. | C12: 0.015 | D12: =IF(ISNA(VLOOKUP(B12,'Listado de Artículos'!$B$16:$F$1328,5,0)),0,(VLOOKUP(B12,'Listado de Artículos'!$B$16:$F$1328,5,0))) -> 0.01 | E12: 1 | F12: 1 | G12: =IF(E12>0,(F12/E12),"") -> 1 | H12: =IF(E12>0,(100%-G12),"") -> 0 | I12: =IF(C12>0,(H12*C12/G12),"") -> 0 | J12: =IF(C12>0,(C12+I12),"") -> 0.015 | K12: =IF(D12>0,(D12*J12),"") -> 0.00015
B13: Queso Serrat Cruda de oveja. | C13: 0.005 | D13: =IF(ISNA(VLOOKUP(B13,'Listado de Artículos'!$B$16:$F$1328,5,0)),0,(VLOOKUP(B13,'Listado de Artículos'!$B$16:$F$1328,5,0))) -> 15.75 | E13: 1 | F13: 1 | G13: =IF(E13>0,(F13/E13),"") -> 1 | H13: =IF(E13>0,(100%-G13),"") -> 0 | I13: =IF(C13>0,(H13*C13/G13),"") -> 0 | J13: =IF(C13>0,(C13+I13),"") -> 0.005 | K13: =IF(D13>0,(D13*J13),"") -> 0.07875
B14: Queso Azul Blau Cereta. Moli de ger. | C14: 0.005 | D14: =IF(ISNA(VLOOKUP(B14,'Listado de Artículos'!$B$16:$F$1328,5,0)),0,(VLOOKUP(B14,'Listado de Artículos'!$B$16:$F$1328,5,0))) -> 2.95 | E14: 1 | F14: 1 | G14: =IF(E14>0,(F14/E14),"") -> 1 | H14: =IF(E14>0,(100%-G14),"") -> 0 | I14: =IF(C14>0,(H14*C14/G14),"") -> 0 | J14: =IF(C14>0,(C14+I14),"") -> 0.005 | K14: =IF(D14>0,(D14*J14),"") -> 0.01475
B15: Queso Altejo moli de ger Vaca. | C15: 0.01 | D15: =IF(ISNA(VLOOKUP(B15,'Listado de Artículos'!$B$16:$F$1328,5,0)),0,(VLOOKUP(B15,'Listado de Artículos'!$B$16:$F$1328,5,0))) -> 0.03 | E15: 1 | F15: 1 | G15: =IF(E15>0,(F15/E15),"") -> 1 | H15: =IF(E15>0,(100%-G15),"") -> 0 | I15: =IF(C15>0,(H15*C15/G15),"") -> 0 | J15: =IF(C15>0,(C15+I15),"") -> 0.01 | K15: =IF(D15>0,(D15*J15),"") -> 0.0003
B16: Salchichon iberico. | C16: 0.005 | D16: =IF(ISNA(VLOOKUP(B16,'Listado de Artículos'!$B$16:$F$1328,5,0)),0,(VLOOKUP(B16,'Listado de Artículos'!$B$16:$F$1328,5,0))) -> 13.54 | E16: 1 | F16: 1 | G16: =IF(E16>0,(F16/E16),"") -> 1 | H16: =IF(E16>0,(100%-G16),"") -> 0 | I16: =IF(C16>0,(H16*C16/G16),"") -> 0 | J16: =IF(C16>0,(C16+I16),"") -> 0.005 | K16: =IF(D16>0,(D16*J16),"") -> 0.0677
B17: Lomo embuchado blanco. | C17: 0.005 | D17: =IF(ISNA(VLOOKUP(B17,'Listado de Artículos'!$B$16:$F$1328,5,0)),0,(VLOOKUP(B17,'Listado de Artículos'!$B$16:$F$1328,5,0))) -> 7.41 | E17: 1 | F17: 1 | G17: =IF(E17>0,(F17/E17),"") -> 1 | H17: =IF(E17>0,(100%-G17),"") -> 0 | I17: =IF(C17>0,(H17*C17/G17),"") -> 0 | J17: =IF(C17>0,(C17+I17),"") -> 0.005 | K17: =IF(D17>0,(D17*J17),"") -> 0.03705
B18: Paleta iberico cebo. | C18: 0.01 | D18: =IF(ISNA(VLOOKUP(B18,'Listado de Artículos'!$B$16:$F$1328,5,0)),0,(VLOOKUP(B18,'Listado de Artículos'!$B$16:$F$1328,5,0))) -> 15.8 | E18: 1 | F18: 1 | G18: =IF(E18>0,(F18/E18),"") -> 1 | H18: =IF(E18>0,(100%-G18),"") -> 0 | I18: =IF(C18>0,(H18*C18/G18),"") -> 0 | J18: =IF(C18>0,(C18+I18),"") -> 0.01 | K18: =IF(D18>0,(D18*J18),"") -> 0.158
B19: Fuet tradicional precio kg* calçotada. | C19: 0.005 | D19: =IF(ISNA(VLOOKUP(B19,'Listado de Artículos'!$B$16:$F$1328,5,0)),0,(VLOOKUP(B19,'Listado de Artículos'!$B$16:$F$1328,5,0))) -> 11.5 | E19: 1 | F19: 1 | G19: =IF(E19>0,(F19/E19),"") -> 1 | H19: =IF(E19>0,(100%-G19),"") -> 0 | I19: =IF(C19>0,(H19*C19/G19),"") -> 0 | J19: =IF(C19>0,(C19+I19),"") -> 0.005 | K19: =IF(D19>0,(D19*J19),"") -> 0.0575
C20: 0
C24: MENU BBQ MAS BORONAT
C25: FICHA TÉCNICA PLATO
C28: ARTÍCULO | D28: Patatas bravas.
C29: TAPA | D29: ELABORADOS. | H29: COSTE UNID.
C30: PAX | D30: 1 | E30: Coste TOTAL | G30: =SUM(K33:K34) -> 0.31997222 | H30: Coste unid: | J30: =G30/D30 -> 0.31997222
B32: ARTICULO | C32: KG | D32: €/UN | E32: BRUTO | F32: NETO | G32: %NETO | H32: %DESP | I32: DESP | J32: SUCIO | K32: € / RACION
B33: Patata Monalisa. | C33: 0.1 | D33: =IF(ISNA(VLOOKUP(B33,'Listado de Artículos'!$B$16:$F$1328,5,0)),0,(VLOOKUP(B33,'Listado de Artículos'!$B$16:$F$1328,5,0))) -> 2 | E33: 1 | F33: 0.9 | G33: =IF(E33>0,(F33/E33),"") -> 0.9 | H33: =IF(E33>0,(100%-G33),"") -> 0.1 | I33: =IF(C33>0,(H33*C33/G33),"") -> 0.011111111 | J33: =IF(C33>0,(C33+I33),"") -> 0.11111111 | K33: =IF(D33>0,(D33*J33),"") -> 0.22222222
B34: Salsa brava Mas Boronat | C34: 0.025 | D34: =IF(ISNA(VLOOKUP(B34,'Listado de Artículos'!$B$16:$F$1328,5,0)),0,(VLOOKUP(B34,'Listado de Artículos'!$B$16:$F$1328,5,0))) -> 3.91 | E34: 1 | F34: 1 | G34: =IF(E34>0,(F34/E34),"") -> 1 | H34: =IF(E34>0,(100%-G34),"") -> 0 | I34: =IF(C34>0,(H34*C34/G34),"") -> 0 | J34: =IF(C34>0,(C34+I34),"") -> 0.025 | K34: =IF(D34>0,(D34*J34),"") -> 0.09775
C37: MENU BBQ MAS BORONAT
C38: FICHA TÉCNICA PLATO
C41: ARTÍCULO | D41: salsa brava.
C42: TAPA | H42: PRECIO DE VENTA P.V.P
C43: unid. | D43: 0.42 | E43: Coste TOTAL | G43: =SUM(K46:K52) -> 6.6794 | H43: Coste kg: | J43: =G43/D43 -> 15.903333
B45: ARTICULO | C45: KG | D45: €/UN | E45: BRUTO | F45: NETO | G45: %NETO | H45: %DESP | I45: DESP | J45: SUCIO | K45: € / RACION
B46: Salsa Brava. bote de 1,850. precio bote 5,20€. Coosur. | C46: 1 | D46: =IF(ISNA(VLOOKUP(B46,'Listado de Artículos'!$B$16:$F$1328,5,0)),0,(VLOOKUP(B46,'Listado de Artículos'!$B$16:$F$1328,5,0))) -> 1.55 | E46: 1 | F46: 1 | G46: =IF(E46>0,(F46/E46),"") -> 1 | H46: =IF(E46>0,(100%-G46),"") -> 0 | I46: =IF(C46>0,(H46*C46/G46),"") -> 0 | J46: =IF(C46>0,(C46+I46),"") -> 1 | K46: =IF(D46>0,(D46*J46),"") -> 1.55
B47: Salsa Allioli. natural. bote de 1 lt. | C47: 0.016 | D47: =IF(ISNA(VLOOKUP(B47,'Listado de Artículos'!$B$16:$F$1328,5,0)),0,(VLOOKUP(B47,'Listado de Artículos'!$B$16:$F$1328,5,0))) -> 3.85 | E47: 1 | F47: 1 | G47: =IF(E47>0,(F47/E47),"") -> 1 | H47: =IF(E47>0,(100%-G47),"") -> 0 | I47: =IF(C47>0,(H47*C47/G47),"") -> 0 | J47: =IF(C47>0,(C47+I47),"") -> 0.016 | K47: =IF(D47>0,(D47*J47),"") -> 0.0616
B48: PIMENTON DULCE DE LA VERA | C48: 0.04 | D48: =IF(ISNA(VLOOKUP(B48,'Listado de Artículos'!$B$16:$F$1328,5,0)),0,(VLOOKUP(B48,'Listado de Artículos'!$B$16:$F$1328,5,0))) -> 23 | E48: 1 | F48: 1 | G48: =IF(E48>0,(F48/E48),"") -> 1 | H48: =IF(E48>0,(100%-G48),"") -> 0 | I48: =IF(C48>0,(H48*C48/G48),"") -> 0 | J48: =IF(C48>0,(C48+I48),"") -> 0.04 | K48: =IF(D48>0,(D48*J48),"") -> 0.92
B49: Mayonesa. bote 750 ml. MAKRO. | C49: 0.04 | D49: =IF(ISNA(VLOOKUP(B49,'Listado de Artículos'!$B$16:$F$1328,5,0)),0,(VLOOKUP(B49,'Listado de Artículos'!$B$16:$F$1328,5,0))) -> 1.05 | E49: 1 | F49: 1 | G49: =IF(E49>0,(F49/E49),"") -> 1 | H49: =IF(E49>0,(100%-G49),"") -> 0 | I49: =IF(C49>0,(H49*C49/G49),"") -> 0 | J49: =IF(C49>0,(C49+I49),"") -> 0.04 | K49: =IF(D49>0,(D49*J49),"") -> 0.042
B50: Curcuma. en povo. MAKRO. | C50: 0.14 | D50: =IF(ISNA(VLOOKUP(B50,'Listado de Artículos'!$B$16:$F$1328,5,0)),0,(VLOOKUP(B50,'Listado de Artículos'!$B$16:$F$1328,5,0))) -> 11.29 | E50: 1 | F50: 1 | G50: =IF(E50>0,(F50/E50),"") -> 1 | H50: =IF(E50>0,(100%-G50),"") -> 0 | I50: =IF(C50>0,(H50*C50/G50),"") -> 0 | J50: =IF(C50>0,(C50+I50),"") -> 0.14 | K50: =IF(D50>0,(D50*J50),"") -> 1.5806
B51: Curry polvo. | C51: 0.04 | D51: =IF(ISNA(VLOOKUP(B51,'Listado de Artículos'!$B$16:$F$1328,5,0)),0,(VLOOKUP(B51,'Listado de Artículos'!$B$16:$F$1328,5,0))) -> 17.63 | E51: 1 | F51: 1 | G51: =IF(E51>0,(F51/E51),"") -> 1 | H51: =IF(E51>0,(100%-G51),"") -> 0 | I51: =IF(C51>0,(H51*C51/G51),"") -> 0 | J51: =IF(C51>0,(C51+I51),"") -> 0.04 | K51: =IF(D51>0,(D51*J51),"") -> 0.7052
B52: Huevos "L" Granja Vidal, pqt de 6 unid: 1,60€ | C52: 7 | D52: =IF(ISNA(VLOOKUP(B52,'Listado de Artículos'!$B$16:$F$1328,5,0)),0,(VLOOKUP(B52,'Listado de Artículos'!$B$16:$F$1328,5,0))) -> 0.26 | E52: 1 | F52: 1 | G52: =IF(E52>0,(F52/E52),"") -> 1 | H52: =IF(E52>0,(100%-G52),"") -> 0 | I52: =IF(C52>0,(H52*C52/G52),"") -> 0 | J52: =IF(C52>0,(C52+I52),"") -> 7 | K52: =IF(D52>0,(D52*J52),"") -> 1.82
C55: CALÇOTADA MAS BORONAT
C56: FICHA TÉCNICA PLATO
C59: ARTÍCULO | D59: Crema Catalana quemada con carquiñoli.
C60: TAPA | D60: ELABORADOS.
C61: unid. | D61: 1 | E61: Coste TOTAL | G61: =SUM(K64:K66) -> 0.7621 | H61: Coste UNID: | J61: =G61/D61 -> 0.7621
B63: ARTICULO | C63: KG | D63: €/UN | E63: BRUTO | F63: NETO | G63: %NETO | H63: %DESP | I63: DESP | J63: SUCIO | K63: € / RACION
B64: Crema Catalana. | C64: 1 | D64: =IF(ISNA(VLOOKUP(B64,'Listado de Artículos'!$B$16:$F$1328,5,0)),0,(VLOOKUP(B64,'Listado de Artículos'!$B$16:$F$1328,5,0))) -> 0.5 | E64: 1 | F64: 1 | G64: =IF(E64>0,(F64/E64),"") -> 1 | H64: =IF(E64>0,(100%-G64),"") -> 0 | I64: =IF(C64>0,(H64*C64/G64),"") -> 0 | J64: =IF(C64>0,(C64+I64),"") -> 1 | K64: =IF(D64>0,(D64*J64),"") -> 0.5
B65: AZUCAR | C65: 0.025 | D65: =IF(ISNA(VLOOKUP(B65,'Listado de Artículos'!$B$16:$F$1328,5,0)),0,(VLOOKUP(B65,'Listado de Artículos'!$B$16:$F$1328,5,0))) -> 0.82 | E65: 1 | F65: 1 | G65: =IF(E65>0,(F65/E65),"") -> 1 | H65: =IF(E65>0,(100%-G65),"") -> 0 | I65: =IF(C65>0,(H65*C65/G65),"") -> 0 | J65: =IF(C65>0,(C65+I65),"") -> 0.025 | K65: =IF(D65>0,(D65*J65),"") -> 0.0205
B66: Carquiñolis. 200 gr. 3,75€ pqt | C66: 0.01 | D66: =IF(ISNA(VLOOKUP(B66,'Listado de Artículos'!$B$16:$F$1328,5,0)),0,(VLOOKUP(B66,'Listado de Artículos'!$B$16:$F$1328,5,0))) -> 24.16 | E66: 1 | F66: 1 | G66: =IF(E66>0,(F66/E66),"") -> 1 | H66: =IF(E66>0,(100%-G66),"") -> 0 | I66: =IF(C66>0,(H66*C66/G66),"") -> 0 | J66: =IF(C66>0,(C66+I66),"") -> 0.01 | K66: =IF(D66>0,(D66*J66),"") -> 0.2416
C70: MENU BBQ MAS BORONAT
C71: FICHA TÉCNICA PLATO
C74: ARTÍCULO | D74: Parrilada de verduras.
C75: TAPA | H75: PRECIO DE VENTA P.V.P
C76: unid. | D76: 1 | E76: Coste TOTAL | G76: =SUM(K79:K86) -> 1.8449563 | H76: Coste kg: | J76: =G76/D76 -> 1.8449563
B78: ARTICULO | C78: KG | D78: €/UN | E78: BRUTO | F78: NETO | G78: %NETO | H78: %DESP | I78: DESP | J78: SUCIO | K78: € / RACION
B79: Pimiento amarillo. | C79: 0.025 | D79: =IF(ISNA(VLOOKUP(B79,'Listado de Artículos'!$B$16:$F$1328,5,0)),0,(VLOOKUP(B79,'Listado de Artículos'!$B$16:$F$1328,5,0))) -> 0.4 | E79: 1 | F79: 1 | G79: =IF(E79>0,(F79/E79),"") -> 1 | H79: =IF(E79>0,(100%-G79),"") -> 0 | I79: =IF(C79>0,(H79*C79/G79),"") -> 0 | J79: =IF(C79>0,(C79+I79),"") -> 0.025 | K79: =IF(D79>0,(D79*J79),"") -> 0.01
B80: Pimiento rojo | C80: 0.025 | D80: =IF(ISNA(VLOOKUP(B80,'Listado de Artículos'!$B$16:$F$1328,5,0)),0,(VLOOKUP(B80,'Listado de Artículos'!$B$16:$F$1328,5,0))) -> 15.25 | E80: 1 | F80: 1 | G80: =IF(E80>0,(F80/E80),"") -> 1 | H80: =IF(E80>0,(100%-G80),"") -> 0 | I80: =IF(C80>0,(H80*C80/G80),"") -> 0 | J80: =IF(C80>0,(C80+I80),"") -> 0.025 | K80: =IF(D80>0,(D80*J80),"") -> 0.38125
B81: Pimiento verde. | C81: 0.025 | D81: =IF(ISNA(VLOOKUP(B81,'Listado de Artículos'!$B$16:$F$1328,5,0)),0,(VLOOKUP(B81,'Listado de Artículos'!$B$16:$F$1328,5,0))) -> 5.7 | E81: 1 | F81: 0.9 | G81: =IF(E81>0,(F81/E81),"") -> 0.9 | H81: =IF(E81>0,(100%-G81),"") -> 0.1 | I81: =IF(C81>0,(H81*C81/G81),"") -> 0.0027777778 | J81: =IF(C81>0,(C81+I81),"") -> 0.027777778 | K81: =IF(D81>0,(D81*J81),"") -> 0.15833333
B82: Berengena | C82: 0.025 | D82: =IF(ISNA(VLOOKUP(B82,'Listado de Artículos'!$B$16:$F$1328,5,0)),0,(VLOOKUP(B82,'Listado de Artículos'!$B$16:$F$1328,5,0))) -> 2.5 | E82: 1 | F82: 0.9 | G82: =IF(E82>0,(F82/E82),"") -> 0.9 | H82: =IF(E82>0,(100%-G82),"") -> 0.1 | I82: =IF(C82>0,(H82*C82/G82),"") -> 0.0027777778 | J82: =IF(C82>0,(C82+I82),"") -> 0.027777778 | K82: =IF(D82>0,(D82*J82),"") -> 0.069444444
B83: Calabacin. makro. | C83: 0.3 | D83: =IF(ISNA(VLOOKUP(B83,'Listado de Artículos'!$B$16:$F$1328,5,0)),0,(VLOOKUP(B83,'Listado de Artículos'!$B$16:$F$1328,5,0))) -> 1.79 | E83: 1 | F83: 1 | G83: =IF(E83>0,(F83/E83),"") -> 1 | H83: =IF(E83>0,(100%-G83),"") -> 0 | I83: =IF(C83>0,(H83*C83/G83),"") -> 0 | J83: =IF(C83>0,(C83+I83),"") -> 0.3 | K83: =IF(D83>0,(D83*J83),"") -> 0.537
B84: Esparrago verde triguero. manojo 400 gr.5,85€ | C84: 0.015 | D84: =IF(ISNA(VLOOKUP(B84,'Listado de Artículos'!$B$16:$F$1328,5,0)),0,(VLOOKUP(B84,'Listado de Artículos'!$B$16:$F$1328,5,0))) -> 4.85 | E84: 1 | F84: 0.7 | G84: =IF(E84>0,(F84/E84),"") -> 0.7 | H84: =IF(E84>0,(100%-G84),"") -> 0.3 | I84: =IF(C84>0,(H84*C84/G84),"") -> 0.0064285714 | J84: =IF(C84>0,(C84+I84),"") -> 0.021428571 | K84: =IF(D84>0,(D84*J84),"") -> 0.10392857
B85: Zanahorias. | C85: 0.02 | D85: =IF(ISNA(VLOOKUP(B85,'Listado de Artículos'!$B$16:$F$1328,5,0)),0,(VLOOKUP(B85,'Listado de Artículos'!$B$16:$F$1328,5,0))) -> 4.25 | E85: 1 | F85: 1 | G85: =IF(E85>0,(F85/E85),"") -> 1 | H85: =IF(E85>0,(100%-G85),"") -> 0 | I85: =IF(C85>0,(H85*C85/G85),"") -> 0 | J85: =IF(C85>0,(C85+I85),"") -> 0.02 | K85: =IF(D85>0,(D85*J85),"") -> 0.085
B86: Alcachofas. | C86: 0.04 | D86: =IF(ISNA(VLOOKUP(B86,'Listado de Artículos'!$B$16:$F$1328,5,0)),0,(VLOOKUP(B86,'Listado de Artículos'!$B$16:$F$1328,5,0))) -> 12.5 | E86: 1 | F86: 1 | G86: =IF(E86>0,(F86/E86),"") -> 1 | H86: =IF(E86>0,(100%-G86),"") -> 0 | I86: =IF(C86>0,(H86*C86/G86),"") -> 0 | J86: =IF(C86>0,(C86+I86),"") -> 0.04 | K86: =IF(D86>0,(D86*J86),"") -> 0.5

Sheet MENU BBQ
A2: MENU CALÇOTADA CARTA. 15-12-25
A4: A COMPARTIR | B4: P.V.P | C4: NETO | D4: COSTO | E4: FOOD COST
A5: EN MESA O COCTEL | B5: GR O KG. | C5: PRECIO KG | D5: EUROS/RACION.
A6: Tabla de embutidos y quesos variados. | B6: 1 | C6: =IF(ISNA(VLOOKUP(A6,'Listado de Artículos'!$B$16:$F$1328,5,0)),0,(VLOOKUP(A6,'Listado de Artículos'!$B$16:$F$1328,5,0))) -> 6.65 | D6: =B6*C6 -> 6.65
A7: Patatas Bravas. menu BBQ. Precio pax. | B7: 1 | C7: =IF(ISNA(VLOOKUP(A7,'Listado de Artículos'!$B$16:$F$1328,5,0)),0,(VLOOKUP(A7,'Listado de Artículos'!$B$16:$F$1328,5,0))) -> 5.27 | D7: =B7*C7 -> 5.27
A8: Ensalada para calçotada terminada lechuga de pages. | B8: 1 | C8: =IF(ISNA(VLOOKUP(A8,'Listado de Artículos'!$B$16:$F$1328,5,0)),0,(VLOOKUP(A8,'Listado de Artículos'!$B$16:$F$1328,5,0))) -> 0.7 | D8: =B8*C8 -> 0.7
A9: Pimiento del padron. | B9: 0.075 | C9: =IF(ISNA(VLOOKUP(A9,'Listado de Artículos'!$B$16:$F$1328,5,0)),0,(VLOOKUP(A9,'Listado de Artículos'!$B$16:$F$1328,5,0))) -> 6.9 | D9: =B9*C9 -> 0.5175
A10: MENU CALÇOTADA BOTIFARRA MONGETES BLANCAS | B10: 1 | C10: =IF(ISNA(VLOOKUP(A10,'Listado de Artículos'!$B$16:$F$1328,5,0)),0,(VLOOKUP(A10,'Listado de Artículos'!$B$16:$F$1328,5,0))) -> 0.84 | D10: =B10*C10 -> 0.84
A11: Pollo muslo fresco. | B11: 0.15 | C11: =IF(ISNA(VLOOKUP(A11,'Listado de Artículos'!$B$16:$F$1328,5,0)),0,(VLOOKUP(A11,'Listado de Artículos'!$B$16:$F$1328,5,0))) -> 2.88 | D11: =B11*C11 -> 0.432
A12: Butifarra negra* calçotada racionada a 70 gr. | B12: 0.07 | C12: =IF(ISNA(VLOOKUP(A12,'Listado de Artículos'!$B$16:$F$1328,5,0)),0,(VLOOKUP(A12,'Listado de Artículos'!$B$16:$F$1328,5,0))) -> 7.6 | D12: =B12*C12 -> 0.532
B13: 0.09 | C13: =IF(ISNA(VLOOKUP(A13,'Listado de Artículos'!$B$16:$F$1328,5,0)),0,(VLOOKUP(A13,'Listado de Artículos'!$B$16:$F$1328,5,0))) -> 0 | D13: =B13*C13 -> 0
A14: Salsa Allioli. natural. bote de 1 lt. | B14: 0.03 | C14: =IF(ISNA(VLOOKUP(A14,'Listado de Artículos'!$B$16:$F$1328,5,0)),0,(VLOOKUP(A14,'Listado de Artículos'!$B$16:$F$1328,5,0))) -> 3.85 | D14: =B14*C14 -> 0.1155
A15: MENU CALÇOTADA. CESTA DE PAN, TOMATE Y AJO. | B15: 1 | C15: =IF(ISNA(VLOOKUP(A15,'Listado de Artículos'!$B$16:$F$1328,5,0)),0,(VLOOKUP(A15,'Listado de Artículos'!$B$16:$F$1328,5,0))) -> 0.54 | D15: =B15*C15 -> 0.54
A16: MENU CALÇOTADA GUARNICION DE CORDERO. | B16: 1 | C16: =IF(ISNA(VLOOKUP(A16,'Listado de Artículos'!$B$16:$F$1328,5,0)),0,(VLOOKUP(A16,'Listado de Artículos'!$B$16:$F$1328,5,0))) -> 0.96 | D16: =B16*C16 -> 0.96
A17: POSTRES
A18: Crema Catalana. | B18: 0.5 | C18: =IF(ISNA(VLOOKUP(A18,'Listado de Artículos'!$B$16:$F$1328,5,0)),0,(VLOOKUP(A18,'Listado de Artículos'!$B$16:$F$1328,5,0))) -> 0.5 | D18: =B18*C18 -> 0.25
A19: Coulant de chocolate | B19: 0.5 | C19: =IF(ISNA(VLOOKUP(A19,'Listado de Artículos'!$B$16:$F$1328,5,0)),0,(VLOOKUP(A19,'Listado de Artículos'!$B$16:$F$1328,5,0))) -> 7.43 | D19: =B19*C19 -> 3.715
A20: PAN, AGUA, SELECCION DE VINOS Y CAFES
A21: CLOS PINELL TERRA TINTO ALTA | B21: 0.25 | C21: =IF(ISNA(VLOOKUP(A21,'Listado de Artículos'!$B$16:$F$1328,5,0)),0,(VLOOKUP(A21,'Listado de Artículos'!$B$16:$F$1328,5,0))) -> 0.9 | D21: =B21*C21 -> 0.225
A22: Agua Fon vella 1 LT Caja de 12 unid. | B22: 0.3 | C22: =IF(ISNA(VLOOKUP(A22,'Listado de Artículos'!$B$16:$F$1328,5,0)),0,(VLOOKUP(A22,'Listado de Artículos'!$B$16:$F$1328,5,0))) -> 0.8 | D22: =B22*C22 -> 0.24
A23: Cafe Natural. 1 kg. 120 cafes. 24,48€ .kg. 0,22 unid | D23: 0.22
A24: ESCANDALLO | B24: 35 | C24: =+B24-(B24*0.1) -> 31.5 | D24: =SUM(D6:D23) -> 21.207 | E24: =(D24*100/C24)/100 -> 0.6732381

Sheet Historial de Compras
A1: Fecha | B1: Artículo | C1: Proveedor | D1: Precio | E1: Cantidad | F1: Importe | G1: Nº Factura | H1: Observaciones
A2: 2026-07-05 12:05:56 | B2: Agua de jamaica | C2: M.P | D2: 0.1256 | H2: Precio anterior: 0.23
A3: 2026-07-05 12:59:23 | B3: prueba gpt | C3: la | D3: 0.333 | H3: Precio anterior: 0.222
